Workbook

Sheet Tax rules
B2: Income Tax Software 2019 - 20 ( Calculator )
B3: For update Income Tax software visit my website www.teacherNews.in
B4: Financial year 2019- 20 | Assessment Year 2020 -21
C5: Follow theTax Rules & Informations (where applicable). Following linked ready reaconer is for your reference.
B6: 1 | C6: New Tax Rates for Financial-Year 2019-20, Assessment Year 2020-2021
B7: 2 | C7: Some Exempted Receipts / Special allowances & Perquisite which are not chargable to tax
B8: 2 | C8: Some Exempted Income ( to be shown while Return filing)
C10: T A X R U L E S & O T H E R U S E F U L I N F O R M A T I O N S
B11: I | C11: HRA exemption
B12: II | C12: Transport allowance
B13: III | C13: Reimbursement of Medical bills
B14: IV | C14: u/s(5) LTA is exempt
B15: IV | C15: u/s 24 Exemption for interest on housing loan.
B16: V | C16: u/s 80CCE & 80CCD Maximum Exemption
B17: VI | C17: u/s 80 CCG Rajiv Gandhi Equity Savings Scheme
B18: VII | C18: u/s 80D Medical Insurance
B19: VIII | C19: u/s 80DD Deduction in respect of medical treatment of handicapped dependents
B20: IX | C20: u/s 80DDB Deduction in respect of medical treatment for specified ailments or diseases
B21: X | C21: u/s 80E Interest repayment on education loan
B22: XI | C22: u/s 80G Donations given for certain charities
... B25: XIV | C25: u/s 80TTA Deduction on interest on saving bank accounts.
C26: KNOW MORE about DEDUCTION under Section 80-C
B27: a | C27: Qualifying Investments u/s 80CCE
B28: b | C28: Provident Fund (PF) & Voluntary Provident Fund (VPF)
B29: c | C29: Life Insurance Premiums & Unit linked Insurance Plan (ULIP)
B30: d | C30: Public Provident Fund (PPF):
B31: e | C31: National Savings Certificate (NSC):
B32: f | C32: Home Loan Principal Repayment & Stamp Duty and Registration Charges for a home
B33: g | C33: Tuition fees for 2 children
B34: h | C34: Equity Linked Savings Scheme (ELSS)
B35: i | C35: 5-Yr bank fixed deposits (FDs) or 5-Yr post office time deposit (POTD)
B36: j | C36: Pension Funds or Pension Policies
B37: k | C37: Stamp Duty and Registration Charges for a home:
B38: l | C38: Infrastructure Bonds: NABARD rural bonds:
B39: m | C39: Senior Citizen Savings Scheme 2004 (SCSS)
B40: 6 | C40: I M P O R T A N T - A D V I S ES
C41: TAX RATES For Financial Year 2019-20 & Assesment Year 2020 -21
C42: For MALE/FEMALE ASSESSE
C43: Net Income Range Income Tax Rates
C44: Up to Rs.2,50,000 Nil
C45: 2,50,001 to Rs. 5,00,000 5% of Total Income (-) Rs.2,50,000
C46: Rs.5,00,001 to Rs. 10,00,000 Rs25,000+20% of Total Income(-)Rs. 5,00,000
C47: More than Rs10.00,000 Rs1,25,0,000+30% of Total Income(-)Rs10,00,000
C48: *Note- (u/s87A- A rebate upto Rs 12500/- for Taxble Income below Rs. 5,00,000 )
C49: For SENIOR CITIZEN ASSESSE (Above 60 Year ) attaining the age during the year
C50: Net Income Range Income Tax Rates
C51: Up to Rs 3,00,000 Nil
C52: Rs3,00,001 to 5,00,000 5% of Total Income(-) Rs.3,00,000
... C76: T A X R U L E S & O T H E R U S E F U L I N F O R M A T I O N S for
B77: I | C77: HRA exemption = Least of (40% (50% for metros) of Basic+DA or HRA or rent paid - 10% of Basic+DA)
B78: II | C78: Transport allowance is exempt up to Rs.800/- per month during the month. ( Expenditure incured for covering journey between office and residence .) For people having permanent physical disability, the exemption is 1,600/- per month
B79: III | C79: Reimbursement of Medical bills are exempt for self and dependent family, up to Rs.50,000/- per annum
B80: IV | C80: u/s(5) LTA is exempt to the tune of economy class Train/ Air /Recognised public Transport fare for the family to any destination in India, by the shortest route. LTA can be claimed twice in a block of 4 calendar years. The current block is from 01.01.2010 to 31.12.2013. For claim, it is must to provide originals tickets etc.
B81: IV(a) | C81: u/s 24 There is an Exemption for interest on housing loan.(for Self occupied Residence). If the loan was taken before Apr 1, 1999 exemption is limited to Rs30,000/- per year. If the loan was taken after Apr 1, 1999 exemption is limited to Rs 2,00,000/- per year if the house is self-occupied; There is no limit if the house is rented out This exemption is available on accrual basis, which means if interest has accrued, you can claim exemption, irrespective of whether you've paid it or not..
B82: (b) | C82: If you have rented out your house, enter the total income / loss from the house (after deducting property tax and standard maintenance expenses).
B83: V | C83: u/s 80CCE- Maximum Exemption up to Rs.150000/- Investments up to Rs.1.5 lac in PF, VPF, PPF, Employee contribution in NPS,Insurance Premium, Housing loan principal repayment, NSC, ELSS, long term bank Fixed Deposit, Post Office Term Deposit, etc. are deductible from the taxable income. There is no limit on individual items, (for example) all 1 lac can be invested in NSC or PPF etc.
B84: VI | C84: u/s 80CCD -The Finance Act, 2011 provides that contribution made by the Central Government or any other employer to NPS (up to 10 per cent of the salary of the employee in the previous year)shall be excluded while computing the limit of Rs1,50,000.The contribution by the employee to the NPS will be subject to the limit of Rs1,00,000.
B85: VII | C85: u/s 80CCG - Rajiv Gandhi Equity Savings Scheme is a new exemption available for investment in stock markets (direct equity). Avaialble only for those with gross income less than 12 lacs and only for first time investors in stock market. Exemption available at 50% ( Rs.25,000/)of investment subject to maximum of Rs.50,000/- invested. Investments are locked-in for three years
B86: VIII | C86: u/s 80D Medical Insurance Premium (such as Mediclaim & Critical illness Cover)& Health Check up Upto Rs 5000, premium is exempt up to Rs 30,000/ per year (Rs.25,000/- for self,spouse and children ) (Rs 15000/- for Parents. If the premium includes for a dependent who is (Senior Citizen) above 60 years of age, an extra Rs 5,000//- can be claimed.
B87: IX | C87: u/s 80DD Deduction in respect of medical treatment of handicapped dependents is limited to Rs.75,000/- per year if the disability is less than 80% and Rs1,25,000/- per year if the disability is more than 80%
B88: X | C88: u/s 80DDB Deduction in respect of medical treatment for specified ailments or diseases for the assesse or dependent can be claimed up to Rs40,000/- per year. If the person being treated is a senior citizen, the exemption can go up toRs60,000/-. but any amount received under Medical Insurance Policy will be reduced from the amount of deduction allowed. The Diseases and ailments specified under rule 11DD are. (1)neurological diseases being demetia, dystonia musculorum deformans, motor neuron disease, ataxia, chorea, hemiballismus, aphasia and parkisons disease, (2) cancer, (3) AIDS, (4)Chronic renal failure, (5) hemophilia, and (6) thalassaemia.
... B93: XV | C93: u/s 80TTA introduced through Finance Act, 2012. Section 80TTA provides a deduction of up to Rs40,000 on your income from interest on saving bank accounts.
C94: KNOW MORE about DEDUCTION under Section 80-C and chapter VIA
C95: Section 80C of the Income Tax Act allows certain investments and expenditure to be deduct from total income. One must plan investments well and spread it out across the various instruments specified under this section to avail maximum tax benefit. There are no sub-limits and is irrespective of how much you earn and under which tax bracket you fall. Most of the Income Tax payee try to save tax by saving under Section 80C of the Income Tax Act. However, it is important to know the Section in total. so that one can make best use of the options available for deduction under income tax Act. One important point to note that one can not only save tax by undertaking the specified investments, but some expenditure which you normally incur can also give you the tax exemptions.
C96: Qualifying Investments u/s 80CCE are
B97: a | C97: Provident Fund (PF) & Voluntary Provident Fund (VPF) PF is automatically deducted from your salary. your contribution [12% of Basic] (i.e., employee’s contribution) is counted towards section 80C investments. You also have the option to contribute additional amounts through voluntary contributions (VPF). Current rate of interest is 8.5% per annum (p.a.) and is tax-free.
B98: b | C98: Life Insurance Premiums: Any amount that you pay towards life insurance premium in Life Insurance Corporation (LIC) or any other Insurance CO.for yourself, your spouse or your children can also be included in Section 80C deduction. If you are paying premium for more than one insurance policy, all the premiums will be included. also premium paid for ULIP will also be treated as Premium paid for Life Insurance Policies. Unit linked Insurance Plan : ULIP stands for Unit linked Saving Schemes. ULIPs cover Life insurance with benefits of equity investments.They have attracted the attention of investors and tax-savers not only because they help us save tax but they also perform well to give decent returns in the long-term. IMP : Total Amount Received at Maturity, Survival Benefits, , Withdrawl in Insurance Policies is Tax Free and fully exempteed u/s 10(10D).
B99: c | C99: Public Provident Fund (PPF): Among all the assured returns small saving schemes, Public Provident Fund (PPF) is one of the best. Current rate of interest is 8% tax-free and the normal maturity period is 15 years. Minimum amount of contribution is Rs500 and maximum is Rs1,50,000.(New Change) from Budget 2014
B100: d | C100: National Savings Certificate (NSC): National Savings Certificate (NSC) is a 5-Yr small savings instrument eligible for section 80C tax benefit. Rate of interest is 8.58% compounded half-yearly, i.e. If you invest Rs.100, it becomes Rs.150.90 after five years. The interest accrued every year is liable to tax (i.e. to be included in your taxable income) but the interest is also deemed to be reinvested and thus eligible for section 80C deduction.
B101: e | C101: Home Loan Principal Repayment & Stamp Duty and Registration Charges for a home Loan The Equated Monthly Installment (EMI) that you pay every month to repay your home loan consists of two components – Principal and Interest.The principal component of the EMI qualifies for deduction under Sec 80C. Even the interest component can save you significant income tax – but that would be under Section 24 of the Income Tax Act. The amount you pay as stamp duty when you buy a house, and the amount you pay for the registration of the documents of the house can be claimed as deduction under section 80C in the year of purchase of the house.
B102: f | C102: Tuition fees for 2 children Apart form the above major investments expenses for children’s education (Only Tution Fee (for which you need receipts)), can be claimed as deductions under Sec 80C.
B103: g | C103: Equity Linked Savings Scheme (ELSS): There are some mutual fund (MF) schemes specially created for offering you tax savings, and these are called Equity Linked Savings Scheme, or ELSS. The investments that you make in ELSS are eligible for deduction under Sec 80C.
B104: h | C104: 5-Yr bank fixed deposits (FDs): Tax-saving fixed deposits (FDs) of scheduled banks with tenure of 5 years are also entitled for section 80C deduction. 5-Yr post office time deposit (POTD) scheme: POTDs are similar to bank fixed deposits. Although available for varying time duration like one year, two year, three year and five year, only 5-Yr post-office time deposit (POTD) – which currently offers 7.5 per cent rate of interest –qualifies for tax saving under section 80C. Effective rate works out to be 7.71% per annum (p.a.) as the rate of interest is compounded quarterly but paid annually. The Interest is entirely taxable.
B105: i | C105: Pension Funds or Pension Policies – Section 80CCC: This section – Sec 80CCC – stipulates that an investment in pension funds is eligible for deduction from your income. Section 80CCC investment limit is clubbed with the limit of Section 80C – it means that the total deduction available for 80CCC and 80C is Rs 1.5 Lakh.This also means that your investment in pension funds upto Rs.1.5 Lakh can be claimed as deduction u/s 80CCC. However, as mentioned earlier, the total deduction u/s 80C and 80CCC can not exceed Rs.1.5 Lakh.
B106: j | C106: Infrastructure Bonds: These are also popularly called Infra Bonds. These are issued by infrastructure companies, and not the government. The amount that you invest in these bonds can also be included in Sec 80C deductions. NABARD rural bonds: There are two types of Bonds issued by NABARD (National Bank for Agriculture and Rural Development): NABARD Rural Bonds and Bhavishya Nirman Bonds (BNB). Out of these two, only NABARD Rural Bonds qualify under section 80C.
B107: k | C107: Senior Citizen Savings Scheme 2004 (SCSS): A recent addition to section 80C list, Senior Citizen Savings Scheme (SCSS) is the most lucrative scheme among all the small savings schemes but is meant only for senior citizens. Current rate of interest is 9% per annum payable quarterly. Please note that the interest is payable quarterly instead of compounded quarterly. Thus, unclaimed interest on these deposits won’t earn any further interest. Interest income is chargeable to tax.
C108: I M P O R T A N T - A D V I S ES
C109: Mostly people gives estimated declaration at year starting to minimise their Tax Liabilities but could not save up to last and face heavy burden in last months. Many of us start looking for investment avenues only in February or March, just before the Financial Year is getting over. This is a big mistake! One, you would end up investing your money without putting proper thought to it. And secondly, you would end up losing the interest / appreciation for the whole year. Instead, decide where you want to make the investments, and start investing right from the beginning of the financial year – from April. so it is advisable to save from start on monthly basis through Bank ECS as a SAP . This way, you would not only make informed decisions, but would also earn the interest for the full year from April to March.
C110: C A L L M E F O R P R E S E N T A T I O N : B. P. C H O U D A R Y P h : 9 8 1 1 3 0 2 4 9 7, 9 2 1 1 1 2 5 5 8 7 or M a i l
C111: TOP

Sheet DATA
X2: DA Arrears
B4: Mobile Income Tax Software | H4: Jul 2018 DA Arrears Online Calculator | M4: Jul 2018 DA Arrears Calculator | Q4: =IF(S11<5000,"You Need Not Submit Rent Receipt for this rent.",IF(AND(S11>5000,S11<8300)," You Should Submit Rent Receipt with Out Owner PAN Number.",IF(S11<83000," You Should Submit Rent Receipt with PAN No. of House Owner."))) -> You Should Submit Rent Receipt with PAN No. of House Owner. | X4: Jul 2018 DA Arrears Taken
X5: Jan 2019 DA Arrears Taken
X6: AAS Taken (07/2018 to 12/2020)
B7: C.Ramanjaneyulu Income Tax Software 2021-22 for AP Teachers & Employees | Y7: July 2018 DA Arrears | AB7: Jan 2019 DA Arrears
C9: Employee & DDO Details | J9: Select Regime | N9: Basic Pay & Benefits | S9: House Rent | X9: =AY144 -> 43282 | Y9: =AW144 -> 19500 | Z9: =IF(X9=AT$189,AT$194,BA144) -> 613
C10: Employee Name | E10: A.Nagesh | J10: Allowances Details | N10: Basic Pay January - 2021 | X10: =AY145 -> 43313 | Y10: =AW145 -> 20050 | Z10: =IF(X10=AT$189,AT$194,BA145) -> 631 | AN10: =(SUM(Z9:Z16)+SUM(AC15:AC16)) -> 6290 | AO10: =IF(CL$274=1,"( DA Arrears FY 2018-19 )","") -> ( DA Arrears FY 2018-19 )
C11: Designation | E11: Deputy Executive Engineer | J11: HRA on Mar - 2021 | N11: Increment Month | S11: 12000 | X11: =AY146 -> 43344 | Y11: =AW146 -> 20050 | Z11: =IF(X11=AT$189,AT$194,BA146) -> 631
C12: Employees PAN No. | J12: Change HRA | N12: AAS Increment | S12: Net Tax | X12: =AY147 -> 43374 | Y12: =AW147 -> 20050 | Z12: =IF(X12=AT$189,AT$194,BA147) -> 631
C13: School/Office | E13: Executive Engineer,TGP Division No.1 | J13: HM Allowance | N13: Promotion | S13: =IF('Annexure -I I'!J67='Annexure -I I'!Q69,"",CONCATENATE("Rs. ",'Annexure -I I'!L67)) -> Rs. 42996 | X13: =AY148 -> 43405 | Y13: =AW148 -> 20050 | Z13: =IF(X13=AT$189,AT$194,BA148) -> 631
C14: Working Place | E14: Velgode | J14: PH Allowance | N14: Surrender leave (2021-22) | S14: Total Saving | X14: =AY149 -> 43435 | Y14: =AW149 -> 20050 | Z14: =IF(X14=AT$189,AT$194,BA149) -> 631
C15: Mandal | E15: Velgode | J15: Edu. Concession | N15: Surrender Leave with Pay, DA, HRA | S15: ='Annexure -I I'!L46 -> 150000 | X15: =AY150 -> 43466 | Y15: =AW150 -> 20050 | Z15: =IF(X15=AT$189,AT$194,BA150) -> 631 | AB15: =AW150 -> 20050 | AC15: =IF(X15=AT$189,AT$197,BC150) -> 630
C16: District | E16: Kurnool | J16: Rented / Own House | N16: Half Pay Leave | X16: =AY151 -> 43497 | Y16: =AW151 -> 20050 | Z16: =IF(X16=AT$189,AT$194,BA151) -> 631 | AB16: =AW151 -> 20050 | AC16: =IF(X16=AT$189,AT$197,BC151) -> 630
C17: Vacation / Non Vacation | J17: Select PF/CPS | N17: Without DA in HRA Calculation | Q17: w | X17: =AY152 -> 43525 | Y17: =AW152 -> 20050 | Z17: =IF(X17=AT$189,AT$194,BA152) -> 631 | AB17: =AW152 -> 20050 | AC17: =IF(X17=AT$189,AT$197,BC152) -> 630
C18: Treasury Id No. | J18: Additional HRA | X18: =AY153 -> 43556 | Y18: =AW153 -> 20050 | Z18: =IF(X18=AT$189,AT$194,BA153) -> 631 | AB18: =AW153 -> 20050 | AC18: =IF(X18=AT$189,AT$197,BC153) -> 630
C19: DDO Name | E19: N.C.Subbarayudu | N19: Employee Salary Deductions | X19: =AY154 -> 43586 | Y19: =AW154 -> 20050 | Z19: =IF(X19=AT$189,AT$194,BA154) -> 631 | AB19: =AW154 -> 20050 | AC19: =IF(X19=AT$189,AT$197,BC154) -> 630
C20: Disignation | E20: Executive Engineer,TGP Division No.1 | J20: CCA Recived Monthly | N20: PF Monthly | P20: 7000 | Q20: PF Change | X20: =AY155 -> 43617 | Y20: =AW155 -> 20050 | Z20: =IF(X20=AT$189,AT$194,BA155) -> 631 | AB20: =AW155 -> 20050 | AC20: =IF(X20=AT$189,AT$197,BC155) -> 630
C21: DDO Office & Place | E21: Velgode | J21: SCA | N21: =IF(CL274=1,"APGLI Mothly ","TSGLI Mothly ") -> APGLI Mothly | P21: 2000 | Q21: =IF(CL274=1," APGLI Change","TSGLI Change") -> APGLI Change | X21: =AY156 -> 43647 | Y21: =AW156 -> 20050 | Z21: =IF(X21=AT$189,AT$194,BA156) -> 631 | AB21: =AW156 -> 20050 | AC21: =IF(X21=AT$189,AT$197,BC156) -> 630 | AN21: =SUM(Z17:Z28)+SUM(AC17:AC28) -> 15391 | AO21: ( DA Arrears FY 2019-20 )
C22: Mandal | E22: Velgode | J22: HRA Under Taking | N22: GIS Monthly | P22: 120 | Q22: GIS Change | X22: =AY157 -> 43678 | Y22: =AW157 -> 20640 | Z22: =IF(X22=AT$189,AT$194,BA157) -> 649 | AB22: =AW157 -> 20640 | AC22: =IF(X22=AT$189,AT$197,BC157) -> 649
C23: DDO PAN | E23: TAN | J23: PP/SP/Addl. Inc. | N23: PF/CPS No | Q23: =IF(CL274=1,"APGLI No","TSGLI No") -> APGLI No | X23: =AY158 -> 43709 | Y23: =AW158 -> 20640 | Z23: =IF(X23=AT$189,AT$194,BA158) -> 649 | AB23: =AW158 -> 20640 | AC23: =IF(X23=AT$189,AT$197,BC158) -> 649
J24: =IF(CL274=2,"TS Increment","") | N24: LIC Paid Monthly in Salary | Q24: LIC Change | X24: =AY159 -> 43739 | Y24: =AW159 -> 20640 | Z24: =IF(X24=AT$189,AT$194,BA159) -> 649 | AB24: =AW159 -> 20640 | AC24: =IF(X24=AT$189,AT$197,BC159) -> 649
C25: Savings | J25: Update IT Software Available at www.teacherNews.in | N25: EWF (March 2021) | P25: 50 | Q25: SWF (December 2021) | X25: =AY160 -> 43770 | Y25: =AW160 -> 20640 | Z25: =IF(X25=AT$189,AT$194,BA160) -> 649 | AB25: =AW160 -> 20640 | AC25: =IF(X25=AT$189,AT$197,BC160) -> 649
N26: Salary Health Insurance | Q26: If Change | X26: =AY161 -> 43800 | Y26: =AW161 -> 20640 | Z26: =IF(X26=AT$189,AT$194,BA161) -> 649 | AB26: =AW161 -> 20640 | AC26: =IF(X26=AT$189,AT$197,BC161) -> 649
X27: =AY162 -> 43831 | Y27: =AW162 -> 20640 | Z27: =IF(X27=AT$189,AT$194,BA162) -> 649 | AB27: =AW162 -> 20640 | AC27: =IF(X27=AT$189,AT$197,BC162) -> 649
N28: Advance Tax Paid | X28: =AY163 -> 43862 | Y28: =AW163 -> 20640 | Z28: =IF(X28=AT$189,AT$194,BA163) -> 649 | AB28: =AW163 -> 20640 | AC28: =IF(X28=AT$189,AT$197,BC163) -> 649
N29: 44256 | O29: 8000 | P29: 44378 | Q29: 8000 | S29: 44501 | T29: 8000 | X29: =AY164 -> 43891 | Y29: =AW164 -> 20640 | Z29: =IF(X29=AT$189,AT$194,BA164) -> 649 | AB29: =AW164 -> 20640 | AC29: =IF(X29=AT$189,AT$197,BC164) -> 649
N30: 44287 | O30: 8000 | P30: 44409 | Q30: 8000 | S30: 44531 | T30: 20000 | X30: =AY165 -> 43922 | Y30: =AW165 -> 20640 | Z30: =IF(X30=AT$189,AT$194,BA165) -> 649 | AB30: =AW165 -> 20640 | AC30: =IF(X30=AT$189,AT$197,BC165) -> 649
N31: 44317 | O31: 8000 | P31: 44440 | Q31: 8000 | S31: 44562 | X31: =AY166 -> 43952 | Y31: =AW166 -> 20640 | Z31: =IF(X31=AT$189,AT$194,BA166) -> 649 | AB31: =AW166 -> 20640 | AC31: =IF(X31=AT$189,AT$197,BC166) -> 649
C32: Tax Deductions | N32: 44348 | O32: 8000 | P32: 44470 | Q32: 8000 | S32: 44593 | X32: =AY167 -> 43983 | Y32: =AW167 -> 20640 | Z32: =IF(X32=AT$189,AT$194,BA167) -> 649 | AB32: =AW167 -> 20640 | AC32: =IF(X32=AT$189,AT$197,BC167) -> 649
X33: =AY168 -> 44013 | Y33: =AW168 -> 20640 | Z33: =IF(X33=AT$189,AT$194,BA168) -> 649 | AB33: =AW168 -> 20640 | AC33: =IF(X33=AT$189,AT$197,BC168) -> 649
C34: Deductions for disabled(blind,PH) person (40%) | X34: =AY169 -> 44044 | Y34: =AW169 -> 21230 | Z34: =IF(X34=AT$189,AT$194,BA169) -> 667 | AB34: =AW169 -> 21230 | AC34: =IF(X34=AT$189,AT$197,BC169) -> 668 | AN34: =SUM(Z29:Z38)+SUM(AC29:AC40) -> 14501 | AO34: ( DA Arrears FY 2020-21 )
X35: =AY170 -> 44075 | Y35: =AW170 -> 21230 | Z35: =IF(X35=AT$189,AT$194,BA170) -> 667 | AB35: =AW170 -> 21230 | AC35: =IF(X35=AT$189,AT$197,BC170) -> 668
X36: =AY171 -> 44105 | Y36: =AW171 -> 21230 | Z36: =IF(X36=AT$189,AT$194,BA171) -> 667 | AB36: =AW171 -> 21230 | AC36: =IF(X36=AT$189,AT$197,BC171) -> 668
C37: National Pension Scheme U/s 80CCD (1B) | N37: Loss or Income from House property select (U/s 24) | X37: =AY172 -> 44136 | Y37: =AW172 -> 21230 | Z37: =IF(X37=AT$189,AT$194,BA172) -> 667 | AB37: =AW172 -> 21230 | AC37: =IF(X37=AT$189,AT$197,BC172) -> 668
J38: Other Sources Income | N38: Rent received during the Year | X38: =AY173 -> 44166 | Y38: =AW173 -> 21230 | Z38: =IF(X38=AT$189,AT$194,BA173) -> 667 | AB38: =AW173 -> 21230 | AC38: =IF(X38=AT$189,AT$197,BC173) -> 668
N39: Muncipal Tax Paid | X39: =AY174 -> 44197 | Y39: =AW174 -> 21230 | AB39: =AW174 -> 21230 | AC39: =IF(X39=AT$189,AT$197,BC174) -> 668
C40: C.Ramanjaneyulu, S.A( P.S ) | N40: 30% of Income as Maintenance | Q40: =IF(DATA!BQ238=1,DATA!BM236,"") | X40: =AY175 -> 44228 | Y40: =AW175 -> 21230 | AB40: =AW175 -> 21230 | AC40: =IF(X40=AT$189,AT$197,BC175) -> 668
C41: Please Don't Call School Hours | G41: Contact : 9160840947 | N41: =BN239&" from Housing Property" -> Income from Housing Property | Q41: =BM239 | X41: =AY176 -> 44256 | Y41: =AW176 -> 21230 | AB41: =AW176 -> 21230 | AC41: =IF(X41=AT$189,AT$197,BC176) -> 668
X42: =AY177 -> 44287 | Y42: =AW177 -> 21230 | AB42: =AW176 -> 21230 | AC42: =IF(X42=AT$189,AT$197,BC177) -> 668
C43: DA & Other Arrears ( Exmption 10E) | N43: House Address for Rent Reciept | X43: =AY178 -> 44317 | Y43: =AW178 -> 21230 | AB43: =AW178 -> 21230 | AC43: =IF(X43=AT$189,AT$197,BC178) -> 668 | AN43: =SUM(AC41:AC44) -> 2672 | AO43: ( DA Arrears FY 2021-22 )
X44: =AY179 -> 44348 | Y44: =AW179 -> 21230 | AB44: =AW179 -> 21230 | AC44: =IF(X44=AT$189,AT$197,BC179) -> 668
C45: FY 2020-21 (DA Arrears) | H45: Taxble Income | N45: D.No. | Q45: 13-254/ A
C46: FY 2019-20 (DA Arrears) | H46: Taxble Income | N46: Street/Area | Q46: Near Bus Stand | AH46: Tax New Regime
C47: FY 2018-19 (DA Arrears ) | H47: Taxble Income | N47: Town/Village | Q47: Peapully | AH47: Tax Old Regime
C48: FY 2017-18 (Arrears) | H48: Taxble Income | N48: Mandal | Q48: Peapully
C49: FY 2016-17 (Arrears) | H49: Taxble Income | N49: District | Q49: Kurnool | AH49: 2
C50: FY 2015-16 (Arrears) | H50: Taxble Income | N50: Owner Name | O50: K Suresh | Q50: PAN No | S50: xxxxxxxxx
N51: =IF('Form 10E'!U61<=0," No Tax Relief ",CONCATENATE(" Congratulation ",E10," Garu Your Tax Relief Rs .")) -> No Tax Relief | S51: =IF('Form 10E'!U61=0,"",CONCATENATE("Rs. ",ROUND('Form 10E'!U61,0)))
N53: Update IT Software Available at www.teacherNews.in
C57: Every time work (Edit) with Copy Software Only from Orginal Software
C58: Download Update Income Tax Software at www.teachernews.in
C59: If You want to Update Softwares, Please Add My WhatsApp Number 8978531101 in Your WhatsApp Groups
BJ137: =IF(CD283=BJ$151,BN$151,IF(CD283=BJ$152,BN$152,IF(CD283=BJ$153,BN$153,0))) -> 0 | BK137: =IF(CD283=BJ$151,BO$151,IF(CD283=BJ$152,BO$152,IF(CD283=BJ$153,BO$153,0))) -> 0
BJ138: =IF(CD284=BJ$151,BN$151,IF(CD284=BJ$152,BN$152,IF(CD284=BJ$153,BN$153,0))) -> 0 | BK138: =IF(CD284=BJ$151,BO$151,IF(CD284=BJ$152,BO$152,IF(CD284=BJ$153,BO$153,0))) -> 0
BJ139: =IF(CD285=BJ$151,BN$151,IF(CD285=BJ$152,BN$152,IF(CD285=BJ$153,BN$153,0))) -> 0 | BK139: =IF(CD285=BJ$151,BO$151,IF(CD285=BJ$152,BO$152,IF(CD285=BJ$153,BO$153,0))) -> 0
BA140: =AZ141-1 -> 7 | BJ140: =IF(CD286=BJ$151,BN$151,IF(CD286=BJ$152,BN$152,IF(CD286=BJ$153,BN$153,0))) -> 0 | BK140: =IF(CD286=BJ$151,BO$151,IF(CD286=BJ$152,BO$152,IF(CD286=BJ$153,BO$153,0))) -> 0
AZ141: =IF(BD274=2,BD261,IF(BD275=2,BD262,IF(BD276=2,BD263,0))) -> 8 | BA141: =IF(AZ141=14,2,IF(AZ141=13,1,BA140)) -> 7 | BJ141: =IF(CD287=BJ$151,BN$151,IF(CD287=BJ$152,BN$152,IF(CD287=BJ$153,BN$153,0))) -> 0 | BK141: =IF(CD287=BJ$151,BO$151,IF(CD287=BJ$152,BO$152,IF(CD287=BJ$153,BO$153,0))) -> 0
BJ142: =IF(CD288=BJ$151,BN$151,IF(CD288=BJ$152,BN$152,IF(CD288=BJ$153,BN$153,0))) -> 0 | BK142: =IF(CD288=BJ$151,BO$151,IF(CD288=BJ$152,BO$152,IF(CD288=BJ$153,BO$153,0))) -> 0 | BL142: =BL143+1 -> 9 | BN142: =BN143+1 -> 9 | BP142: =BP143+1 -> 13
BD143: ="" | BJ143: =IF(CD289=BJ$151,BN$151,IF(CD289=BJ$152,BN$152,IF(CD289=BJ$153,BN$153,0))) -> 0 | BK143: =IF(CD289=BJ$151,BO$151,IF(CD289=BJ$152,BO$152,IF(CD289=BJ$153,BO$153,0))) -> 0 | BL143: 8 | BM143: =VLOOKUP(BL142,BP151:BQ165,2,0) -> 44409 | BN143: 8 | BO143: =VLOOKUP(BN142,BP151:BQ165,2,0) -> 44409 | BP143: 12 | BQ143: =VLOOKUP(BP142,BP151:BQ165,2,0) -> 44531 | BS143: Increment
AT144: Old | AU144: New | AV144: Diffenrence | AW144: ='DA Table'!Z198 -> 19500 | AX144: 7 | AY144: 43282 | BA144: =IF(AY144=AT196,AU197,0)+ROUND(AW144*AU$146,0)-ROUND(AW144*AT$146,0) -> 613 | BE144: 0 days | BJ144: =IF(CD290=BJ$151,BN$151,IF(CD290=BJ$152,BN$152,IF(CD290=BJ$153,BN$153,0))) -> 0 | BK144: =IF(CD290=BJ$151,BO$151,IF(CD290=BJ$152,BO$152,IF(CD290=BJ$153,BO$153,0))) -> 0 | BL144: 1 | BM144: =VLOOKUP(BL144,BP151:BQ165,2,0) -> No Change | BR144: 1 | BS144: 6700 | BT144: 6900 | BU144: 7100
AQ145: 8.908% | AS145: 43101 | AT145: 0.25676 | AU145: 0.27248 | AV145: =AU145-AT145 -> 0.01572 | AW145: ='DA Table'!Z199 -> 20050 | AX145: 8 | AY145: 43313 | BA145: =ROUND(AW145*AU$146,0)-ROUND(AW145*AT$146,0) -> 631 | BE145: 1 days | BG145: =VLOOKUP(BJ151,BF$156:BG$169,2,TRUE) -> 44408 | BJ145: =IF(CD291=BJ$151,BN$151,IF(CD291=BJ$152,BN$152,IF(CD291=BJ$153,BN$153,0))) -> 0 | BK145: =IF(CD291=BJ$151,BO$151,IF(CD291=BJ$152,BO$152,IF(CD291=BJ$153,BO$153,0))) -> 0 | BR145: 2 | BS145: 6900 | BT145: 7100 | BU145: 7300
AQ146: 0.12052 | AS146: 43282 | AT146: 0.27248 | AU146: 0.30392 | AV146: =AU146-AT146 -> 0.03144 | AW146: ='DA Table'!Z200 -> 20050 | AX146: 9 | AY146: 43344 | BA146: =ROUND(AW146*AU$146,0)-ROUND(AW146*AT$146,0) -> 631 | BE146: 2 days | BG146: =VLOOKUP(BJ152,BF$156:BG$169,2,TRUE) -> 44408 | BJ146: =IF(CD292=BJ$151,BN$151,IF(CD292=BJ$152,BN$152,IF(CD292=BJ$153,BN$153,0))) -> 0 | BK146: =IF(CD292=BJ$151,BO$151,IF(CD292=BJ$152,BO$152,IF(CD292=BJ$153,BO$153,0))) -> 0 | BR146: 3 | BS146: 7100 | BT146: 7300 | BU146: 7520
AQ147: 0.15196 | AS147: 43466 | AT147: 0.30392 | AU147: 0.33536 | AV147: =AU147-AT147 -> 0.03144 | AW147: ='DA Table'!Z201 -> 20050 | AX147: 10 | AY147: 43374 | BA147: =ROUND(AW147*AU$146,0)-ROUND(AW147*AT$146,0) -> 631 | BE147: 3 days | BG147: =VLOOKUP(BJ153,BF$156:BG$169,2,TRUE) -> 44316 | BJ147: =IF(CD293=BJ$151,BN$151,IF(CD293=BJ$152,BN$152,IF(CD293=BJ$153,BN$153,0))) -> 0 | BK147: =IF(CD293=BJ$151,BO$151,IF(CD293=BJ$152,BO$152,IF(CD293=BJ$153,BO$153,0))) -> 0 | BR147: 4 | BS147: 7300 | BT147: 7520 | BU147: 7740
AQ148: 0.1834 | AS148: 43647 | AT148: 0.33536 | AU148: 0.38776 | AV148: =AU148-AT148 -> 0.0524 | AW148: ='DA Table'!Z202 -> 20050 | AX148: 11 | AY148: 43405 | BA148: =ROUND(AW148*AU$146,0)-ROUND(AW148*AT$146,0) -> 631 | BE148: 4 days | BJ148: =IF(CD294=BJ$151,BN$151,IF(CD294=BJ$152,BN$152,IF(CD294=BJ$153,BN$153,0))) -> 0 | BK148: =IF(CD294=BJ$151,BO$151,IF(CD294=BJ$152,BO$152,IF(CD294=BJ$153,BO$153,0))) -> 0 | BR148: 5 | BS148: 7520 | BT148: 7740 | BU148: 7960
AW149: ='DA Table'!Z203 -> 20050 | AX149: 12 | AY149: 43435 | BA149: =ROUND(AW149*AU$146,0)-ROUND(AW149*AT$146,0) -> 631 | BE149: 5 days | BR149: 6 | BS149: 7740 | BT149: 7960 | BU149: 8200 | BV149: FR 22(a)i
AW150: ='DA Table'!Z204 -> 20050 | AX150: 1 | AY150: 43466 | BA150: =ROUND(AW150*AU$146,0)-ROUND(AW150*AT$146,0) -> 631 | BC150: =ROUND(AW150*AU$147,0)-ROUND(AW150*AT$147,0) -> 630 | BE150: 6 days | BG150: Half.P.L | BN150: Pay | BO150: DA | BP150: 0 | BR150: 7 | BS150: 7960 | BT150: 8200 | BU150: 8440
AW151: ='DA Table'!Z205 -> 20050 | AX151: 2 | AY151: 43497 | BA151: =ROUND(AW151*AU$146,0)-ROUND(AW151*AT$146,0) -> 631 | BC151: =ROUND(AW151*AU$147,0)-ROUND(AW151*AT$147,0) -> 630 | BE151: 7 days | BF151: 2 | BG151: 1 | BH151: 25 | BI151: 5 | BJ151: =VLOOKUP(BI151,BO$154:BQ$165,3,0) -> 44378 | BK151: =VLOOKUP(BJ151,BO$261:BP$274,2,0) -> 21230 | BL151: =BG145 -> 44408 | BM151: =DAY(BL151) -> 31 | BN151: =IF(BF151=1,ROUND(BK151*BH151/BM151,0),0) -> 0 | BO151: =ROUND(BN151*VLOOKUP(BJ$151,BU$265:BZ278,6,0),0) -> 0 | BP151: 1 | BQ151: No Change | BR151: 8 | BS151: 8200 | BT151: 8440 | BU151: 8680 | BZ151: FR 22B
AW152: ='DA Table'!Z206 -> 20050 | AX152: 3 | AY152: 43525 | BA152: =ROUND(AW152*AU$146,0)-ROUND(AW152*AT$146,0) -> 631 | BC152: =ROUND(AW152*AU$147,0)-ROUND(AW152*AT$147,0) -> 630 | BE152: 8 days | BF152: 2 | BG152: 2 | BH152: 16 | BI152: 5 | BJ152: =VLOOKUP(BI152,BO$154:BQ$165,3,0) -> 44378 | BK152: =VLOOKUP(BJ152,BO$261:BP$274,2,0) -> 21230 | BL152: =BG146 -> 44408 | BM152: =DAY(BL152) -> 31 | BN152: =IF(BF152=1,ROUND(BK152*BH152/BM152,0),0) -> 0 | BO152: =ROUND(BN152*VLOOKUP(BJ$152,BU$265:BZ279,6,0),0) -> 0 | BP152: 2 | BQ152: 44197 | BR152: 9 | BS152: 8440 | BT152: 8680 | BU152: 8940 | BV152: 10900 | BW152: 14860 | BX152: 18030 | BZ152: 10900 | CA152: 14860 | CB152: 18030
AT153: 1 | AU153: Select | AV153: Select | AW153: ='DA Table'!Z207 -> 20050 | AX153: 4 | AY153: 43556 | BA153: =ROUND(AW153*AU$146,0)-ROUND(AW153*AT$146,0) -> 631 | BC153: =ROUND(AW153*AU$147,0)-ROUND(AW153*AT$147,0) -> 630 | BE153: 9 days | BF153: 2 | BG153: 3 | BH153: 13 | BI153: 2 | BJ153: =VLOOKUP(BI153,BO$154:BQ$165,3,0) -> 44287 | BK153: =VLOOKUP(BJ153,BO$261:BP$274,2,0) -> 21230 | BL153: =BG147 -> 44316 | BM153: =DAY(BL153) -> 30 | BN153: =IF(BF153=1,ROUND(BK153*BH153/BM153,0),0) -> 0 | BO153: =ROUND(BN153*VLOOKUP(BJ$153,BU$265:BZ280,6,0),0) -> 0 | BP153: 3 | BQ153: 44228 | BR153: 10 | BS153: 8680 | BT153: 8940 | BU153: 9200 | BV153: 11200 | BW153: 14860 | BX153: 18030 | BZ153: 11200 | CA153: 14860 | CB153: 18030
AT154: 2 | AU154: 43282 | AV154: 44256 | AW154: ='DA Table'!Z208 -> 20050 | AX154: 5 | AY154: 43586 | BA154: =ROUND(AW154*AU$146,0)-ROUND(AW154*AT$146,0) -> 631 | BC154: =ROUND(AW154*AU$147,0)-ROUND(AW154*AT$147,0) -> 630 | BE154: 10 days | BO154: 1 | BP154: 4 | BQ154: 44256 | BR154: 11 | BS154: 8940 | BT154: 9200 | BU154: 9460 | BV154: 11530 | BW154: 14860 | BX154: 18030 | BZ154: 11530 | CA154: 14860 | CB154: 18030 | CC154: 1 | CD154: S.A (P.D) | CE154: 1 | CF154: 2
AR155: 1 | AS155: 31 | AT155: 3 | AU155: 43313 | AV155: 44287 | AW155: ='DA Table'!Z209 -> 20050 | AX155: 6 | AY155: 43617 | BA155: =ROUND(AW155*AU$146,0)-ROUND(AW155*AT$146,0) -> 631 | BC155: =ROUND(AW155*AU$147,0)-ROUND(AW155*AT$147,0) -> 630 | BE155: 11 days | BO155: 2 | BP155: 5 | BQ155: 44287 | BR155: 12 | BS155: 9200 | BT155: 9460 | BU155: 9740 | BV155: 11860 | BW155: 14860 | BX155: 18030 | BZ155: 11860 | CA155: 14860 | CB155: 18030 | CC155: 2 | CD155: PET | CE155: 2 | CF155: 1
AR156: 2 | AS156: 28 | AT156: 4 | AU156: 43344 | AV156: 44317 | AW156: ='DA Table'!Z210 -> 20050 | AX156: 7 | AY156: 43647 | BA156: =ROUND(AW156*AU$146,0)-ROUND(AW156*AT$146,0) -> 631 | BC156: =ROUND(AW156*AU$147,0)-ROUND(AW156*AT$147,0) -> 630 | BE156: 12 days | BF156: 44197 | BG156: 44227 | BO156: 3 | BP156: 6 | BQ156: 44317 | BR156: 13 | BS156: 9460 | BT156: 9740 | BU156: 10020 | BV156: 12190 | BW156: 14860 | BX156: 18030 | BZ156: 12190 | CA156: 14860 | CB156: 18030 | CC156: 3 | CD156: SGT | CE156: 3 | CF156: 1
AR157: 3 | AS157: 31 | AT157: 5 | AU157: 43374 | AV157: 44348 | AW157: ='DA Table'!Z211 -> 20640 | AX157: 8 | AY157: 43678 | BA157: =ROUND(AW157*AU$146,0)-ROUND(AW157*AT$146,0) -> 649 | BC157: =ROUND(AW157*AU$147,0)-ROUND(AW157*AT$147,0) -> 649 | BE157: 13 days | BF157: 44228 | BG157: 44255 | BO157: 4 | BP157: 7 | BQ157: 44348 | BR157: 14 | BS157: 9740 | BT157: 10020 | BU157: 10300 | BV157: 12550 | BW157: 14860 | BX157: 18030 | BZ157: 12550 | CA157: 14860 | CB157: 18030 | CC157: 4 | CD157: LFL HM | CE157: 4 | CF157: 2
AR158: 4 | AS158: 30 | AT158: 6 | AU158: 43405 | AV158: 44378 | AW158: ='DA Table'!Z212 -> 20640 | AX158: 9 | AY158: 43709 | BA158: =ROUND(AW158*AU$146,0)-ROUND(AW158*AT$146,0) -> 649 | BC158: =ROUND(AW158*AU$147,0)-ROUND(AW158*AT$147,0) -> 649 | BE158: 14 days | BF158: 44256 | BG158: 44286 | BO158: 5 | BP158: 8 | BQ158: 44378 | BR158: 15 | BS158: 10020 | BT158: 10300 | BU158: 10600 | BV158: 12910 | BW158: 14860 | BX158: 18030 | BZ158: 12910 | CA158: 14860 | CB158: 18030 | CC158: 5 | CD158: SA(Telugu) | CE158: 5 | CF158: 2
AR159: 5 | AS159: 31 | AT159: 7 | AU159: 43435 | AV159: 44409 | AW159: ='DA Table'!Z213 -> 20640 | AX159: 10 | AY159: 43739 | BA159: =ROUND(AW159*AU$146,0)-ROUND(AW159*AT$146,0) -> 649 | BC159: =ROUND(AW159*AU$147,0)-ROUND(AW159*AT$147,0) -> 649 | BE159: 15 days | BF159: 44287 | BG159: 44316 | BL159: PRC Effect | BM159: 2 | BN159: =VLOOKUP(BM159,BP151:BQ165,2,TRUE) -> 44197 | BO159: 6 | BP159: 9 | BQ159: 44409 | BR159: 16 | BS159: 10300 | BT159: 10600 | BU159: 10900 | BV159: 13270 | BW159: 14860 | BX159: 18030 | BZ159: 13270 | CA159: 14860 | CB159: 18030 | CC159: 6 | CD159: SA(Hindi) | CE159: 6 | CF159: 2 | CJ159: No Change
AR160: 6 | AS160: 30 | AT160: 8 | AU160: 43466 | AV160: 44440 | AW160: ='DA Table'!Z214 -> 20640 | AX160: 11 | AY160: 43770 | BA160: =ROUND(AW160*AU$146,0)-ROUND(AW160*AT$146,0) -> 649 | BC160: =ROUND(AW160*AU$147,0)-ROUND(AW160*AT$147,0) -> 649 | BE160: 16 days | BF160: 44317 | BG160: 44347 | BO160: 7 | BP160: 10 | BQ160: 44440 | BR160: 17 | BS160: 10600 | BT160: 10900 | BU160: 11200 | BV160: 13660 | BW160: 14860 | BX160: 18030 | BZ160: 13660 | CA160: 14860 | CB160: 18030 | CC160: 7 | CD160: SA(Eng) | CE160: 7 | CF160: 2 | CJ160: Month of Annual Increment after Jan-13 | CN160: S.A (P.D) | CO160: PET
AR161: 7 | AS161: 31 | AT161: 9 | AU161: 43497 | AV161: 44470 | AW161: ='DA Table'!Z215 -> 20640 | AX161: 12 | AY161: 43800 | BA161: =ROUND(AW161*AU$146,0)-ROUND(AW161*AT$146,0) -> 649 | BC161: =ROUND(AW161*AU$147,0)-ROUND(AW161*AT$147,0) -> 649 | BE161: 17 days | BF161: 44348 | BG161: 44377 | BO161: 8 | BP161: 11 | BQ161: 44470 | BR161: 18 | BS161: 10900 | BT161: 11200 | BU161: 11530 | BV161: 14050 | BW161: 14860 | BX161: 18030 | BZ161: 14050 | CA161: 14860 | CB161: 18030 | CC161: 8 | CD161: SA(Maths) | CE161: 8 | CF161: 2 | CJ161: Prephonement Increment Month | CN161: LFL HM | CO161: SGT | DB161: Nonmandal | DC161: mandal | DD161: Hills | DF161: SCA
AR162: 8 | AS162: 31 | AT162: 10 | AU162: 43525 | AV162: 44501 | AW162: ='DA Table'!Z216 -> 20640 | AX162: 1 | AY162: 43831 | BA162: =ROUND(AW162*AU$146,0)-ROUND(AW162*AT$146,0) -> 649 | BC162: =ROUND(AW162*AU$147,0)-ROUND(AW162*AT$147,0) -> 649 | BE162: 18 days | BF162: 44378 | BG162: 44408 | BO162: 9 | BP162: 12 | BQ162: 44501 | BR162: 19 | BS162: 11200 | BT162: 11530 | BU162: 11860 | BV162: 14440 | BW162: 14860 | BX162: 18030 | BZ162: 14440 | CA162: 15280 | CB162: 18030 | CC162: 9 | CD162: SA(PS) | CE162: 9 | CF162: 2 | CJ162: Stepup Increment Month | CN162: SA(Telugu) | CO162: Gr.II/ S.G.T | CZ162: =CZ178 -> 44256 | DA162: =CE283 -> 21230 | DB162: =IF(AND(CI$190=2,DA162<=CX$163),325,IF(AND(CI$190=2,DA162<=CY$164),400,IF(AND(CI$190=2,DA162<=CY$165),475,IF(AND(CI$190=2,DA162<=CY$166),575,IF(AND(CI$190=2,DA162<=CY$167),625,IF(AND(CI$190=2,DA162>CX$168),675,"")))))) -> 575 | DC162: =IF(AND(CI$190=3,DA162<=CX$163),400,IF(AND(CI$190=3,DA162<=CY$164),475,IF(AND(CI$190=3,DA162<=CY$165),575,IF(AND(CI$190=3,DA162<=CY$166),625,IF(AND(CI$190=3,DA162<=CY$167),675,IF(AND(CI$190=2,DA162>CX$168),725,"")))))) | DD162: =IF(AND(CI$190=4,DA162<=CX$163),475,IF(AND(CI$190=4,DA162<=CY$164),550,IF(AND(CI$190=4,DA162<=CY$165),625,IF(AND(CI$190=4,DA162<=CY$166),700,IF(AND(CI$190=4,DA162<=CY$167),775,IF(AND(CI$190=4,DA162>CX$168),850,"")))))) | DE162: =L$21 -> 0 | DF162: =IF(DE162=0,0,DE162) -> 0
AR163: 9 | AS163: 30 | AT163: 11 | AU163: 43556 | AV163: 44531 | AW163: ='DA Table'!Z217 -> 20640 | AX163: 2 | AY163: 43862 | BA163: =ROUND(AW163*AU$146,0)-ROUND(AW163*AT$146,0) -> 649 | BC163: =ROUND(AW163*AU$147,0)-ROUND(AW163*AT$147,0) -> 649 | BE163: 19 days | BF163: 44409 | BG163: 44439 | BO163: 10 | BP163: 13 | BQ163: 44531 | BR163: 20 | BS163: 11530 | BT163: 11860 | BU163: 12190 | BV163: 14860 | BW163: 15280 | BX163: 18030 | BZ163: 14860 | CA163: 15700 | CB163: 18030 | CC163: 10 | CD163: SA(Bio.Sc) | CE163: 10 | CF163: 2 | CJ163: Promotion ( one Increment ) | CN163: SA(Hindi) | CO163: Gr.II/ S.G.T | CX163: 10600 | CZ163: =CZ179 -> 44287 | DA163: =CE284 -> 21230 | DB163: =IF(AND(CI$190=2,DA163<=CX$163),325,IF(AND(CI$190=2,DA163<=CY$164),400,IF(AND(CI$190=2,DA163<=CY$165),475,IF(AND(CI$190=2,DA163<=CY$166),575,IF(AND(CI$190=2,DA163<=CY$167),625,IF(AND(CI$190=2,DA163>CX$168),675,"")))))) -> 575 | DC163: =IF(AND(CI$190=3,DA163<=CX$163),400,IF(AND(CI$190=3,DA163<=CY$164),475,IF(AND(CI$190=3,DA163<=CY$165),575,IF(AND(CI$190=3,DA163<=CY$166),625,IF(AND(CI$190=3,DA163<=CY$167),675,IF(AND(CI$190=2,DA163>CX$168),725,"")))))) | DD163: =IF(AND(CI$190=4,DA163<=CX$163),475,IF(AND(CI$190=4,DA163<=CY$164),550,IF(AND(CI$190=4,DA163<=CY$165),625,IF(AND(CI$190=4,DA163<=CY$166),700,IF(AND(CI$190=4,DA163<=CY$167),775,IF(AND(CI$190=4,DA163>CX$168),850,"")))))) | DE163: =L$21 -> 0 | DF163: =IF(DE163=0,0,DE163) -> 0
AR164: 10 | AS164: 31 | AT164: 12 | AU164: 43586 | AV164: 44562 | AW164: ='DA Table'!Z218 -> 20640 | AX164: 3 | AY164: 43891 | BA164: =ROUND(AW164*AU$146,0)-ROUND(AW164*AT$146,0) -> 649 | BC164: =ROUND(AW164*AU$147,0)-ROUND(AW164*AT$147,0) -> 649 | BE164: 20 days | BF164: 44440 | BG164: 44469 | BO164: 11 | BP164: 14 | BQ164: 44562 | BR164: 21 | BS164: 11860 | BT164: 12190 | BU164: 12550 | BV164: 15280 | BW164: 15700 | BX164: 18030 | BZ164: 15280 | CA164: 16150 | CB164: 18030 | CC164: 11 | CD164: SA(Social) | CE164: 11 | CF164: 2 | CJ164: Promotion ( Two Increment or Promotion date ) | CN164: SA(Eng) | CO164: S.G.T | CX164: 10601 | CY164: 13660 | CZ164: =CZ180 -> 44317 | DA164: =CE285 -> 21230 | DB164: =IF(AND(CI$190=2,DA164<=CX$163),325,IF(AND(CI$190=2,DA164<=CY$164),400,IF(AND(CI$190=2,DA164<=CY$165),475,IF(AND(CI$190=2,DA164<=CY$166),575,IF(AND(CI$190=2,DA164<=CY$167),625,IF(AND(CI$190=2,DA164>CX$168),675,"")))))) -> 575 | DC164: =IF(AND(CI$190=3,DA164<=CX$163),400,IF(AND(CI$190=3,DA164<=CY$164),475,IF(AND(CI$190=3,DA164<=CY$165),575,IF(AND(CI$190=3,DA164<=CY$166),625,IF(AND(CI$190=3,DA164<=CY$167),675,IF(AND(CI$190=2,DA164>CX$168),725,"")))))) | DD164: =IF(AND(CI$190=4,DA164<=CX$163),475,IF(AND(CI$190=4,DA164<=CY$164),550,IF(AND(CI$190=4,DA164<=CY$165),625,IF(AND(CI$190=4,DA164<=CY$166),700,IF(AND(CI$190=4,DA164<=CY$167),775,IF(AND(CI$190=4,DA164>CX$168),850,"")))))) | DE164: =L$21 -> 0 | DF164: =IF(DE164=0,0,DE164) -> 0
AR165: 11 | AS165: 30 | AT165: 13 | AU165: 43617 | AV165: 44593 | AW165: ='DA Table'!Z219 -> 20640 | AX165: 4 | AY165: 43922 | BA165: =ROUND(AW165*AU$146,0)-ROUND(AW165*AT$146,0) -> 649 | BC165: =ROUND(AW165*AU$147,0)-ROUND(AW165*AT$147,0) -> 649 | BE165: 21 days | BF165: 44470 | BG165: 44500 | BO165: 12 | BP165: 15 | BQ165: 44593 | BR165: 22 | BS165: 12190 | BT165: 12550 | BU165: 12910 | BV165: 15700 | BW165: 16150 | BX165: 18030 | BZ165: 15700 | CA165: 16600 | CB165: 18030 | CC165: 12 | CD165: Head Master | CE165: 12 | CF165: 3 | CJ165: AAS Increment (6/12/18/24 years) | CN165: SA(Maths) | CO165: S.G.T | CX165: 13661 | CY165: 17050 | CZ165: =CZ181 -> 44348 | DA165: =CE286 -> 21230 | DB165: =IF(AND(CI$190=2,DA165<=CX$163),325,IF(AND(CI$190=2,DA165<=CY$164),400,IF(AND(CI$190=2,DA165<=CY$165),475,IF(AND(CI$190=2,DA165<=CY$166),575,IF(AND(CI$190=2,DA165<=CY$167),625,IF(AND(CI$190=2,DA165>CX$168),675,"")))))) -> 575 | DC165: =IF(AND(CI$190=3,DA165<=CX$163),400,IF(AND(CI$190=3,DA165<=CY$164),475,IF(AND(CI$190=3,DA165<=CY$165),575,IF(AND(CI$190=3,DA165<=CY$166),625,IF(AND(CI$190=3,DA165<=CY$167),675,IF(AND(CI$190=2,DA165>CX$168),725,"")))))) | DD165: =IF(AND(CI$190=4,DA165<=CX$163),475,IF(AND(CI$190=4,DA165<=CY$164),550,IF(AND(CI$190=4,DA165<=CY$165),625,IF(AND(CI$190=4,DA165<=CY$166),700,IF(AND(CI$190=4,DA165<=CY$167),775,IF(AND(CI$190=4,DA165>CX$168),850,"")))))) | DE165: =L$21 -> 0 | DF165: =IF(DE165=0,0,DE165) -> 0
AR166: 12 | AS166: 31 | AT166: 14 | AU166: 43647 | AW166: ='DA Table'!Z220 -> 20640 | AX166: 5 | AY166: 43952 | BA166: =ROUND(AW166*AU$146,0)-ROUND(AW166*AT$146,0) -> 649 | BC166: =ROUND(AW166*AU$147,0)-ROUND(AW166*AT$147,0) -> 649 | BE166: 22 days | BF166: 44501 | BG166: 44530 | BH166: 1 | BI166: ULIP LIC Yearly | BK166: Interest of Housing Loan Section 24 | BL166: 200000 | BP166: 16 | BR166: 23 | BS166: 12550 | BT166: 12910 | BU166: 13270 | BV166: 16150 | BW166: 16600 | BX166: 18030 | BZ166: 16150 | CA166: 17050 | CB166: 18030 | CC166: 13 | CD166: Gr-2 (Telugu) | CE166: 13 | CF166: 1 | CN166: SA(PS) | CO166: S.G.T | CX166: 17051 | CY166: 21250 | CZ166: =CZ182 -> 44378 | DA166: =CE287 -> 21230 | DB166: =IF(AND(CI$190=2,DA166<=CX$163),325,IF(AND(CI$190=2,DA166<=CY$164),400,IF(AND(CI$190=2,DA166<=CY$165),475,IF(AND(CI$190=2,DA166<=CY$166),575,IF(AND(CI$190=2,DA166<=CY$167),625,IF(AND(CI$190=2,DA166>CX$168),675,"")))))) -> 575 | DC166: =IF(AND(CI$190=3,DA166<=CX$163),400,IF(AND(CI$190=3,DA166<=CY$164),475,IF(AND(CI$190=3,DA166<=CY$165),575,IF(AND(CI$190=3,DA166<=CY$166),625,IF(AND(CI$190=3,DA166<=CY$167),675,IF(AND(CI$190=2,DA166>CX$168),725,"")))))) | DD166: =IF(AND(CI$190=4,DA166<=CX$163),475,IF(AND(CI$190=4,DA166<=CY$164),550,IF(AND(CI$190=4,DA166<=CY$165),625,IF(AND(CI$190=4,DA166<=CY$166),700,IF(AND(CI$190=4,DA166<=CY$167),775,IF(AND(CI$190=4,DA166>CX$168),850,"")))))) | DE166: =L$21 -> 0 | DF166: =IF(DE166=0,0,DE166) -> 0
AT167: 15 | AU167: 43678 | AW167: ='DA Table'!Z221 -> 20640 | AX167: 6 | AY167: 43983 | BA167: =ROUND(AW167*AU$146,0)-ROUND(AW167*AT$146,0) -> 649 | BC167: =ROUND(AW167*AU$147,0)-ROUND(AW167*AT$147,0) -> 649 | BE167: 23 days | BF167: 44531 | BG167: 44561 | BH167: 2 | BI167: Bajaj Alliance life Insurance | BK167: Interest of Housing Loan 80EE | BL167: 250000 | BP167: 17 | BQ167: 5 | BR167: 24 | BS167: 12910 | BT167: 13270 | BU167: 13660 | BV167: 16600 | BW167: 17050 | BX167: 18030 | BZ167: 16600 | CA167: 17540 | CB167: 18030 | CC167: 14 | CD167: Gr-2 (Hindi) | CE167: 14 | CF167: 1 | CJ167: =IF(OR(BF254=CJ163,BF254=CJ164),VLOOKUP(CD169,CN160:CO170,2,0),IF(OR(BF255=CJ163,BF255=CJ164),VLOOKUP(CD169,CN160:CO170,2,0),IF(OR(BF256=CJ163,BF256=CJ164),VLOOKUP(CD169,CN160:CO170,2,0),CD169))) -> Deputy Executive Engineer | CN167: SA(Bio.Sc) | CO167: S.G.T | CX167: 21251 | CY167: 25450 | CZ167: =CZ183 -> 44409 | DA167: =CE288 -> 21820 | DB167: =IF(AND(CI$190=2,DA167<=CX$163),325,IF(AND(CI$190=2,DA167<=CY$164),400,IF(AND(CI$190=2,DA167<=CY$165),475,IF(AND(CI$190=2,DA167<=CY$166),575,IF(AND(CI$190=2,DA167<=CY$167),625,IF(AND(CI$190=2,DA167>CX$168),675,"")))))) -> 625 | DC167: =IF(AND(CI$190=3,DA167<=CX$163),400,IF(AND(CI$190=3,DA167<=CY$164),475,IF(AND(CI$190=3,DA167<=CY$165),575,IF(AND(CI$190=3,DA167<=CY$166),625,IF(AND(CI$190=3,DA167<=CY$167),675,IF(AND(CI$190=2,DA167>CX$168),725,"")))))) | DD167: =IF(AND(CI$190=4,DA167<=CX$163),475,IF(AND(CI$190=4,DA167<=CY$164),550,IF(AND(CI$190=4,DA167<=CY$165),625,IF(AND(CI$190=4,DA167<=CY$166),700,IF(AND(CI$190=4,DA167<=CY$167),775,IF(AND(CI$190=4,DA167>CX$168),850,"")))))) | DE167: =L$21 -> 0 | DF167: =IF(DE167=0,0,DE167) -> 0
AT168: 16 | AU168: 43709 | AW168: ='DA Table'!Z222 -> 20640 | AX168: 7 | AY168: 44013 | BA168: =ROUND(AW168*AU$146,0)-ROUND(AW168*AT$146,0) -> 649 | BC168: =ROUND(AW168*AU$147,0)-ROUND(AW168*AT$147,0) -> 649 | BE168: 24 days | BF168: 44562 | BG168: 44592 | BH168: 3 | BI168: Tuition Fee for Two children | BK168: Interest of HBA Loan 80EEA | BL168: 350000 | BP168: 18 | BQ168: 12 | BR168: 25 | BS168: 13270 | BT168: 13660 | BU168: 14050 | BV168: 17050 | BW168: 17540 | BX168: 18030 | BZ168: 17050 | CA168: 18030 | CB168: 18030 | CC168: 15 | CD168: MEO | CE168: 15 | CF168: 3 | CN168: SA(Social) | CO168: S.G.T | CX168: 28451 | CZ168: =CZ184 -> 44440 | DA168: =CE289 -> 21820 | DB168: =IF(AND(CI$190=2,DA168<=CX$163),325,IF(AND(CI$190=2,DA168<=CY$164),400,IF(AND(CI$190=2,DA168<=CY$165),475,IF(AND(CI$190=2,DA168<=CY$166),575,IF(AND(CI$190=2,DA168<=CY$167),625,IF(AND(CI$190=2,DA168>CX$168),675,"")))))) -> 625 | DC168: =IF(AND(CI$190=3,DA168<=CX$163),400,IF(AND(CI$190=3,DA168<=CY$164),475,IF(AND(CI$190=3,DA168<=CY$165),575,IF(AND(CI$190=3,DA168<=CY$166),625,IF(AND(CI$190=3,DA168<=CY$167),675,IF(AND(CI$190=2,DA168>CX$168),725,"")))))) | DD168: =IF(AND(CI$190=4,DA168<=CX$163),475,IF(AND(CI$190=4,DA168<=CY$164),550,IF(AND(CI$190=4,DA168<=CY$165),625,IF(AND(CI$190=4,DA168<=CY$166),700,IF(AND(CI$190=4,DA168<=CY$167),775,IF(AND(CI$190=4,DA168>CX$168),850,"")))))) | DE168: =L$21 -> 0 | DF168: =IF(DE168=0,0,DE168) -> 0
AT169: 17 | AU169: 43739 | AW169: ='DA Table'!Z223 -> 21230 | AX169: 8 | AY169: 44044 | BA169: =ROUND(AW169*AU$146,0)-ROUND(AW169*AT$146,0) -> 667 | BC169: =ROUND(AW169*AU$147,0)-ROUND(AW169*AT$147,0) -> 668 | BE169: 25 days | BF169: 44593 | BG169: 44620 | BH169: 4 | BI169: LIC Policies premium - Yearly | BM169: 1 | BN169: Sri. | BO169: With Undertaking | BP169: 19 | BQ169: 14.5 | BR169: 26 | BS169: 13660 | BT169: 14050 | BU169: 14440 | BV169: 17540 | BW169: 18030 | BX169: 18520 | BZ169: 17540 | CA169: 18520 | CB169: 18520 | CD169: =CD170 -> Deputy Executive Engineer | CE169: 7 | CF169: =VLOOKUP(CD169,CD154:CF168,3,0) -> #N/A | CN169: Head Master | CO169: SA ( ) | CZ169: =CZ185 -> 44470 | DA169: =CE290 -> 21820 | DB169: =IF(AND(CI$190=2,DA169<=CX$163),325,IF(AND(CI$190=2,DA169<=CY$164),400,IF(AND(CI$190=2,DA169<=CY$165),475,IF(AND(CI$190=2,DA169<=CY$166),575,IF(AND(CI$190=2,DA169<=CY$167),625,IF(AND(CI$190=2,DA169>CX$168),675,"")))))) -> 625 | DC169: =IF(AND(CI$190=3,DA169<=CX$163),400,IF(AND(CI$190=3,DA169<=CY$164),475,IF(AND(CI$190=3,DA169<=CY$165),575,IF(AND(CI$190=3,DA169<=CY$166),625,IF(AND(CI$190=3,DA169<=CY$167),675,IF(AND(CI$190=2,DA169>CX$168),725,"")))))) | DD169: =IF(AND(CI$190=4,DA169<=CX$163),475,IF(AND(CI$190=4,DA169<=CY$164),550,IF(AND(CI$190=4,DA169<=CY$165),625,IF(AND(CI$190=4,DA169<=CY$166),700,IF(AND(CI$190=4,DA169<=CY$167),775,IF(AND(CI$190=4,DA169>CX$168),850,"")))))) | DE169: =L$21 -> 0 | DF169: =IF(DE169=0,0,DE169) -> 0
AT170: 18 | AU170: 43770 | AW170: ='DA Table'!Z224 -> 21230 | AX170: 9 | AY170: 44075 | BA170: =ROUND(AW170*AU$146,0)-ROUND(AW170*AT$146,0) -> 667 | BC170: =ROUND(AW170*AU$147,0)-ROUND(AW170*AT$147,0) -> 668 | BE170: 26 days | BH170: 5 | BI170: Housing Loan Principal Amount | BL170: =IF(BO188=1,"24B",IF(BO188=2,"80EE","80EEA")) -> 24B | BM170: 2 | BN170: Smt. | BO170: Without Undertaking | BP170: 20 | BQ170: 20 | BR170: 27 | BS170: 14050 | BT170: 14440 | BU170: 14860 | BV170: 18030 | BW170: 18520 | BX170: 19050 | BZ170: 18030 | CA170: 19050 | CB170: 19050 | CC170: 9 | CD170: =E11 -> Deputy Executive Engineer | CF170: =CF169 -> #N/A | CG170: =VLOOKUP(CC170,CC154:CD168,2,0) -> SA(PS) | CN170: MEO | CO170: SA ( ) | CZ170: =CZ186 -> 44501 | DA170: =CE291 -> 21820 | DB170: =IF(AND(CI$190=2,DA170<=CX$163),325,IF(AND(CI$190=2,DA170<=CY$164),400,IF(AND(CI$190=2,DA170<=CY$165),475,IF(AND(CI$190=2,DA170<=CY$166),575,IF(AND(CI$190=2,DA170<=CY$167),625,IF(AND(CI$190=2,DA170>CX$168),675,"")))))) -> 625 | DC170: =IF(AND(CI$190=3,DA170<=CX$163),400,IF(AND(CI$190=3,DA170<=CY$164),475,IF(AND(CI$190=3,DA170<=CY$165),575,IF(AND(CI$190=3,DA170<=CY$166),625,IF(AND(CI$190=3,DA170<=CY$167),675,IF(AND(CI$190=2,DA170>CX$168),725,"")))))) | DD170: =IF(AND(CI$190=4,DA170<=CX$163),475,IF(AND(CI$190=4,DA170<=CY$164),550,IF(AND(CI$190=4,DA170<=CY$165),625,IF(AND(CI$190=4,DA170<=CY$166),700,IF(AND(CI$190=4,DA170<=CY$167),775,IF(AND(CI$190=4,DA170>CX$168),850,"")))))) | DE170: =L$21 -> 0 | DF170: =IF(DE170=0,0,DE170) -> 0
AT171: 19 | AU171: 43800 | AW171: ='DA Table'!Z225 -> 21230 | AX171: 10 | AY171: 44105 | BA171: =ROUND(AW171*AU$146,0)-ROUND(AW171*AT$146,0) -> 667 | BC171: =ROUND(AW171*AU$147,0)-ROUND(AW171*AT$147,0) -> 668 | BE171: 27 days | BH171: 6 | BI171: SBI Life Insurance | BL171: =IF(G$33<=BL166,G$33,IF(G$33>BL166,BL166)) -> 0 | BM171: 3 | BN171: Kum. | BO171: 1 | BP171: 21 | BQ171: 30 | BR171: 28 | BS171: 14440 | BT171: 14860 | BU171: 15280 | BV171: 18520 | BW171: 19050 | BX171: 19580 | BZ171: 18520 | CA171: 19580 | CB171: 19580 | CC171: 1 | CD171: Not Applicable | CE171: 0 | CZ171: =CZ187 -> 44531 | DA171: =CE292 -> 21820 | DB171: =IF(AND(CI$190=2,DA171<=CX$163),325,IF(AND(CI$190=2,DA171<=CY$164),400,IF(AND(CI$190=2,DA171<=CY$165),475,IF(AND(CI$190=2,DA171<=CY$166),575,IF(AND(CI$190=2,DA171<=CY$167),625,IF(AND(CI$190=2,DA171>CX$168),675,"")))))) -> 625 | DC171: =IF(AND(CI$190=3,DA171<=CX$163),400,IF(AND(CI$190=3,DA171<=CY$164),475,IF(AND(CI$190=3,DA171<=CY$165),575,IF(AND(CI$190=3,DA171<=CY$166),625,IF(AND(CI$190=3,DA171<=CY$167),675,IF(AND(CI$190=2,DA171>CX$168),725,"")))))) | DD171: =IF(AND(CI$190=4,DA171<=CX$163),475,IF(AND(CI$190=4,DA171<=CY$164),550,IF(AND(CI$190=4,DA171<=CY$165),625,IF(AND(CI$190=4,DA171<=CY$166),700,IF(AND(CI$190=4,DA171<=CY$167),775,IF(AND(CI$190=4,DA171>CX$168),850,"")))))) | DE171: =L$21 -> 0 | DF171: =IF(DE171=0,0,DE171) -> 0
AT172: 20 | AU172: 43831 | AW172: ='DA Table'!Z226 -> 21230 | AX172: 11 | AY172: 44136 | BA172: =ROUND(AW172*AU$146,0)-ROUND(AW172*AT$146,0) -> 667 | BC172: =ROUND(AW172*AU$147,0)-ROUND(AW172*AT$147,0) -> 668 | BE172: 28 days | BH172: 7 | BI172: National Savings Certificates (NSC) | BL172: =IF(G$33<=BL167,G$33,IF(G$33>BL167,BL167)) -> 0 | BM172: 1 | BN172: =VLOOKUP(BM172,BM169:BN171,2,0) -> Sri. | BP172: 22 | BR172: 29 | BS172: 14860 | BT172: 15280 | BU172: 15700 | BV172: 19050 | BW172: 19580 | BX172: 20110 | BZ172: 19050 | CA172: 20110 | CB172: 20110 | CC172: 2 | CD172: 50 | CE172: 50 | CF172: 1 | CZ172: =CZ188 -> 44562 | DA172: =CE293 -> 21820 | DB172: =IF(AND(CI$190=2,DA172<=CX$163),325,IF(AND(CI$190=2,DA172<=CY$164),400,IF(AND(CI$190=2,DA172<=CY$165),475,IF(AND(CI$190=2,DA172<=CY$166),575,IF(AND(CI$190=2,DA172<=CY$167),625,IF(AND(CI$190=2,DA172>CX$168),675,"")))))) -> 625 | DC172: =IF(AND(CI$190=3,DA172<=CX$163),400,IF(AND(CI$190=3,DA172<=CY$164),475,IF(AND(CI$190=3,DA172<=CY$165),575,IF(AND(CI$190=3,DA172<=CY$166),625,IF(AND(CI$190=3,DA172<=CY$167),675,IF(AND(CI$190=2,DA172>CX$168),725,"")))))) | DD172: =IF(AND(CI$190=4,DA172<=CX$163),475,IF(AND(CI$190=4,DA172<=CY$164),550,IF(AND(CI$190=4,DA172<=CY$165),625,IF(AND(CI$190=4,DA172<=CY$166),700,IF(AND(CI$190=4,DA172<=CY$167),775,IF(AND(CI$190=4,DA172>CX$168),850,"")))))) | DE172: =L$21 -> 0 | DF172: =IF(DE172=0,0,DE172) -> 0
AT173: 21 | AU173: 43862 | AW173: ='DA Table'!Z227 -> 21230 | AX173: 12 | AY173: 44166 | BA173: =ROUND(AW173*AU$146,0)-ROUND(AW173*AT$146,0) -> 667 | BC173: =ROUND(AW173*AU$147,0)-ROUND(AW173*AT$147,0) -> 668 | BE173: 29 days | BH173: 8 | BI173: Exide Life Insurance | BL173: =IF(G$33<=BL168,G$33,IF(G$33>BL168,BL168)) -> 0 | BN173: 1 | BO173: 12 | BP173: 23 | BR173: 30 | BS173: 15280 | BT173: 15700 | BU173: 16150 | BV173: 19580 | BW173: 20110 | BX173: 20680 | BZ173: 19580 | CA173: 20680 | CB173: 20680 | CC173: 3 | CD173: 75 | CE173: 75 | CF173: =VLOOKUP(CF172,CC171:CD174,2,0) -> Not Applicable | CL173: RA | CO173: A HRA | CZ173: =CZ189 -> 44593 | DA173: =CE294 -> 21820 | DB173: =IF(AND(CI$190=2,DA173<=CX$163),325,IF(AND(CI$190=2,DA173<=CY$164),400,IF(AND(CI$190=2,DA173<=CY$165),475,IF(AND(CI$190=2,DA173<=CY$166),575,IF(AND(CI$190=2,DA173<=CY$167),625,IF(AND(CI$190=2,DA173>CX$168),675,"")))))) -> 625 | DC173: =IF(AND(CI$190=3,DA173<=CX$163),400,IF(AND(CI$190=3,DA173<=CY$164),475,IF(AND(CI$190=3,DA173<=CY$165),575,IF(AND(CI$190=3,DA173<=CY$166),625,IF(AND(CI$190=3,DA173<=CY$167),675,IF(AND(CI$190=2,DA173>CX$168),725,"")))))) | DD173: =IF(AND(CI$190=4,DA173<=CX$163),475,IF(AND(CI$190=4,DA173<=CY$164),550,IF(AND(CI$190=4,DA173<=CY$165),625,IF(AND(CI$190=4,DA173<=CY$166),700,IF(AND(CI$190=4,DA173<=CY$167),775,IF(AND(CI$190=4,DA173>CX$168),850,"")))))) | DE173: =L$21 -> 0 | DF173: =IF(DE173=0,0,DE173) -> 0
AT174: 22 | AU174: 43891 | AW174: ='DA Table'!Z228 -> 21230 | AX174: 1 | AY174: 44197 | BC174: =ROUND(AW174*AU$147,0)-ROUND(AW174*AT$147,0) -> 668 | BE174: 30 days | BH174: 9 | BI174: Birla Sun Life Insurance | BL174: =IF(BO188=1,BL171,IF(BO188=2,BL172,BL173)) -> 0 | BN174: 2 | BO174: 14.5 | BP174: 24 | BR174: 31 | BS174: 15700 | BT174: 16150 | BU174: 16600 | BV174: 20110 | BW174: 20680 | BX174: 21250 | BZ174: 20110 | CA174: 21250 | CB174: 21250 | CC174: 4 | CD174: 100 | CE174: 100 | CF174: HMA | CI174: PHA | CO174: 1 | CP174: Not Applicaple
AT175: 23 | AU175: 43922 | AW175: ='DA Table'!Z229 -> 21230 | AX175: 2 | AY175: 44228 | BC175: =ROUND(AW175*AU$147,0)-ROUND(AW175*AT$147,0) -> 668 | BE175: 31 days | BH175: 10 | BI175: Reliance Life Insurance | BN175: 3 | BO175: 20 | BP175: 25 | BR175: 32 | BS175: 16150 | BT175: 16600 | BU175: 17050 | BV175: 20680 | BW175: 21250 | BX175: 21820 | BZ175: 20680 | CA175: 21820 | CB175: 21820 | CD175: =L13 -> 0 | CE175: =L13 -> 0 | CF175: =IF(CE175=0,0,CE175) -> 0 | CG175: 1 | CH175: Not Applicable | CI175: 0 | CJ175: 1 | CL175: 1 | CM175: Not Applicable | CO175: 2 | CP175: Applicable
AT176: 24 | AU176: 43952 | AW176: ='DA Table'!Z230 -> 21230 | AX176: 3 | AY176: 44256 | BC176: =ROUND(AW176*AU$147,0)-ROUND(AW176*AT$147,0) -> 668 | BE176: 0 days | BH176: 11 | BI176: Stamp Duty and Registration Charges | BN176: 4 | BO176: 30 | BP176: 26 | BR176: 33 | BS176: 16600 | BT176: 17050 | BU176: 17540 | BV176: 21250 | BW176: 21820 | BX176: 22430 | BZ176: 21250 | CA176: 22430 | CB176: 22430 | CC176: 1 | CD176: Rented House | CF176: =IF(CF177=CD176,CJ236,IF(CF177=CD177,0)) -> 40150 | CG176: 2 | CH176: with holidays | CI176: =IF(CL274=1,1350,IF(CL274=2,2000,0)) -> 1350 | CL176: 2 | CM176: 400 | CT176: =CU176 -> #N/A | CU176: =#N/A -> #N/A | CW176: Hyderabad, Secunderabad | CX176: Visakhapatnam & Vijayawada | CY176: Other Mpl.Corporations
AT177: 25 | AU177: 43983 | AW177: ='DA Table'!Z231 -> 21230 | AX177: 4 | AY177: 44287 | BC177: =ROUND(AW177*AU$147,0)-ROUND(AW177*AT$147,0) -> 668 | BH177: 12 | BI177: ICICI Life Insurance | BN177: 5 | BO177: 0 | BP177: 27 | BR177: 34 | BS177: 17050 | BT177: 17540 | BU177: 18030 | BV177: 21820 | BW177: 22430 | BX177: 23040 | BZ177: 21820 | CA177: 23040 | CB177: 23040 | CC177: 2 | CD177: Own House | CF177: =VLOOKUP(CE178,CC176:CD177,2,0) -> Rented House | CG177: 3 | CH177: without holidays | CI177: =IF(CH178=CH175,0,CI176) -> 0 | CL177: 3 | CM177: 500 | CQ177: 21 | DE177: 1 | DI177: 2
AT178: 26 | AU178: 44013 | AW178: ='DA Table'!Z232 -> 21230 | AX178: 5 | AY178: 44317 | BC178: =ROUND(AW178*AU$147,0)-ROUND(AW178*AT$147,0) -> 668 | BH178: 13 | BI178: Public Provident Fund | BP178: 28 | BR178: 35 | BS178: 17540 | BT178: 18030 | BU178: 18520 | BV178: 22430 | BW178: 23040 | BX178: 23650 | BZ178: 22430 | CA178: 23650 | CB178: 23650 | CE178: 1 | CH178: =VLOOKUP(CJ175,CG175:CH177,2,0) -> Not Applicable | CI178: =IF(CI177=0,"",CI177) | CJ178: =IF(CI178="",0,CI176) -> 0 | CL178: 4 | CM178: 600 | CP178: 1 | CQ178: 22 | CS178: 12 | CT178: 7 | CU178: =IF(CT193=1,"",VLOOKUP(CT178,BO154:BQ165,3,FALSE)) | CZ178: 44256 | DA178: =CE283 -> 21230 | DJ178: =IF(CZ178=CU$178,CV$195,CV$192) -> 0 | DK178: =IF(CZ178=CU$178,CV$184,DJ178) -> 0 | DL178: =IF(DK178=0,"",DK178)
AT179: 27 | AU179: 44044 | AW179: ='DA Table'!Z233 -> 21230 | AX179: 6 | AY179: 44348 | BC179: =ROUND(AW179*AU$147,0)-ROUND(AW179*AT$147,0) -> 668 | BH179: 14 | BI179: HDFC life Insurance | BN179: 3 | BO179: =VLOOKUP(BN179,BN173:BO177,2,0) -> 20 | BP179: 29 | BR179: 36 | BS179: 18030 | BT179: 18520 | BU179: 19050 | BV179: 23040 | BW179: 23650 | BX179: 24300 | BZ179: 23040 | CA179: 24300 | CB179: 24300 | CD179: Not Applicable | CF179: PP | CH179: 44287 | CI179: 23 | CJ179: =IF(CJ$178="","",ROUND(CJ$178/30*CI179,0)) -> 0 | CK179: =IF(CJ$175=1,0,IF(CJ$175=2,CJ179,IF(CJ$175=3,CI176))) -> 0 | CP179: =VLOOKUP(CP178,CO174:CP175,2,FALSE) -> Not Applicaple | CQ179: 23 | CS179: =IF(CT193=1,"",MONTH(CU178)) | CT179: =IF(CT193=1,"",YEAR(CU178)) | CU179: =IF(CT193=1,"",DATE(CT179,CS179,CS178)) | CW179: 200 | CX179: 120 | CY179: 100 | CZ179: 44287 | DA179: =CE284 -> 21230 | DJ179: =IF(CZ179=CU$178,CV$195,DJ178) -> 0 | DK179: =IF(CZ179=CU$178,CV$184,DJ179) -> 0 | DL179: =IF(DK179=0,"",DK179)
AT180: 28 | AU180: 44075 | AW180: ='DA Table'!Z234 -> 21230 | AX180: 7 | AY180: 44378 | BH180: 15 | BI180: PLI (Postal Life Insurance) | BN180: 2 | BO180: =VLOOKUP(BN180,BN173:BO176,2,0) -> 14.5 | BP180: 30 | BR180: 37 | BS180: 18520 | BT180: 19050 | BU180: 19580 | BV180: 23650 | BW180: 24300 | BX180: 24950 | BZ180: 23650 | CA180: 24950 | CB180: 24950 | CD180: Applicable | CF180: =L23 -> 0 | CH180: 44348 | CI180: 18 | CJ180: =IF(CJ$178="","",ROUND(CJ$178/30*CI180,0)) -> 0 | CK180: =IF(CJ$175=1,0,IF(CJ$175=2,CJ180,IF(CJ$175=3,CI176))) -> 0 | CP180: =IF(CP178=2,Bill!N25,0) -> 0 | CQ180: 24 | CS180: =CV192 -> 0 | CT180: =IF(CS181="","",CU179) | CV180: =IF(CS181="","",(CV181-CS178+1)) | CW180: 300 | CX180: 160 | CY180: 120 | CZ180: 44317 | DA180: =CE285 -> 21230 | DJ180: =IF(CZ180=CU$178,CV$195,DJ179) -> 0 | DK180: =IF(CZ180=CU$178,CV$184,DJ180) -> 0 | DL180: =IF(DK180=0,"",DK180)
AO181: =ROUND(AQ181*10%,0) -> 0 | AP181: 43282 | AQ181: =IF(AY189=1,0,IF(AY189=2,BB190,IF(AY189=3,(BB190+BB191),BB193))) -> 0 | AR181: Total | AS181: =SUM(AQ181:AQ183) -> 0 | AT181: 29 | AU181: 44105 | AW181: ='DA Table'!Z235 -> 21820 | AX181: 8 | AY181: 44409 | BH181: 16 | BI181: UTI Retirment benefit Pension fund | BP181: 31 | BR181: 38 | BS181: 19050 | BT181: 19580 | BU181: 20110 | BV181: 24300 | BW181: 24950 | BX181: 25600 | BZ181: 24300 | CA181: 25600 | CB181: 25600 | CF181: =IF(CF180=0,0,CF180) -> 0 | CH181: 44470 | CI181: 18 | CJ181: =IF(CJ$178="","",ROUND(CJ$178/31*CI181,0)) -> 0 | CK181: =IF(CJ$175=1,0,IF(CJ$175=2,CJ181,IF(CJ$175=3,CI176))) -> 0 | CM181: 2 | CQ181: 25 | CR181: =CU178 | CS181: =IF(CT193=1,"",CV195) | CU181: =CT176 -> #N/A | CV181: =IF(CS181="","",DAY(CU181)) | CW181: 350 | CX181: 220 | CY181: 130 | CZ181: 44348 | DA181: =CE286 -> 21230 | DJ181: =IF(CZ181=CU$178,CV$195,DJ180) -> 0 | DK181: =IF(CZ181=CU$178,CV$184,DJ181) -> 0 | DL181: =IF(DK181=0,"",DK181)
AO182: =ROUND(AQ182*10%,0) -> 0 | AP182: 43466 | AQ182: =IF(AY190=1,0,IF(AY190=2,BC190,IF(AY190=3,(BC190+BC191),BC193))) -> 0 | AR182: Net | AS182: =SUM(BA174:BA175) -> 0 | AT182: 30 | AU182: 44136 | AW182: ='DA Table'!Z236 -> 21820 | AX182: 9 | AY182: 44440 | BH182: 17 | BI182: Subscription to NSC VIII Issue | BP182: 0 | BR182: 39 | BS182: 19580 | BT182: 20110 | BU182: 20680 | BV182: 24950 | BW182: 25600 | BX182: 26300 | BZ182: 24950 | CA182: 26300 | CB182: 26300 | CC182: 1 | CD182: PF | CF182: 1 | CH182: 44562 | CI182: 21 | CJ182: =IF(CJ$178="","",ROUND(CJ$178/31*CI182,0)) -> 0 | CK182: =IF(CJ$175=1,0,IF(CJ$175=2,CJ182,IF(CJ$175=3,CI176))) -> 0 | CM182: =L19 -> 0 | CQ182: 26 | CV182: =IF(CS181="","",(CV181-CV180)) | CW182: 525 | CX182: 350 | CY182: 140 | CZ182: 44378 | DA182: =CE287 -> 21230 | DJ182: =IF(CZ182=CU$178,CV$195,DJ181) -> 0 | DK182: =IF(CZ182=CU$178,CV$184,DJ182) -> 0 | DL182: =IF(DK182=0,"",DK182)
AR183: PF/ CPS | AS183: 0 | AT183: 31 | AU183: 44166 | AW183: ='DA Table'!Z237 -> 21820 | AX183: 10 | AY183: 44470 | BH183: 18 | BI183: LIC Annuity Plan (Jeevan Dhara, Jeevan Akhsay etc.) | BQ183: 31 | BR183: 40 | BS183: 20110 | BT183: 20680 | BU183: 21250 | BV183: 25600 | BW183: 26300 | BX183: 27000 | BZ183: 25600 | CA183: 27000 | CB183: 27000 | CC183: 2 | CD183: CPS | CG183: 2 | CI183: =IF(CF182=2,Bill!Y25,0) -> 0 | CJ183: =IF(CG183=1,CI183+CI183,CI183) -> 0 | CQ183: 27 | CR183: =CU178 | CS183: =IF(CS181="","",VLOOKUP(CR183,CD281:CE294,2,FALSE)) | CT183: =CS181 | CU183: =IF(CS181="","",ROUND(CS180*CV180/CV181,0)) | CV183: =IF(CS181="","",ROUND(CS181*CV182/CV181,0)) | CZ183: 44409 | DA183: =CE288 -> 21820 | DJ183: =IF(CZ183=CU$178,CV$195,DJ182) -> 0 | DK183: =IF(CZ183=CU$178,CV$184,DJ183) -> 0 | DL183: =IF(DK183=0,"",DK183)
AP184: =AQ181+AQ182 -> 0 | AW184: ='DA Table'!Z238 -> 21820 | AX184: 11 | AY184: 44501 | BH184: 19 | BI184: Subscription to deposit scheme of National Housing Bank | BR184: 41 | BS184: 20680 | BT184: 21250 | BU184: 21820 | BV184: 26300 | BW184: 27000 | BX184: 27700 | BZ184: 26300 | CA184: 27700 | CB184: 27700 | CD184: =VLOOKUP(CF182,CC182:CD183,2,0) -> PF | CE184: =IF(CD184=CD182,"PF",IF(CD184=CD183,"CPS")) -> PF | CQ184: 28 | CV184: =IF(CS181="","",(CU183+CV183)) | CZ184: 44440 | DA184: =CE289 -> 21820 | DJ184: =IF(CZ184=CU$178,CV$195,DJ183) -> 0 | DK184: =IF(CZ184=CU$178,CV$184,DJ184) -> 0 | DL184: =IF(DK184=0,"",DK184)
...

Sheet Bill
X2: =IF(DATA!CL274=1,"Select","") -> Select | Y2: =IF(DATA!CL274=1,"If You want to One or Two DA Arrears","") -> If You want to One or Two DA Arrears | AH2: Two
B4: =CONCATENATE(" Month wise Income of ",DATA!BN172," ",DATA!E10,", ",DATA!CD169,", ",DATA!E13," , ",DATA!E14,", ",DATA!E15," (","Mandal",")"," for the year of 2021-22") -> Month wise Income of Sri. A.Nagesh, Deputy Executive Engineer, Executive Engineer,TGP Division No.1 , Velgode, Velgode (Mandal) for the year of 2021-22
B6: S.No | C6: Month & Year | D6: Pay | E6: DA | F6: IR | G6: HRA | H6: =IF(DATA!CL274=2,"TS. Inc.","IR") -> IR | I6: =H6 -> IR | J6: HM Allowance | K6: =J6 -> HM Allowance | L6: SP/PP/Add. Inc. | M6: =L6 -> SP/PP/Add. Inc. | N6: A HRA | O6: =N6 -> A HRA | P6: DA Arrears | Q6: =P6 -> DA Arrears | R6: PHA | S6: =R6 -> PHA | T6: CCA | U6: =T6 -> CCA | V6: SCA | W6: =V6 -> SCA | X6: Gross Total | Y6: =DATA!CE184 -> PF | Z6: =Y6 -> PF | AA6: APGLI | AB6: =AA6 -> APGLI | AC6: P.Tax | AD6: GIS | AE6: =AD6 -> GIS | AF6: SWF/ EWF/ CMRF | AG6: EHF Deduction | AH6: Salary LIC | AI6: Adavance Tax | AJ6: Total Deduction | AK6: Net Amount | AL6: DA %
B7: 1 | C7: 44256 | D7: 55410 | E7: 16840 | G7: 6649 | H7: =IF(DATA!CR$273=2,IF(DATA!CL$274=2,DATA!L$24,DATA!CL283),ROUND(IF(DATA!CL$274=2,DATA!L$24,DATA!CL283)/2,0)) -> 5732 | I7: 14961 | J7: =IF(DATA!CR$273=2,DATA!L$13,ROUND(DATA!L$13/2,0)) -> 0 | K7: =IF(J7=0,"",J7) | L7: =IF(DATA!CR$273=2,DATA!CH283,ROUND(DATA!CH283/2,0)) -> 0 | M7: =IF(L7=0,"",L7) | N7: =IF(DATA!CR$273=2,DATA!CZ283,ROUND(DATA!CZ283/2,0)) -> 0 | O7: =IF(N7=0,"",N7) | R7: =IF(DATA!CR$273=2,DATA!CJ283,ROUND(DATA!CJ283/2,0)) -> 0 | S7: =IF(R7=0,"",R7) | T7: =IF(DATA!CR$273=2,IF(DATA!DK178=0,0,DATA!DK178),ROUND(IF(DATA!DK178=0,0,DATA!DK178)/2,0)) -> 0 | U7: =IF(T7=0,"",T7) | V7: =IF(DATA!CR$273=2,DATA!DF162,ROUND(DATA!DF162/2,0)) -> 0 | W7: =IF(V7=0,"",V7) | X7: =SUM(D7,E7,G7,I7,K7,M7,O7,Q7,S7,U7,W7) -> 93860 | Y7: =IF(DATA!CR$273=2,IF(X7=0,0,DATA!CP283)+AP7,"") -> 7000 | Z7: =IF(Y7=0,"",Y7) -> 7000 | AA7: =IF(DATA!CR$273=2,IF(X7=0,0,DATA!CQ283),"") -> 2000 | AB7: =IF(AA7=0,"",AA7) -> 2000 | AC7: =IF(DATA!CJ$175=1,IF(X7=0,0,DATA!CR283),"") -> 200 | AD7: =IF(DATA!CR$273=2,IF(X7=0,0,DATA!CS283),"") -> 120 | AE7: =IF(AD7=0,"",AD7) -> 120 | AF7: =IF(DATA!CR273=2,IF(X7=0,0,DATA!CT283),"") -> 50 | AG7: 300 | AH7: =IF(DATA!CR$273=2,DATA!CV283,"") | AI7: =IF(DATA!O29="","",DATA!O29) -> 8000 | AJ7: =SUM(Z7,AB7,AC7,AE7,AF7,AG7,AH7,AI7) -> 17670 | AK7: =X7-AJ7 -> 76190 | AL7: =DATA!BS267 -> 0.30392 | AO7: =IF(DATA!CL274=2,ROUND(D7/31,0),"") | AP7: =IF(DATA!CL$274=2,DATA!U$53,0) -> 0 | AW7: =IF(DATA!CL$274=2,DATA!Q$53,DATA!L$19) -> 0
B8: 2 | C8: 44287 | D8: 55410 | E8: 16840 | G8: 6649 | H8: 5732 | I8: 14961 | J8: 0 | L8: 0 | N8: 0 | R8: 0 | T8: 0 | V8: 0 | X8: 93860 | Y8: =IF(DATA!CR$273=2,IF(X8=0,0,DATA!CP284)+AP8,"") -> 7000 | Z8: =IF(Y8=0,"",Y8) -> 7000 | AA8: =IF(DATA!CR$273=2,IF(X8=0,0,DATA!CQ284),"") -> 2000 | AB8: =IF(AA8=0,"",AA8) -> 2000 | AC8: =IF(DATA!CJ$175=1,IF(X8=0,0,DATA!CR284),"") -> 200 | AD8: =IF(DATA!CR$273=2,IF(X8=0,0,DATA!CS284),"") -> 120 | AE8: =IF(AD8=0,"",AD8) -> 120 | AG8: 300 | AH8: =IF(DATA!CR$273=2,DATA!CV283,"") | AI8: =IF(DATA!O30="","",DATA!O30) -> 8000 | AJ8: =SUM(Z8,AB8,AC8,AE8,AF8,AG8,AH8,AI8) -> 17620 | AK8: =X8-AJ8 -> 76240 | AL8: =DATA!BS268 -> 0.30392 | AM8: =IF(AK8="",0,1) -> 1 | AP8: =IF(DATA!CL$274=2,DATA!U$53,0) -> 0 | AW8: =IF(DATA!CL$274=2,DATA!Q$53,DATA!L$19) -> 0
B9: 3 | C9: 44317 | D9: 55410 | E9: 16840 | G9: 6649 | H9: 5732 | I9: 14961 | J9: 0 | L9: 0 | N9: 0 | R9: 0 | T9: 0 | V9: 0 | X9: 93860 | Y9: =DATA!CV319 -> 7000 | Z9: =IF(Y9=0,"",Y9) -> 7000 | AA9: =DATA!CW319 -> 2000 | AB9: =IF(AA9=0,"",AA9) -> 2000 | AC9: =IF(DATA!CJ$175=1,IF(X9=0,0,DATA!CR285),"") -> 200 | AD9: =DATA!CY319 -> 120 | AE9: =IF(AD9=0,"",AD9) -> 120 | AG9: 300 | AH9: =IF(DATA!DA319=0,"",DATA!DA319) | AI9: =IF(DATA!O31="","",DATA!O31) -> 8000 | AJ9: =SUM(Z9,AB9,AC9,AE9,AF9,AG9,AH9,AI9) -> 17620 | AK9: =X9-AJ9 -> 76240 | AL9: =DATA!BS269 -> 0.30392 | AM9: =IF(AK9="",0,1) -> 1 | AP9: =IF(DATA!CL$274=2,DATA!U$53,0) -> 0 | AW9: =IF(DATA!CL$274=2,DATA!Q$53,DATA!L$19) -> 0
B10: 4 | C10: 44348 | D10: 55410 | E10: 16840 | G10: 6649 | H10: 5732 | I10: 14961 | J10: 0 | L10: 0 | N10: 0 | R10: 0 | T10: 0 | V10: 0 | X10: 93860 | Y10: =IF(X10=0,0,DATA!CP286)+AP7 -> 7000 | Z10: =IF(Y10=0,"",Y10) -> 7000 | AA10: =IF(X10=0,0,DATA!CQ286) -> 2000 | AB10: =IF(AA10=0,"",AA10) -> 2000 | AC10: =IF(DATA!CJ$175=1,IF(X10=0,0,DATA!CR286),"") -> 200 | AD10: =IF(X10=0,0,DATA!CS286) -> 120 | AE10: =IF(AD10=0,"",AD10) -> 120 | AG10: 300 | AH10: =DATA!CV286 | AI10: =IF(DATA!O32="","",DATA!O32) -> 8000 | AJ10: =SUM(Z10,AB10,AC10,AE10,AF10,AG10,AH10,AI10) -> 17620 | AK10: =X10-AJ10 -> 76240 | AL10: =DATA!BS270 -> 0.30392 | AM10: =IF(AK10="",0,1) -> 1 | AP10: =ROUND(DATA!AQ182*10/100,0) -> 0 | AW10: =IF(DATA!CL$274=2,DATA!Q$53,DATA!L$19) -> 0
B11: 5 | C11: 44378 | D11: 55410 | E11: 16840 | G11: 6649 | H11: 5732 | I11: 14961 | J11: 0 | L11: 0 | N11: 0 | R11: 0 | T11: 0 | V11: 0 | X11: 93860 | Y11: =IF(X11=0,0,DATA!CP287)+AP7 -> 7000 | Z11: =IF(Y11=0,"",Y11) -> 7000 | AA11: =IF(X11=0,0,DATA!CQ287) -> 2000 | AB11: =IF(AA11=0,"",AA11) -> 2000 | AC11: =IF(DATA!CJ$175=1,IF(X11=0,0,DATA!CR287),"") -> 200 | AD11: =IF(X11=0,0,DATA!CS287) -> 120 | AE11: =IF(AD11=0,"",AD11) -> 120 | AG11: 300 | AH11: =DATA!CV287 | AI11: =IF(DATA!Q29="","",DATA!Q29) -> 8000 | AJ11: =SUM(Z11,AB11,AC11,AE11,AF11,AG11,AH11,AI11) -> 17620 | AK11: =X11-AJ11 -> 76240 | AL11: =DATA!BS271 -> 0.33536 | AM11: =IF(AK11="",0,1) -> 1 | AO11: =IF(DATA!CF$182=2,AP10,AP12) -> 0 | AP11: =ROUND(DATA!AQ182*90/100,0) -> 0 | AW11: =IF(DATA!CL$274=2,DATA!Q$53,DATA!L$19) -> 0
B12: 6 | C12: 44409 | D12: 55410 | E12: 18582 | G12: 6649 | H12: =IF(DATA!CL$274=2,DATA!L$24,DATA!CL288) -> 5891 | I12: 14961 | J12: =DATA!L$13 -> 0 | K12: =IF(J12=0,"",J12) | L12: =DATA!CH288 -> 0 | M12: =IF(L12=0,"",L12) | N12: =DATA!CZ288 -> 0 | O12: =IF(N12=0,"",N12) | R12: =DATA!CJ288 -> 0 | S12: =IF(R12=0,"",R12) | T12: =IF(DATA!DK183=0,"",DATA!DK183) | U12: =T12 | V12: =DATA!DF167 -> 0 | W12: =IF(V12=0,"",V12) | X12: =SUM(D12,E12,G12,I12,K12,M12,O12,Q12,S12,U12,W12) -> 95602 | Y12: =IF(X12=0,0,DATA!CP288)+AP7 -> 7000 | Z12: =IF(Y12=0,"",Y12) -> 7000 | AA12: =IF(X12=0,0,DATA!CQ288) -> 2000 | AB12: =IF(AA12=0,"",AA12) -> 2000 | AC12: =IF(DATA!CJ$175=1,IF(X12=0,0,DATA!CR288),"") -> 200 | AD12: =IF(X12=0,0,DATA!CS288) -> 120 | AE12: =IF(AD12=0,"",AD12) -> 120 | AF12: =IF(DATA!CN196=1,Bill!#REF!,"") | AG12: 300 | AH12: =DATA!CV288 | AI12: =IF(DATA!Q30="","",DATA!Q30) -> 8000 | AJ12: =SUM(Z12,AB12,AC12,AE12,AF12,AG12,AH12,AI12) -> 17620 | AK12: =X12-AJ12 -> 77982 | AL12: =DATA!BS272 -> 0.33536 | AM12: =IF(AK12="",0,1) -> 1 | AP12: =SUM(AP10:AP11) -> 0 | AW12: =IF(DATA!CL$274=2,DATA!Q$53,DATA!L$19) -> 0
B13: 7 | C13: 44440 | D13: 55410 | E13: 18582 | G13: 6649 | H13: 5891 | I13: 14961 | J13: 0 | L13: 0 | N13: 0 | R13: 0 | V13: 0 | X13: 95602 | Y13: =IF(X13=0,0,DATA!CP289)+AP7 -> 7000 | Z13: =IF(Y13=0,"",Y13) -> 7000 | AA13: =IF(X13=0,0,DATA!CQ289) -> 2000 | AB13: =IF(AA13=0,"",AA13) -> 2000 | AC13: =IF(DATA!CJ$175=1,IF(X13=0,0,DATA!CR289),"") -> 200 | AD13: =IF(X13=0,0,DATA!CS289) -> 120 | AE13: =IF(AD13=0,"",AD13) -> 120 | AG13: 300 | AH13: =DATA!CV289 | AI13: =IF(DATA!Q31="","",DATA!Q31) -> 8000 | AJ13: =SUM(Z13,AB13,AC13,AE13,AF13,AG13,AH13,AI13) -> 17620 | AK13: =X13-AJ13 -> 77982 | AL13: =DATA!BS273 -> 0.33536 | AM13: =IF(AK13="",0,1) -> 1 | AW13: =IF(DATA!CL$274=2,DATA!Q$53,DATA!L$19) -> 0
B14: 8 | C14: 44470 | D14: 56870 | E14: 19072 | G14: 6824 | H14: 5891 | I14: 15355 | J14: 0 | L14: 0 | N14: 0 | R14: 0 | V14: 0 | X14: 98121 | Y14: =IF(X14=0,0,DATA!CP290)+AP7 -> 7000 | Z14: =IF(Y14=0,"",Y14) -> 7000 | AA14: =IF(X14=0,0,DATA!CQ290) -> 2000 | AB14: =IF(AA14=0,"",AA14) -> 2000 | AC14: =IF(DATA!CJ$175=1,IF(X14=0,0,DATA!CR290),"") -> 200 | AD14: =IF(X14=0,0,DATA!CS290) -> 120 | AE14: =IF(AD14=0,"",AD14) -> 120 | AG14: 300 | AH14: =DATA!CV290 | AI14: =IF(DATA!Q32="","",DATA!Q32) -> 8000 | AJ14: =SUM(Z14,AB14,AC14,AE14,AF14,AG14,AH14,AI14) -> 17620 | AK14: =X14-AJ14 -> 80501 | AL14: =DATA!BS274 -> 0.33536 | AM14: =IF(AK14="",0,1) -> 1 | AP14: AP | AQ14: TS | AW14: =IF(DATA!CL$274=2,DATA!Q$53,DATA!L$19) -> 0
B15: 9 | C15: 44501 | D15: 56870 | E15: 19072 | G15: 6824 | H15: 5891 | I15: 15355 | J15: 0 | L15: 0 | N15: 0 | R15: 0 | V15: 0 | X15: 98121 | Y15: =IF(X15=0,0,DATA!CP291)+AP7 -> 7000 | Z15: =IF(Y15=0,"",Y15) -> 7000 | AA15: =IF(X15=0,0,DATA!CQ291) -> 2000 | AB15: =IF(AA15=0,"",AA15) -> 2000 | AC15: =IF(DATA!CJ$175=1,IF(X15=0,0,DATA!CR291),"") -> 200 | AD15: =IF(X15=0,0,DATA!CS291) -> 120 | AE15: =IF(AD15=0,"",AD15) -> 120 | AG15: 300 | AH15: =DATA!CV291 | AI15: =IF(DATA!T29="","",DATA!T29) -> 8000 | AJ15: =SUM(Z15,AB15,AC15,AE15,AF15,AG15,AH15,AI15) -> 17620 | AK15: =X15-AJ15 -> 80501 | AL15: =DATA!BR275 -> 0.30392 | AM15: =IF(AK15="",0,1) -> 1 | AO15: =IF(DATA!CF$182=2,AQ15,0) -> 0 | AP15: =ROUND(DATA!AQ181*10/100,0) -> 0 | AQ15: =ROUND(DATA!AT183*10/100,0) -> 3 | AW15: =IF(DATA!CL$274=2,DATA!Q$53,DATA!L$19) -> 0
B16: 10 | C16: 44531 | D16: 56870 | E16: 19072 | G16: 6824 | H16: 5891 | I16: 15355 | J16: 0 | L16: 0 | N16: 0 | R16: 0 | V16: 0 | X16: 98121 | Y16: =IF(X16=0,0,DATA!CP292) -> 7000 | Z16: =IF(Y16=0,"",Y16) -> 7000 | AA16: =IF(X16=0,0,DATA!CQ292) -> 2000 | AB16: =IF(AA16=0,"",AA16) -> 2000 | AC16: =IF(DATA!CJ$175=1,IF(X16=0,0,DATA!CR292),"") -> 200 | AD16: =IF(X16=0,0,DATA!CS292) -> 120 | AE16: =IF(AD16=0,"",AD16) -> 120 | AF16: 100 | AG16: 300 | AI16: =IF(DATA!T30="","",DATA!T30) -> 20000 | AJ16: =SUM(Z16,AB16,AC16,AE16,AF16,AG16,AH16,AI16) -> 29720 | AK16: =X16-AJ16 -> 68401 | AL16: =DATA!BR276 -> 0.30392 | AM16: =IF(AK16="",0,1) -> 1 | AO16: =IF(DATA!CF$182=2,AP15,AP17) -> 0 | AP16: =ROUND(DATA!AQ181*90/100,0) -> 0 | AQ16: =ROUND(DATA!AT183*90/100,0) -> 28 | AW16: =IF(DATA!CL$274=2,"",DATA!L$19) -> 0
B17: 11 | C17: 44562 | D17: 56870 | E17: 22052 | G17: 6824 | H17: 5891 | I17: 15355 | J17: 0 | L17: 0 | N17: 0 | R17: 0 | V17: 0 | X17: 101101 | Y17: =IF(X17=0,0,DATA!CP293) -> 7000 | Z17: =IF(Y17=0,"",Y17) -> 7000 | AA17: =IF(X17=0,0,DATA!CQ293) -> 2000 | AB17: =IF(AA17=0,"",AA17) -> 2000 | AC17: =IF(DATA!CJ$175=1,IF(X17=0,0,DATA!CR293),"") -> 200 | AD17: =IF(X17=0,0,DATA!CS293) -> 120 | AE17: =IF(AD17=0,"",AD17) -> 120 | AG17: 300 | AH17: =DATA!CV293 | AI17: =IF(DATA!T31="","",DATA!T31) | AJ17: =SUM(Z17,AB17,AC17,AE17,AF17,AG17,AH17,AI17) -> 9620 | AK17: =X17-AJ17 -> 91481 | AL17: =DATA!BR277 -> 0.33536 | AM17: =IF(AK17="",0,1) -> 1 | AO17: =IF(DATA!CF$182=2,AQ15,AQ17) -> 31 | AP17: =SUM(AP15:AP16) -> 0 | AQ17: =SUM(AQ15:AQ16) -> 31 | AW17: =IF(DATA!CL$274=2,"",DATA!L$19) -> 0
B18: 12 | C18: 44593 | D18: 56870 | E18: 22052 | G18: 6824 | H18: 5891 | I18: 15355 | J18: 0 | L18: 0 | N18: 0 | R18: 0 | V18: 0 | X18: 101101 | Y18: =IF(X18=0,0,DATA!CP294) -> 7000 | Z18: =IF(Y18=0,"",Y18) -> 7000 | AA18: =IF(X18=0,0,DATA!CQ294) -> 2000 | AB18: =IF(AA18=0,"",AA18) -> 2000 | AC18: =IF(DATA!CJ$175=1,IF(X18=0,0,DATA!CR294),"") -> 200 | AD18: =IF(X18=0,0,DATA!CS294) -> 120 | AE18: =IF(AD18=0,"",AD18) -> 120 | AG18: 300 | AH18: =DATA!CV294 | AI18: =IF(DATA!T32="","",DATA!T32) | AJ18: =SUM(Z18,AB18,AC18,AE18,AF18,AG18,AH18,AI18) -> 9620 | AK18: =X18-AJ18 -> 91481 | AL18: =DATA!BR278 -> 0.33536 | AM18: =IF(AK18="",0,1) -> 1 | AT18: =IF(DATA!CL$274=2,DATA!#REF!,0) -> 0 | AW18: =IF(DATA!CL$274=2,"",DATA!L$19) -> 0
B19: 13 | C19: SEL for 15 days | D19: 27705 | E19: 8420 | G19: 3325 | X19: 39450 | Y19: =IF(DATA!CL$274=1,AO16,AO17) -> 0 | Z19: =Y19 -> 0 | AJ19: =Z19 -> 0 | AK19: =X19-AJ19 -> 39450 | AM19: =IF(AK19="",0,1) -> 1
C20: pay fixation Arrears | Y20: =IF(DATA!CL$274=1,AO11,0) -> 0 | AL20: =IF(DATA!CL274=1,AP12,0) -> 0 | AM20: =IF(AK20="",0,1) -> 0
B21: 15 | C21: July DA - 1 M | D21: =AT21 | E21: 1742 | G21: =AV21 | L21: =AX21 | R21: =AW21 -> 0 | T21: =AY21 | X21: 1742 | AK21: =IF(X21="","",(X21-AJ21)) -> 1742 | AM21: =IF(AK21="",0,1) -> 1 | AS21: =IF(C21="","",DATA!BH280+DATA!BI282+DATA!BJ282+DATA!BL285+DATA!BO295+DATA!BL293) -> #VALUE! | AT21: =IF(DATA!BK289=1,DATA!BH280,"") | AU21: =IF(DATA!BK289=1,DATA!BI282,"") | AV21: =IF(DATA!BK289=1,DATA!BJ282,"") | AX21: =IF(DATA!BK289=1,DATA!BO295,"") | AY21: =IF(DATA!BK289=1,DATA!BL293,"")
B22: 18 | C22: DA - 1 (1,2,3) | D22: =DATA!CE304 | E22: 52244 | G22: =IF(DATA!CG304=0,"",DATA!CG304) | H22: =AZ22 | I22: =IF(DATA!CK304=0,"",DATA!CK304) | L22: =IF(C22="","",DATA!CH304) -> 0 | R22: =DATA!CJ304 | T22: =IF(C22="","",DATA!CI304) -> 0 | X22: 52244 | Y22: =DATA!CO304 | Z22: 52244 | AJ22: =IF(D22="","",SUM(Z22,AB22,AC22,AE22,AF22,AG22,AH22,AI22)) | AK22: 0 | AM22: =IF(AK22="",0,1) -> 1 | AZ22: =IF(DATA!CL$274=1,DATA!CK304,"")
B23: 19 | C23: DA - 2 (1,2,3) | D23: =DATA!CE305 | E23: 53473 | G23: =IF(DATA!CG305=0,"",DATA!CG305) | H23: =AZ23 | L23: =IF(C23="","",DATA!CH305) -> 0 | R23: =DATA!CJ305 | T23: =IF(C23="","",DATA!CI305) -> 0 | X23: 53473 | Y23: =DATA!CO305 | Z23: 53473 | AJ23: =IF(D23="","",SUM(Z23,AB23,AC23,AE23,AF23,AG23,AH23,AI23)) | AK23: 0 | AM23: =IF(AK23="",0,1) -> 1 | AZ23: =IF(DATA!CL$274=1,DATA!CK305,"")
B24: 21 | C24: =IF(DATA!L15="","","Child Fee Conces") | X24: =IF(DATA!L15="","",DATA!L15) | AK24: =IF(X24="","",X24-AJ24) | AM24: =IF(AK24="",0,1) -> 0
C25: Grand Totals | D25: =SUM(D7:D24) -> 699925 | E25: =SUM(E7:E24) -> 338563 | G25: =SUM(G7:G24) -> 83988 | H25: =SUM(H7:H24) -> 69897 | I25: =SUM(I7:I24) -> 181502 | J25: =SUM(J7:J24) -> 0 | K25: =SUM(K7:K24) -> 0 | L25: =SUM(L7:L24) -> 0 | M25: =SUM(M7:M24) -> 0 | N25: =SUM(N7:N24) -> 0 | ... AJ25: =SUM(AJ7:AJ24) -> 207590 | AK25: =X25-AJ25 -> 1096388
D29: Signature of the DDO | AF29: Signature of the Employee
B32: Prepared by: C.Ramanjaneyulu, S.A (P.S), www.teacherNews.in

Sheet Annexure -I I
B2: =IF(DATA!$AH$49=2,"Old Tax IT Calculation","New Tax IT Calculation") -> Old Tax IT Calculation
B4: Financial Year 2021-22 | G4: ANNEXURE - II | K4: Assessment year 2022-23
B5: =IF(DATA!$AH$49=1,"INCOME TAX CALCULATION 2021-22 (New Regime)","INCOME TAX CALCULATION 2021-22 (Old Regime)") -> INCOME TAX CALCULATION 2021-22 (Old Regime)
B6: Name | D6: =CONCATENATE(DATA!BN172," ",DATA!E10) -> Sri. A.Nagesh | H6: Office/ School: | I6: =CONCATENATE(DATA!E21," , ",DATA!E22," (","Mandal",")"," ") -> Velgode , Velgode (Mandal)
B7: Designation | D7: =DATA!CD169 -> Deputy Executive Engineer | H7: Address: | I7: =CONCATENATE(DATA!E13,",",DATA!E14,",",DATA!E15," ( Mandal )") -> Executive Engineer,TGP Division No.1,Velgode,Velgode ( Mandal )
C8: Whether living in | F8: =DATA!CF177 -> Rented House | H8: =CONCATENATE("PAN No : ",DATA!E12) -> PAN No : | J8: Treasury Id. No. | L8: =IF(DATA!E18="","",DATA!E18)
B9: 1 | C9: Gross Salary……… | J9: Rs. | L9: =Bill!X25 -> 1303978
B10: 2 | C10: H.R.A. Exemption as per eligibility U/s 10(13-A) | Y10: =Bill!D25+Bill!E25 -> 1038488
C11: a) | D11: Actual HRA received | J11: Rs. | K11: =IF(DATA!AH49=1,"",Bill!G25+Bill!N25) -> 83988
C12: b) | D12: Actual House Rent paid by you minus 10% of your Salary | I12: =IF(DATA!AH49=1,"",IF(DATA!CE178=2,"",CONCATENATE("Rent @ ",DATA!S11))) -> Rent @ 12000 | J12: Rs. | K12: =IF(DATA!AH49=1,"",IF(AC25=1,"",DATA!CF176)) -> 40150 | M12: House rent paid monthly | P12: =DATA!S11 -> 12000 | Q12: X 12 | U12: =ROUND(DATA!S11*12,0) -> 144000
C13: c) | D13: 40% of Salary (Salary means Basic Pay+D.A) | J13: Rs. | K13: =IF(DATA!AH49=1,"",IF(AC25=1,"",DATA!CF244)) -> 415396 | L13: =MIN(K11:K13) -> 40150 | P13: 10% of salary | U13: =ROUND(Y10*10%,-1) -> 103850 | W13: =CONCATENATE(" ( Pay - ",Bill!D25," + DA - ",Z13," )") -> ( Pay - 699925 + DA - 338563 ) | Z13: =IF(DATA!CH262=1,0,Bill!E25) -> 338563
J14: Rs. | L14: =K14 -> 0
B15: 3 | C15: Total Salary (1-2) | J15: Rs. | L15: =L9-L13 -> 1263828 | Q15: -- | U15: =ROUND(U12-U13,0) -> 40150 | Y15: =U13+Bill!G25 -> 187838
B16: 4 | C16: Deductions from Salary Income | Y16: =ROUND(Y15/12,-2)+100 -> 15800
C17: a) | D17: Exemption from Conveyance Allowance U/s. 10(14) (i) | J17: Rs. | K17: =IF(DATA!AH49=1,"",DATA!CI245) -> 0
C18: b) | D18: Profession Tax U/s 16 (3) B | J18: Rs. | K18: =IF(DATA!AH49=1,"",IF(AC25=1,"",Bill!AC25)) -> 2400 | L18: =IF(DATA!AH49=1,0,IF(DATA!CJ175=1,(DATA!CG243+DATA!CJ245),MAX(K17:K18))) -> 2400
B19: 5 | C19: Income From Salary (3-4) | J19: Rs. | L19: =L15-L18 -> 1261428
B20: 6 | C20: Less: Standard deduction- u/s16 (Ia) | I20: =IF(DATA!BQ238=1,DATA!N38,"") | J20: =IF(DATA!BQ238=1,DATA!Q38,"") | L20: =IF(DATA!AH49=1,0,50000) -> 50000
B21: 7 | C21: Net Income from Salary (5-6) | I21: =IF(DATA!BQ238=1,DATA!N39,"") | J21: =IF(DATA!BQ238=1,DATA!Q39,"") | L21: =L19-L20 -> 1211428
B22: 8 | C22: =DATA!BB209 -> Income From other sources | I22: =IF(DATA!BQ238=1,DATA!N40,"") | J22: =IF(DATA!BQ238=1,DATA!Q40,"") | L22: =DATA!G38 -> 0 | AC22: New Tax Slab
C23: =DATA!BB210 -> Income From Capital Gains | I23: =IF(DATA!BQ238=1,"Interest Paid on Housing Loan","") | J23: =IF(DATA!BQ238=1,DATA!BQ229,"") | L23: =DATA!G39 -> 0 | AC23: Old Tax Slab
B24: 9 | C24: =DATA!BN239 -> Income | E24: from House Property U/s 24 (vi) | I24: =IF(DATA!BQ238=1,DATA!N41,"") | J24: =IF(DATA!BQ238=1,DATA!Q41,"") | L24: =IF(M24="",0,M24) -> 0 | M24: =CONCATENATE("",DATA!BM239) | AA24: =IF(AA25>AA31,AA31,AA25) -> 0
B25: 10 | C25: Gross Total Income (7+8+9) | L25: =SUM(L21:L23)+L24 -> 1211428 | Z25: =IF(X27>X28,Z27,Z26) -> 84000 | AA25: =IF(Z31>Z25,(Z31-Z25),IF(Z31<Z25,-(Z31-Z25),0)) -> 0 | AC25: =DATA!AH49 -> 2
B26: 11 | C26: Deductions | Z26: =IF(Y27<X28,Z31,Z27) -> 84000
C27: a) | D27: 80G | E27: E.W.F. & S.W.F & CMRF | J27: Rs. | K27: =IF(DATA!AH49=1,"",Bill!AF25) -> 150 | X27: =Bill!Y25+Bill!AA25+Bill!AD25+Bill!AH25+K41+K42+K43+K44+K45 -> 109440 | Y27: =Bill!AA25+Bill!AD25+Bill!AH25+K41+K42+K43+K44+K45 -> 25440 | Z27: =IF(Y27>X28,0,IF(Y27<X28,-(Y27-X28))) -> 124560
C28: b) | D28: =DATA!BL211 -> 80EE | E28: =DATA!BO190 -> Interest of Housing Loan 80EE | J28: Rs. | K28: =IF(DATA!AH49=1,"",DATA!BP193) -> 0 | X28: 150000
C29: c) | D29: =DATA!BL212 -> 80EEA | E29: =DATA!BO191 -> Interest of HBA Loan 80EEA | J29: Rs. | K29: =IF(DATA!AH49=1,"",DATA!BP194) -> 0 | X29: =IF((X27-X28)>0,(X27-X28),IF((X27-X28)<0,0)) -> 0
C30: d) | D30: =DATA!BL170 -> 24B | E30: =DATA!BO189 -> Interest of Housing Loan Section 24 | J30: Rs. | K30: =IF(DATA!AH49=1,"",DATA!BQ192) -> 0
C31: e) | D31: 80U | E31: =DATA!BL223 -> Disabled Person (PH)-above 40% disability ( Rule 11A) | J31: Rs. | K31: =IF(DATA!AH49=1,"",DATA!BL225) -> 0 | Z31: =Bill!Y25 -> 84000 | AA31: 50000
C32: f) | D32: 80d | E32: Employees Health Cards Premium in AP | J32: Rs. | K32: =IF(DATA!AH49=1,"",IF(AC25=1,"",Bill!AG25)) -> 3600 | Z32: =IF(DATA!CF174=1,Bill!Y25,Z25) -> 84000
C34: TOTAL----------- | J34: Rs. | K34: =SUM(K27:K33) -> 3750 | L34: =K34 -> 3750
B35: 12 | C35: Gross Total Income (10-11) | J35: Rs. | L35: =IF((L25-L34)>0,(L25-L34),IF((L25-L34)<0,0)) -> 1207678
B36: 13 | C36: Savings U/s 80C ( Limited to Rs.1,50,000 )
C37: a) | D37: =IF(DATA!CF182=1,DATA!CD182,"CPS Employees Contribution Amount U/s 80CCD 1") -> PF | I37: =CONCATENATE("No. : ",DATA!O23) -> No. : | J37: Rs. | K37: =IF(DATA!AH49=1,"",Bill!Z25) -> 189717
C38: b) | D38: APGLI | F38: A/C No: | G38: =DATA!S23 -> 0 | J38: Rs. | K38: =IF(DATA!AH49=1,"",Bill!AB25) -> 24000
C39: c) | D39: GIS | J39: Rs. | K39: =IF(DATA!AH49=1,"",Bill!AE25) -> 1440
C40: d) | D40: LIC Policies Monthly Premium in Salary | J40: Rs. | K40: =IF(DATA!AH49=1,"",Bill!AH25) -> 0
C41: e) | D41: =DATA!BI189 -> LIC Policies premium - Yearly | J41: Rs. | K41: =IF(DATA!AH49=1,"",DATA!G27) -> 0
C42: f) | D42: =DATA!BI190 -> Exide Life Insurance | J42: Rs. | K42: =IF(DATA!AH49=1,"",DATA!G28) -> 0
C43: g) | D43: =DATA!BG189 -> Sukanya Samruddhi Yojana | J43: Rs. | K43: =IF(DATA!AH49=1,"",DATA!G29) -> 0
C44: h) | D44: =DATA!BG190 -> PLI (Postal Life Insurance) | J44: Rs. | K44: =IF(DATA!AH49=1,"",DATA!G30) -> 0
C45: j) | D45: =DATA!BG191 -> Housing Loan Principal Amount | J45: Rs. | K45: =IF(DATA!AH49=1,"",DATA!G26) -> 0
C46: Total Savings (Deductions) u/s 80C, 80CCC, 80CCD | J46: Rs. | K46: =SUM(K37:K45) -> 215157 | L46: =IF(K46>=150000,150000,IF(K46<150000,K46)) -> 150000
D47: =IF(DATA!CF182=1,"National Pension Scheme U/s 80CCD (1B) ","Additional Benefit CPS Employees NPS U/s 80CCD 1B ") -> National Pension Scheme U/s 80CCD (1B) | J47: Rs. | K47: =IF(DATA!AH49=1,0,IF(DATA!CF182=2,AA24,DATA!BF199)) -> 0 | L47: =K47 -> 0
C48: =DATA!BE200 -> 80TTA | D48: =DATA!BC200 -> Intrest on Saving Account ( Not Fixed Deposit ) | K48: =IF(DATA!AH49=1,0,DATA!BF200) -> 0 | L48: =K48 -> 0
B50: 14 | C50: Net Taxable Income (12-13) Rounded nearest 10 ruppes | L50: =ROUND(O50,-1) -> 1057680 | N50: =L46+L47+L48 -> 150000 | O50: =IF((L35-N50)>0,(L35-N50),IF((L35-N50)<0,0)) -> 1057678 | R50: Tax | S50: Income Tax | T50: Taxble Inc | U50: Tax %
B51: 15 | C51: Tax on Income | J51: =CONCATENATE("Tax Rs. ",DATA!CU261) -> Tax Rs. 807680 | R51: - | S51: 250000 | T51: =S51 -> 250000 | U51: 0 | AE51: 0 -250000 | AF51: =AJ51*AI51 -> 0 | AG51: 250000 | AI51: =AG51 -> 250000 | AJ51: 0
C52: a) | D52: Upto-2,50,000 | J52: Rs. | L52: Nil | N52: =CONCATENATE(L50," - ",250000) -> 1057680 - 250000 | P52: =CONCATENATE("= ",DATA!CU261) -> = 807680 | R52: =MAX(0,MIN(T51*U52,T$52*U52)) -> 12500 | S52: =S51+S51 -> 500000 | T52: =IF((L50-T51)<=0,0,(L50-T51)) -> 807680 | U52: 0.05 | V52: =IF(T52>=T51,T51,T52) -> 250000 | AE52: 250001 - 500000 | AF52: =MAX(0,MIN(AJ52*AI52,AJ52*AH52)) -> 12500 | AG52: 500000 | AH52: =AG52-AG51 -> 250000 | AI52: =L50-AI51 -> 807680 | AJ52: 0.05 | AK52: =IF(AH52<=AI52,AH52,AI52) -> 250000
C53: b) | D53: =IF(L53=0,"","2,50,001/- to 5,00,000/- 5% ") -> 2,50,001/- to 5,00,000/- 5% | H53: =IF(L53=0,"",(IF(DATA!AH49=1,CONCATENATE("( ",AL63," @"," 5% )"),CONCATENATE("( ",AK52," @"," 5% )")))) -> ( 250000 @ 5% ) | J53: Rs. | L53: =IF(DATA!AH49=1,AF63,AF52) -> 12500 | R53: =MAX(0,MIN(T53*U53,T$51*U53)) -> 50000 | S53: =S51+S52 -> 750000 | T53: =IF((T52-S51)<=0,0,(T52-S51)) -> 557680 | U53: =IF(DATA!AH49=1,10%,20%) -> 0.2 | V53: =IF(T53>=S52,S52,T53) -> 500000 | AE53: 500001 - 1000000 | AF53: =MAX(0,MIN(AJ53*AI53,AJ53*AH53)) -> 100000 | AG53: 1000000 | AH53: =AG53-AG52 -> 500000 | AI53: =AI52-AH52 -> 557680 | AJ53: 0.2 | AK53: =IF(AH53<=AI53,AH53,AI53) -> 500000
C54: c) | D54: =IF(L54=0,"",(IF(DATA!AH49=1,"5,00,001/- to 7,50,000/- 10% ","5,00,001/- to 10,00,000/- 20% "))) -> 5,00,001/- to 10,00,000/- 20% | H54: =IF(L54=0,"",(IF(DATA!AH49=1,CONCATENATE("( ",AL64," @"," 10% )"),CONCATENATE("( ",AK53," @"," 20% )")))) -> ( 500000 @ 20% ) | J54: Rs. | L54: =IF(DATA!AH49=1,AF64,AF53) -> 100000 | R54: =MAX(0,MIN(T54*U54,T$51*U54)) -> 50000 | S54: =S53+S51 -> 1000000 | T54: =IF((T53-S51)<=0,0,(T53-S51)) -> 307680 | U54: =IF(DATA!AH49=1,15%,20%) -> 0.2 | V54: =IF(T54>=S53,S53,T54) -> 307680 | AE54: 1000001 + | AF54: =MAX(0,MIN(AJ54*AI55,AJ54*AH54)) -> 17304 | AH54: =L50-AG53 -> 57680 | AI54: =AI53-AH53 -> 57680 | AJ54: 0.3 | AK54: =IF(AH54<=AI54,AH54,AI54) -> 57680
C55: d) | D55: =IF(L55=0,"",(IF(DATA!AH49=1,"7,50,001/- to 10,00,000/- 15% ","10,00,001/ Above - 30% "))) -> 10,00,001/ Above - 30% | H55: =IF(L55=0,"",(IF(DATA!AH49=1,CONCATENATE("( ",AL65," @"," 15% )"),CONCATENATE("( ",AK54," @"," 30% )")))) -> ( 57680 @ 30% ) | J55: Rs. | L55: =IF(DATA!AH49=1,AF65,AF54) -> 17304 | R55: =MAX(0,MIN(T55*U55,T$51*U55)) -> 17304 | S55: =S54+S51 -> 1250000 | T55: =IF((T54-S51)<=0,0,(T54-S51)) -> 57680 | U55: =IF(DATA!AH49=1,20%,30%) -> 0.3 | V55: =IF(T55>=S54,S54,T55) -> 57680 | AE55: Total Tax | AF55: =SUM(AF50:AF54) -> 129804 | AI55: =AI53-AH53 -> 57680
C56: e) | D56: =IF(L56=0,"",(IF(DATA!AH49=1,"10,00,001/- to 12,50,000/- 20% ",""))) | H56: =IF(L56=0,"",(IF(DATA!AH49=1,CONCATENATE("( ",AL66," @"," 20% )"),""))) | L56: =IF(DATA!AH49=1,AF66,0) -> 0 | R56: =MAX(0,MIN(T55*U56,T$51*U56)) -> 17304 | S56: =S55+S51 -> 1500000 | T56: =IF((T55-S51)<=0,0,(T55-S51)) -> 0 | U56: =IF(DATA!AH49=1,25%,30%) -> 0.3 | V56: =IF(T56>=S55,S55,T56) -> 0
C57: f) | D57: =IF(L57=0,"",(IF(DATA!AH49=1,"12,50,001/- to 15,00,000/- 25% ",""))) | H57: =IF(L57=0,"",(IF(DATA!AH49=1,CONCATENATE("( ",AL67," @"," 25% )"),""))) | L57: =IF(DATA!AH49=1,AF67,0) -> 0 | R57: =MAX(0,MIN(T56*U57,T$51*U57)) -> 0 | S57: =CONCATENATE(S56," + ") -> 1500000 + | T57: =IF((T56-S51)<=0,0,(T56-S51)) -> 0 | U57: 0.3 | V57: =IF(T57>=S56,S56,T57) -> 0 | AH57: 4% Cess | AI57: =ROUND(AF55*4%,0) -> 5192
C58: g) | D58: =IF(L58=0,"",(IF(DATA!AH49=1,"Above 15,00,000 - 30%",""))) | H58: =IF(L58=0,"",(IF(DATA!AH49=1,CONCATENATE("( ",AL68," @"," 30% )"),""))) | L58: =IF(DATA!AH49=1,AF68,0) -> 0
B59: 16 | C59: Tax Rebate ( U/s 87 A) ( Rs. 12500/-upto Rs.5,00,000 Taxble Income ) | J59: Rs. | L59: =IF(AND(L50<=500000,L50>250000),DATA!CP265,0) -> 0 | N59: =CONCATENATE("If Taxble income "," ",L60," ","deduction ",L59) -> If Taxble income 129804 deduction 0
B60: 17 | C60: Total Tax Payable (15-16) | L60: =IF(((L53-L59)+L54+L55+L56+L57+L58)>0,((L53-L59)+L54+L55+L56+L57+L58),0) -> 129804 | R60: =SUM(R52:R59) -> 147108 | S60: Total Tax
B61: 18 | C61: Cess (Health 1% + Education 3% ) | J61: Rs. | L61: =IF(L60=0,0,AF72) -> 5192 | T61: 4% Cess | U61: =ROUND(R60*4%,0) -> 5884 | AE61: Income Tax for General | AF61: Tax | AG61: Tax Slabs | AH61: Incremental | AI61: Taxable Inc | AJ61: Tax Bracket
AE62: 0 - 2.5 | AF62: =AJ62*AI62 -> 0 | AG62: 250000 | AI62: =AG62 -> 250000 | AJ62: 0
B63: 19 | C63: Total (17+18) | J63: Rs. | L63: =L60+L61 -> 134996 | AE63: 2.5 - 5 | AF63: =MAX(0,MIN(AJ63*AI63,AJ63*AH63)) -> 12500 | AG63: 500000 | AH63: =AG63-AG62 -> 250000 | AI63: =L50-AI62 -> 807680 | AJ63: 0.05 | AL63: =IF(AH63<=AI63,AH63,AI63) -> 250000
B64: 20 | C64: Less Relief Under Section 89 (1) (Attatched details) | J64: Rs. | L64: =IF(M65>0,M65,0) -> 0 | AE64: 5 - 7.5 | AF64: =MAX(0,MIN(AJ64*AI64,AJ64*AH64)) -> 25000 | AG64: 750000 | AH64: =AG64-AG63 -> 250000 | AI64: =AI63-AH63 -> 557680 | AJ64: 0.1 | AL64: =IF(AH64<=AI64,AH64,AI64) -> 250000
B65: 21 | C65: Total Advance Tax Deductions | L65: =SUM(F67:F72)+SUM(H67:H72) -> 92000 | M65: =ROUND('Form 10E'!U61,0) -> 0 | N65: =IF((N66-L65)>0,(N66-L65),0) -> 42996 | O65: =-(N66-L65) -> -42996 | X65: =SUM(F67:F69) -> 24000 | AE65: 7.5 - 10 | AF65: =MAX(0,MIN(AJ65*AI65,AJ65*AH65)) -> 37500 | AG65: 1000000 | AH65: =AG65-AG64 -> 250000 | AI65: =AI64-AH64 -> 307680 | AJ65: 0.15 | AL65: =IF(AH65<=AI65,AH65,AI65) -> 250000
C66: Details of Adv.Tax Deductions | N66: =IF((L63-L64)>0,(L63-L64),0) -> 134996 | O66: =L63-L64 -> 134996 | X66: =SUM(F70:F72) -> 24000 | AE66: 10 - 12.5 | AF66: =MAX(0,MIN(AJ66*AI66,AJ66*AH66)) -> 11536 | AG66: 1250000 | AH66: =AG66-AG65 -> 250000 | AI66: =AI65-AH65 -> 57680 | AJ66: 0.2 | AL66: =IF(AH66<=AI66,AH66,AI66) -> 57680
E67: 44256 | F67: =IF(Bill!AI7="","",Bill!AI7) -> 8000 | G67: 44440 | H67: =IF(Bill!AI13="","",Bill!AI13) -> 8000 | J67: =O69 -> Net Tax to be Paid | L67: =O70 -> 42996 | X67: =SUM(H67:H69) -> 24000 | AE67: 12.5 - 15 | AF67: =MAX(0,MIN(AJ67*AI67,AJ67*AH67)) -> 0 | AG67: 1500000 | AH67: =AG67-AG66 -> 250000 | AI67: =AI66-AH66 -> -192320 | AJ67: 0.25 | AL67: =IF(AH67<=AI67,AH67,AI67) -> -192320
E68: 44287 | F68: =IF(Bill!AI8="","",Bill!AI8) -> 8000 | G68: 44470 | H68: =IF(Bill!AI14="","",Bill!AI14) -> 8000 | N68: =IF(N65>0,N65,"No Tax") -> 42996 | O68: =IF(N65>0,N65,O65) -> 42996 | X68: =SUM(H70:H72) -> 20000 | AE68: 15+ | AF68: =MAX(0,MIN(AJ68*AI68,AJ68*AH68)) -> 0 | AH68: =L50-AG67 -> -442320 | AI68: =AI67-AH67 -> -442320 | AJ68: 0.3 | AL68: =IF(AH68<=AI68,AH68,AI68) -> -442320
E69: 44317 | F69: =IF(Bill!AI9="","",Bill!AI9) -> 8000 | G69: 44501 | H69: =IF(Bill!AI15="","",Bill!AI15) -> 8000 | O69: =IF(L65<=N66,"Net Tax to be Paid","Tax to be Refundable") -> Net Tax to be Paid | Q69: Tax to be Refundable | AE69: Total Tax | AF69: =SUM(AF62:AF68) -> 86536
E70: 44348 | F70: =IF(Bill!AI10="","",Bill!AI10) -> 8000 | G70: 44531 | H70: =IF(Bill!AI16="","",Bill!AI16) -> 20000 | O70: =IF(N66=L65,N68,O68) -> 42996 | AH70: 4% Cess | AI70: =ROUND(AF69*4%,0) -> 3461
E71: 44378 | F71: =IF(Bill!AI11="","",Bill!AI11) -> 8000 | G71: 44562 | H71: =IF(Bill!AI17="","",Bill!AI17)
E72: 44409 | F72: =IF(Bill!AI12="","",Bill!AI12) -> 8000 | G72: 44593 | H72: =IF(Bill!AI18="","",Bill!AI18) | AF72: =IF(DATA!AH49=1,CONCATENATE(" ",AI70),CONCATENATE(" ",AI57)) -> 5192
B73: =DATA!CM240 -> Undertaking Certificate
B74: =CONCATENATE(" ",DATA!CM238) -> This is to certify that I have paid an amount of Rs.144000 (One Lakh Fourty Four Thousands and only) towards house rent year 2021 - 2022. (Rent 12000 per month X 12 months) )
B78: Signature of the Drawing Officer | I78: Signature of the Employee
B81: Prepared by: C.Ramanjaneyulu, S.A(P.S) www.teacherNews.in

Sheet Form-16
B2: =IF(DATA!AH49=1,"FORM No. 16 - New Regime","FORM No. 16 - Old Regime") -> FORM No. 16 - Old Regime
B3: ( Vide rule 31(1)(a) of Income Tax Rules, 1962 )
B4: for Tax deducted at source from income chargeable under the head "salaries"
B5: NAME AND ADDRESS OF THE EMPLOYER | G5: NAME AND DESIGNATION OF THE EMPLOYEE
B6: =CONCATENATE("Sri./Smt. "," ",DATA!E19) -> Sri./Smt. N.C.Subbarayudu | G6: =CONCATENATE(DATA!BN172," ",DATA!E10) -> Sri. A.Nagesh
B7: =DATA!E20 -> Executive Engineer,TGP Division No.1 | G7: =DATA!CD169 -> Deputy Executive Engineer
B8: =DATA!E21 -> Velgode | G8: =CONCATENATE(DATA!E13,", ",DATA!E14) -> Executive Engineer,TGP Division No.1, Velgode
B9: =CONCATENATE(DATA!E22," ("," Mandal",")") -> Velgode ( Mandal) | G9: =CONCATENATE(DATA!E15," (","Mandal",")") -> Velgode (Mandal)
B10: PAN No. of Deductor | E10: TAN No. of Deductor | G10: PAN OF Employee | K10: Treasury Id. No.
B11: =IF(DATA!D23="","",DATA!D23) | E11: =IF(DATA!F23="","",DATA!F23) | G11: =IF(DATA!E12="","",DATA!E12) | K11: =IF(DATA!E18="","",DATA!E18)
B12: Acknowledgement Nos.of allquarterly statements of TDS under sub-section 200 as provided by TIN facilitation center or NSDL web-site
B13: Quarter | E13: Acknowledgement No | F13: Amount | G13: Period | K13: Assessment
B14: 1 (Mar to May) | F14: =IF('Annexure -I I'!X65="","",'Annexure -I I'!X65) -> 24000 | G14: From | I14: To | K14: Year
B15: 2 (Jun to Aug) | F15: =IF('Annexure -I I'!X66="","",'Annexure -I I'!X66) -> 24000 | G15: 44256 | I15: 44620 | K15: 2022 -2023
B16: 3 (Sep to Nov) | F16: =IF('Annexure -I I'!X67="","",'Annexure -I I'!X67) -> 24000
B17: 4 (Dec to Feb) | F17: =IF('Annexure -I I'!X68="","",'Annexure -I I'!X68) -> 20000
B18: DETAILS OF SALARY PAID AND ANY OTHER INCOME AND TAX DEDUCTED
B19: 1 | C19: Gross Salary
C20: a) | D20: Salary as per provisions cotained in section 17 (1) | G20: Rs. | H20: =Bill!X25 -> 1303978
C21: b) | D21: Value of percuisites under section 17(2) | G21: Rs. | H21: 0
D22: (As Per Form No. 12BA, Wherever applicable)
C23: c) | D23: Profits in lieu of salary under section 17(3) | G23: Rs. | H23: 0
D24: (as per Form No. 12BA, Wherver applicable)
C25: d) | D25: Total | G25: Rs. | H25: =H19+H20+H21+H23 -> 1303978 | K25: Rs. | L25: =H25 -> 1303978
B26: 2 | C26: Reported Total amount of salary received | K26: Rs. | L26: =L25 -> 1303978
B27: 3 | C27: Less: Allowance to the extent exempted U/s 10
C28: a) | D28: Travel concession or assistance under section 10(5) | G28: Rs.
C29: b) | D29: Death-cum-retirement gratuity under section 10(10) | G29: Rs.
C30: c) | D30: Commuted value of pension under section 10(10A) | G30: Rs.
C31: d) | D31: Cash equivalent of leave salary encashment u/s 10(10AA) | G31: Rs.
C32: e) | D32: PH Allowence | G32: Rs. | H32: =IF('Annexure -I I'!K17="",0,'Annexure -I I'!K17) -> 0
C33: f) | D33: House rent allowance under section 10(13A) | G33: Rs. | H33: =IF(DATA!AH49=1,0,'Annexure -I I'!L13) -> 40150
C34: Total amount of exemption claimed u/s 3 (a+f) | K34: Rs. | L34: =SUM(H28:H33) -> 40150
B35: 4 | C35: Income under the Head Salaries (2-3) | K35: Rs. | L35: =L26-L34 -> 1263828
B36: 5 | C36: Less: Standard deduction- u/s 16
C37: Standard deduction under section 16(ia) | H37: =IF(DATA!AH49=1,0,50000) -> 50000
C38: Entertainment allowance under section 16(ii) | H38: 0
C39: Tax on employment under section 16(iii) | H39: =IF(DATA!AH49=1,0,(IF('Annexure -I I'!K18="",0,'Annexure -I I'!K18))) -> 2400 | K39: Rs. | L39: =SUM(H37:H39) -> 52400
B40: 6 | C40: Net Income from Salary | H40: ='Annexure -I I'!I20 | I40: ='Annexure -I I'!J20 | L40: =L35-L39 -> 1211428
B41: 7 | C41: Any other income reported by the employee under as per section 192 (2B) | H41: ='Annexure -I I'!I21 | I41: ='Annexure -I I'!J21
C42: ='Annexure -I I'!C22 -> Income From other sources | H42: ='Annexure -I I'!I22 | I42: ='Annexure -I I'!J22 | K42: Rs. | L42: ='Annexure -I I'!L22 -> 0
C43: ='Annexure -I I'!C23 -> Income From Capital Gains | H43: ='Annexure -I I'!I23 | I43: ='Annexure -I I'!J23 | K43: Rs. | L43: ='Annexure -I I'!L23 -> 0 | N43: =L42+L43+L44 -> 0
C44: =CONCATENATE('Annexure -I I'!C24,"",'Annexure -I I'!E24) -> Incomefrom House Property U/s 24 (vi) | H44: ='Annexure -I I'!I24 | I44: ='Annexure -I I'!J24 | K44: Rs. | L44: ='Annexure -I I'!L24 -> 0 | N44: =L42+L43+L44 -> 0
B45: 8 | C45: Gross Total Income (6+7) | K45: Rs. | L45: =L40+N44 -> 1211428
B46: 9 | C46: Deductions Under Chapter VI-A
B47: A) | C47: UnderSection 80C,80CCC,80CCD,80CCF | G47: Gross | I47: Qualifying
C48: a) | D48: Section 80C | G48: Amount | I48: Amount
C49: 80C | D49: ='Annexure -I I'!D37 -> PF | G49: Rs. | H49: =IF(DATA!AH49=1,0,IF(DATA!AH49=1,0,'Annexure -I I'!K37)) -> 189717 | I49: Rs. | J49: =IF(H49<=M$50,H49,IF(H49>=M$50,M$50)) -> 150000
C50: 80C | D50: A.P.G.L.I | G50: Rs. | H50: =IF(DATA!AH49=1,0,IF(DATA!AH49=1,0,Bill!AA25)) -> 24000 | I50: Rs. | J50: =IF(H50<=M$50,H50,IF(H50>=M$50,M$50)) -> 24000 | M50: 150000
C51: 80C | D51: G.I.S | G51: Rs. | H51: =IF(DATA!AH49=1,0,IF(DATA!AH49=1,0,Bill!AD25)) -> 1440 | I51: Rs. | J51: =IF(H51<=M$50,H51,IF(H51>=M$50,M$50)) -> 1440
C52: 80C | D52: ='Annexure -I I'!D40 -> LIC Policies Monthly Premium in Salary | G52: Rs. | H52: =IF(DATA!AH49=1,0,IF(DATA!AH49=1,0,'Annexure -I I'!K40)) -> 0 | I52: Rs. | J52: =IF(H52<=M$50,H52,IF(H52>=M$50,M$50)) -> 0
C53: 80C | D53: ='Annexure -I I'!D41 -> LIC Policies premium - Yearly | G53: Rs. | H53: =IF(DATA!AH49=1,0,IF(DATA!AH49=1,0,DATA!G27)) -> 0 | I53: Rs. | J53: =IF(H53<=M$50,H53,IF(H53>=M$50,M$50)) -> 0
C54: 80C | D54: ='Annexure -I I'!D42 -> Exide Life Insurance | G54: Rs. | H54: =IF(DATA!AH49=1,0,IF(DATA!AH49=1,0,DATA!G28)) -> 0 | I54: Rs. | J54: =IF(H54<=M$50,H54,IF(H54>=M$50,M$50)) -> 0
C55: 80C | D55: ='Annexure -I I'!D43 -> Sukanya Samruddhi Yojana | G55: Rs. | H55: =IF(DATA!AH49=1,0,IF(DATA!AH49=1,0,DATA!G29)) -> 0 | I55: Rs. | J55: =IF(H55<=M$50,H55,IF(H55>=M$50,M$50)) -> 0
C56: 80C | D56: ='Annexure -I I'!D44 -> PLI (Postal Life Insurance) | G56: Rs. | H56: =IF(DATA!AH49=1,0,IF(DATA!AH49=1,0,DATA!G30)) -> 0 | I56: Rs. | J56: =IF(H56<=M$50,H56,IF(H56>=M$50,M$50)) -> 0
C57: 80C | D57: ='Annexure -I I'!D45 -> Housing Loan Principal Amount | G57: Rs. | H57: =IF(DATA!AH49=1,0,IF(DATA!AH49=1,0,DATA!G26)) -> 0 | I57: Rs. | J57: =IF(H57<=M$50,H57,IF(H57>=M$50,M$50)) -> 0
G58: Rs. | H58: =SUM(H49:H57) -> 215157 | I58: Rs. | J58: =IF((SUM(J49:J57))<=DATA!BQ212,(SUM(J49:J57)),IF((SUM(J49:J57))>=DATA!BQ212,DATA!BQ212)) -> 150000
E59: Total Under Section 80C,80CCC,80CCD,80CC | K59: Rs. | L59: =J58 -> 150000
C60: =DATA!BE200 -> 80TTA | D60: =DATA!BC200 -> Intrest on Saving Account ( Not Fixed Deposit ) | G60: Rs. | H60: =IF(DATA!AH49=1,0,IF(DATA!AH49=1,0,DATA!G31)) -> 0 | J60: =IF(DATA!AH49=1,0,IF(DATA!AH49=1,0,DATA!BF200)) -> 0
B62: Prepared by: C.Ramanjaneyulu, S.A(P.S), www.teacherNews.in

Sheet Form-16 Back
C2: b) | D2: =IF(DATA!CF182=1,"NPS U/s 80CCD (1)","NPS U/s 80CCD 2(B)") -> NPS U/s 80CCD (1)
D3: ='Annexure -I I'!D47 -> National Pension Scheme U/s 80CCD (1B) | I3: Rs. | J3: =IF(DATA!AH49=1,0,IF(DATA!AH49=1,0,'Annexure -I I'!K47)) -> 0 | K3: =IF(DATA!AH49=1,0,IF(DATA!AH49=1,0,'Annexure -I I'!L47)) -> 0
F4: Total Amount of Section a and b | L4: Rs. | M4: =IF(DATA!AH49=1,0,'Annexure -I I'!N50) -> 150000
B6: B) | C6: Other Section Under Chapter VI A | J6: Gross | K6: Qualifying
C7: ( Under Section 80E, 80G, 80TTA, 80G, 80DD etc. ) | J7: Amount | K7: Amount
C8: 80G | E8: EWF , SWF & CMRF | I8: Rs. | J8: =IF(DATA!AH49=1,0,Bill!AF25) -> 150 | K8: =J8 -> 150
C9: ='Annexure -I I'!D30 -> 24B | E9: =DATA!BO189 -> Interest of Housing Loan Section 24 | I9: Rs. | J9: =IF(DATA!AH49=1,0,IF(DATA!AH49=1,0,DATA!G33)) -> 0 | K9: =IF(DATA!AH49=1,0,IF(DATA!AH49=1,0,DATA!BP192)) -> 0
C10: =DATA!BL211 -> 80EE | E10: =DATA!BO190 -> Interest of Housing Loan 80EE | I10: Rs. | J10: =IF(DATA!AH49=1,0,IF(DATA!AH49=1,0,DATA!G34)) -> 0 | K10: =IF(DATA!AH49=1,0,IF(DATA!AH49=1,0,'Annexure -I I'!K28)) -> 0
C11: =DATA!BL212 -> 80EEA | E11: =DATA!BO191 -> Interest of HBA Loan 80EEA | I11: Rs. | J11: =IF(DATA!AH49=1,0,IF(DATA!AH49=1,0,DATA!G35)) -> 0 | K11: =IF(DATA!AH49=1,0,'Annexure -I I'!K29) -> 0
C12: ='Annexure -I I'!D31 -> 80U | E12: ='Annexure -I I'!E31 -> Disabled Person (PH)-above 40% disability ( Rule 11A) | I12: Rs. | J12: =IF(DATA!AH49=1,0,DATA!G36) -> 0 | K12: =IF(DATA!AH49=1,0,IF(DATA!AH49=1,0,DATA!BL225)) -> 0
C13: 80D | E13: Employees Health Cards Premium in AP | I13: Rs. | J13: =IF(DATA!AH49=1,0,IF(DATA!AH49=1,0,Bill!AG25)) -> 3600 | K13: =IF(DATA!AH49=1,0,IF(DATA!AH49=1,0,Bill!AG25)) -> 3600
C14: Employees Contribution towards NPS U/s 80CCD (2) | I14: Rs. | J14: =IF(DATA!AH49=1,0,'Annexure -I I'!K33) -> 0 | K14: =IF(DATA!AH49=1,0,J14) -> 0
G15: Total Under Sections 80G,80E,80DD etc….. | L15: Rs. | M15: =SUM(K8:K14) -> 3750
B16: 10 | C16: Aggregate of Deductible Amounts U/Chapter VIA (A+B)… | L16: Rs. | M16: ='Annexure -I I'!N50+'Form-16 Back'!M15 -> 153750
B18: 11 | C18: Net Taxable Income ( Column 8- Column 10) | L18: Rs. | M18: ='Annexure -I I'!L50 -> 1057680
C19: Tax on Income | J19: ='Annexure -I I'!J51 -> Tax Rs. 807680
C20: a) | D20: Upto-2,50,000 | L20: Rs. | M20: Nil
C21: b) | D21: ='Annexure -I I'!D53 -> 2,50,001/- to 5,00,000/- 5% | H21: ='Annexure -I I'!H53 -> ( 250000 @ 5% ) | L21: Rs. | M21: ='Annexure -I I'!L53 -> 12500
C22: c) | D22: ='Annexure -I I'!D54 -> 5,00,001/- to 10,00,000/- 20% | H22: ='Annexure -I I'!H54 -> ( 500000 @ 20% ) | L22: Rs. | M22: ='Annexure -I I'!L54 -> 100000
C23: d) | D23: ='Annexure -I I'!D55 -> 10,00,001/ Above - 30% | H23: ='Annexure -I I'!H55 -> ( 57680 @ 30% ) | L23: Rs. | M23: ='Annexure -I I'!L55 -> 17304
C24: e) | D24: ='Annexure -I I'!D56 | H24: ='Annexure -I I'!H56 | L24: Rs. | M24: ='Annexure -I I'!L56 -> 0
C25: f) | D25: ='Annexure -I I'!D57 | H25: ='Annexure -I I'!H57 | L25: Rs. | M25: ='Annexure -I I'!L57 -> 0
C26: g) | D26: ='Annexure -I I'!D58 | H26: ='Annexure -I I'!H58 | L26: Rs. | M26: ='Annexure -I I'!L58 -> 0
B27: 12 | C27: TAX ON TOTAL INCOME Rs.
B28: 13 | C28: Tax Rebate Rs. 12500/-upto Rs.5,00,000 Taxble Income( U/s 87 A) | L28: Rs. | M28: ='Annexure -I I'!L59 -> 0
B29: 14 | C29: TAX PAYBLE (12-13) | L29: Rs. | M29: ='Annexure -I I'!L60 -> 129804
B30: 15 | C30: Health Cess @ 1% + Education Cess @ 3% | L30: Rs. | M30: ='Annexure -I I'!L61 -> 5192
B32: 16 | C32: TAX PAYABLE (14+15) | L32: Rs. | M32: ='Annexure -I I'!L63 -> 134996
B33: 17 | C33: Less: (a) Tax deducted at source U/s 192(1) | L33: Rs.
C34: (b)Tax Paid by the Employer on behalf of the Employee U/S 192 (1A) on perquisited U/S 17 (2) | L34: Rs. | M34: ='Annexure -I I'!L65 -> 92000
B35: 18 | C35: Less: Relief under section 89 (1) (attach details) | L35: Rs. | M35: ='Annexure -I I'!L64 -> 0
B36: 20 | C36: Less: (a) Tax deducted at source U/S 192 (1) | L36: Rs.
B37: 21 | C37: (b) Tax paid by the Employer on behalf of the Employee U/S 192 (A1) on perquisited U/S 17 (2) | L37: Rs.
B39: 19 | C39: ='Annexure -I I'!J67 -> Net Tax to be Paid | L39: Rs. | M39: ='Annexure -I I'!L67 -> 42996
B41: DETAILS OF TAX DEDUCTED AND DEPOSITED INTO CENTRAL GOVERNMENT ACCOUNT
B42: ( The employer is provide tranction - wise details of tax deducted and deposited )
B44: Sl. | C44: TDS | E44: Surcharge | F44: Education | G44: Total Tax | H44: Cheque/DD | I44: BSR Code | K44: Date on | L44: Transfer
B45: No. | C45: Rs. | E45: Rs. | F45: Cess | G45: Deposited | H45: No. (if any) | I45: of Bank | K45: Which Tax | L45: vocher/chalana
F46: Rs. | G46: Rs. | I46: Branch | K46: Deposited | L46: Identification No
B47: 1
B48: 2
B49: 3
B50: 4
B51: 5
B52: 6
B53: 7
B54: 8
B55: 9
B56: 10
B57: 11
B58: 12
B62: =CONCATENATE(" I Sri./Smt. ",DATA!E19," working in the capacity of ",DATA!E20," do hereby certify that sum of Rs. ",DATA!BX223," Rupees in words ( ",DATA!CD223," has been deducted at source and paid to the credit of the central Government. I further certify that the Informtion given above is true, complete and correct based on the books of account, documents and other available records.") -> I Sri./Smt. N.C.Subbarayudu working in the capacity of Executive Engineer,TGP Division No.1 do hereby certify that sum of Rs. 134996 Rupees in words ( One Lakh Thirty Four Thousands Nine Hundred and Ninty Six only has been deducted at source and paid to the credit of the central Government. I further certify that the Informtion given above is true, complete and correct based on the books of account, documents and other available records.
G67: Sign--
B69: Place: | D69: =DATA!E21 -> Velgode | G69: Signature of the person responsible for deduction of tax
B70: Date: | D70: =TODAY() -> 44553 | G70: Full Name-- | H70: =CONCATENATE("Sri./Smt. ",DATA!E19) -> Sri./Smt. N.C.Subbarayudu
G71: Designation- | H71: =DATA!E20 -> Executive Engineer,TGP Division No.1
B74: Prepared by: C.Ramanjaneyulu, S.A(P.S), www.teacherNews.in

Sheet Form 12BB
B3: INCOME TAX RULES,1962
B4: Form 12 BB
B6: Statement showing particulars of claims by an employee for deduction of tax under section 192
B8: 1 | C8: Name and address of the Employee | J8: : | K8: =CONCATENATE(DATA!E10,", ",DATA!E13,", ",DATA!E14) -> A.Nagesh, Executive Engineer,TGP Division No.1, Velgode
B9: 2 | C9: Permanent Account Number of the Employee | J9: : | K9: =IF(DATA!E12="","",DATA!E12)
B10: 3 | C10: Financial year | G10: 2021-22 | K10: Designation | M10: : | N10: =DATA!E11 -> Deputy Executive Engineer
B11: Details of claims and Evidence thereof
B12: S.No | C12: Nature of claim | M12: Amount(Rs) | Q12: Evidence/particulars
B13: 1 | C13: House Rent Allowence:
C14: 1) | D14: Rent paid to the landlord | I14: =IF(DATA!AH49=1,0,'Annexure -I I'!P12) -> 12000 | K14: x12 | M14: =IF(DATA!AH49=1,0,'Annexure -I I'!U12) -> 144000 | Q14: =IF(DATA!AH49=1,0,"Receipt Produced") -> Receipt Produced
C15: 2) | D15: Name of the landlord
C16: 3) | D16: Address of the landlord
C17: 4) | D17: PAN number of the landlord
B18: 2 | C18: Leave travel concession or assistance
B19: 3 | C19: Deduction of interest on borrowing
C20: 1) | D20: Interest payable/paid to the lender
C21: 2) | D21: Name of the lender
C22: 3) | D22: Address of the lender
C23: 4) | D23: PAN number of the lender
C24: a) | D24: Financial institutions (if available)
C25: b) | D25: Employer (if available)
C26: c) | D26: Others
B27: 4 | C27: Deduction under Chapter VI-A | X27: ='Annexure -I I'!K37 -> 189717
B28: A) | C28: Section 80C,80CC, 80CCC and 80CCD | X28: =IF('Annexure -I I'!K47="",0,'Annexure -I I'!K47) -> 0
C29: a) | D29: ='Form-16'!C49 -> 80C | E29: ='Form-16'!D49 -> PF | M29: =IF(DATA!AH49=1,0,(X27+X28)) -> 189717 | Q29: =IF(DATA!AH49=1,0,IF(M29>0,"Salary deduction","")) -> Salary deduction
C30: b) | D30: ='Form-16'!C50 -> 80C | E30: ='Form-16'!D50 -> A.P.G.L.I | M30: =IF(DATA!AH49=1,0,'Annexure -I I'!K38) -> 24000 | Q30: =IF(DATA!AH49=1,0,IF(M30>0,"Salary deduction","")) -> Salary deduction
C31: c) | D31: ='Form-16'!C51 -> 80C | E31: ='Form-16'!D51 -> G.I.S | M31: =IF(DATA!AH49=1,0,'Annexure -I I'!K39) -> 1440 | Q31: =IF(DATA!AH49=1,0,IF(M31>0,"Salary deduction","")) -> Salary deduction
C32: d) | D32: ='Form-16'!C52 -> 80C | E32: ='Form-16'!D52 -> LIC Policies Monthly Premium in Salary | M32: =IF(DATA!AH49=1,0,'Annexure -I I'!K40) -> 0 | Q32: =IF(DATA!AH49=1,0,IF(M32>0,"Salary deduction",""))
C33: e) | D33: ='Form-16'!C53 -> 80C | E33: ='Form-16'!D53 -> LIC Policies premium - Yearly | M33: =IF(DATA!AH49=1,0,'Annexure -I I'!K41) -> 0 | Q33: =IF(DATA!AH49=1,0,IF(M33>0,"Receipt Added",""))
C34: f) | D34: ='Form-16'!C54 -> 80C | E34: ='Form-16'!D54 -> Exide Life Insurance | M34: =IF(DATA!AH49=1,0,'Annexure -I I'!K42) -> 0 | Q34: =IF(DATA!AH49=1,0,IF(M34>0,"Receipt Added",""))
C35: g) | D35: ='Form-16'!C55 -> 80C | E35: ='Form-16'!D55 -> Sukanya Samruddhi Yojana | M35: =IF(DATA!AH49=1,0,'Annexure -I I'!K43) -> 0 | Q35: =IF(DATA!AH49=1,0,IF(M35>0,"Receipt Added",""))
C36: h) | D36: ='Form-16'!C56 -> 80C | E36: ='Form-16'!D56 -> PLI (Postal Life Insurance) | M36: =IF(DATA!AH49=1,0,'Annexure -I I'!K44) -> 0 | Q36: =IF(DATA!AH49=1,0,IF(M36>0,"Receipt Added",""))
C37: j) | D37: 80C | E37: ='Form-16'!D57 -> Housing Loan Principal Amount | M37: =IF(DATA!AH49=1,0,'Annexure -I I'!K45) -> 0 | Q37: =IF(DATA!AH49=1,0,IF(M37>0,"Receipt Added",""))
D38: Total of ( 80C,80CCC,80CCD,80CCF ) | M38: =IF(DATA!AH49=1,0,'Annexure -I I'!K46+X28) -> 215157
D39: ='Annexure -I I'!C48 -> 80TTA | E39: ='Annexure -I I'!D48 -> Intrest on Saving Account ( Not Fixed Deposit ) | M39: =IF(DATA!AH49=1,0,'Annexure -I I'!K48) -> 0 | Q39: =IF(M39>0,"Receipt Added","")
B40: B) | C40: Other Sections (80E,80G,80TTA)ChapterVI-A
C41: i) | D41: ='Annexure -I I'!D27 -> 80G | E41: ='Annexure -I I'!E27 -> E.W.F. & S.W.F & CMRF | M41: ='Annexure -I I'!K27 -> 150 | Q41: =IF(M41>0,"Salary deduction","") -> Salary deduction
C42: ii) | D42: ='Annexure -I I'!D28 -> 80EE | E42: ='Annexure -I I'!E28 -> Interest of Housing Loan 80EE | M42: =IF(DATA!AH49=1,0,'Annexure -I I'!K28) -> 0 | Q42: =IF(DATA!AH49=1,0,IF(M42>0,"Receipt Added",""))
C43: iii) | D43: ='Annexure -I I'!D29 -> 80EEA | E43: ='Annexure -I I'!E29 -> Interest of HBA Loan 80EEA | M43: =IF(DATA!AH49=1,0,'Annexure -I I'!K29) -> 0 | Q43: =IF(DATA!AH49=1,0,IF(M43>0,"Receipt Added",""))
C44: iv) | D44: ='Annexure -I I'!D30 -> 24B | E44: ='Annexure -I I'!E30 -> Interest of Housing Loan Section 24 | M44: =IF(DATA!AH49=1,0,'Annexure -I I'!K30) -> 0 | Q44: =IF(DATA!AH49=1,0,IF(M44>0,"Receipt Added",""))
C45: v) | D45: ='Annexure -I I'!D31 -> 80U | E45: ='Annexure -I I'!E31 -> Disabled Person (PH)-above 40% disability ( Rule 11A) | M45: =IF(DATA!AH49=1,0,'Annexure -I I'!K31) -> 0 | Q45: =IF(DATA!AH49=1,0,IF(M45>0,"Receipt Added",""))
C46: vi) | D46: ='Annexure -I I'!D32 -> 80d | E46: ='Annexure -I I'!E32 -> Employees Health Cards Premium in AP | M46: =IF(DATA!AH49=1,0,'Annexure -I I'!K32) -> 3600 | Q46: =IF(DATA!AH49=1,0,IF(M46>0,"Salary deduction","")) -> Salary deduction
C48: Verification
C49: I, | D49: =DATA!E10 -> A.Nagesh | K49: son/daughter of
C50: do hereby certify that the information given is above is complete and correct
C53: Place
C54: Date | M54: Signature of the Employee

Sheet Form 10E
AB2: Detail | AC2: 2020-21 | AD2: Detail | AE2: 2020-21
B4: FORM NO.10E | AB4: Total income (excluding salary received in arrars or advance) | AC4: ='Annexure -I I'!L50-AC6 -> 1057680 | AD4: Net Taxable Income | AE4: =AC4 -> 1057680
B5: [ See rule 21AA ]
B6: 1 | C6: Name and address of the Employee | L6: =CONCATENATE(DATA!BN172," ",DATA!E10,", ",DATA!CD169,", ",DATA!E13," , ",DATA!E14,", ",DATA!E15," (","Mandal",")"," ") -> Sri. A.Nagesh, Deputy Executive Engineer, Executive Engineer,TGP Division No.1 , Velgode, Velgode (Mandal) | AB6: Arrears Received | AC6: =IF(AN19="","",AN19) -> 0 | AD6: Arrears Received | AE6: 0
AB7: Total Taxable Income | AC7: =SUM(AC4:AC6) -> 1057680 | AD7: Total Taxable Income | AE7: =SUM(AE4:AE6) -> 1057680
B8: 2 | C8: Permanent Account Number | L8: =IF(DATA!E12="","",DATA!E12) | AB8: Up to Rs. 2,50,000 | AC8: 0 | AD8: Up to Rs. 2,50,000 | AE8: 0 | AT8: Yes
B9: 3 | C9: Residential Status | M9: Resident | AB9: Rs.2,50,001 To 5,00,000. (@ 5%) | AC9: =IF(AH9>0,AH9,0)*5% -> 12500 | AD9: Rs.2,50,001 To 5,00,000. (@ 5%) | AE9: =IF(AJ9>0,AJ9,0)*5% -> 12500 | AG9: =AC7-250000 -> 807680 | AH9: =IF(AG9>250000,250000,AG9) -> 250000 | AI9: =AE7-250000 -> 807680 | AJ9: =IF(AI9>250000,250000,AI9) -> 250000 | AT9: No
AB10: Rs.5,00,001 To 10,00,000. (@ 20%) | AC10: =IF(AH10>0,AH10,0)*20% -> 100000 | AD10: Rs.5,00,001 To 10,00,000. (@ 20%) | AE10: =IF(AJ10>0,AJ10,0)*20% -> 100000 | AG10: =AC7-500000 -> 557680 | AH10: =IF(AG10>500000,500000,AG10) -> 500000 | AI10: =AE7-500000 -> 557680 | AJ10: =IF(AI10>500000,500000,AI10) -> 500000 | AL10: Financil Year | AM10: Taxable | AN10: Arrears | AU10: REBATE AMOUNT UNDER SECTION 87A OF INCOME TAX ACT, 1961
C11: ="Particulars of income referred to in rule 21A of the Income Tax rules, 1962, during the previous year relevent to Assessment year"&" "&"2021"&""&"-"&""&"2022" -> Particulars of income referred to in rule 21A of the Income Tax rules, 1962, during the previous year relevent to Assessment year 2021-2022 | AB11: above Rs.10,00,001. (@ 30%) | AC11: =IF(AH11>0,AH11,0)*30% -> 17304 | AD11: above Rs.10,00,001. (@ 30%) | AE11: =IF(AJ11>0,AJ11,0)*30% -> 17304 | AG11: =AC7-1000000 -> 57680 | AH11: =IF(AG11>500000,500000,AG11) -> 57680 | AI11: =AE7-1000000 -> 57680 | AJ11: =IF(AI11>500000,500000,AI11) -> 57680 | AL11: 2020-21 | AM11: =DATA!K45 -> 0 | AN11: =DATA!F45 -> 0 | AT11: 2
AB12: Tax rebate U/s 87A | AC12: ='Annexure -I I'!L59 -> 0 | AD12: Tax rebate U/s 87A | AE12: =IF(AE7>500000,0,AC12) -> 0 | AL12: 2019-20 | AM12: =DATA!K46 -> 0 | AN12: =DATA!F46 -> 0 | AU12: S. No. | AV12: Financial Year | AW12: Rebate Available
B13: 1 | C13: a. | D13: Salary received in arrears or in advance in accordance with the provisions of sub-rule (2) of rule 21A | S13: Rs. | T13: =I81 -> 0 | AB13: Total | AC13: =IF((SUM(AC9:AC11)-AC12)>0,(SUM(AC9:AC11)-AC12),0) -> 129804 | AD13: Total | AE13: =IF((SUM(AE9:AE11)-AE12)>0,(SUM(AE9:AE11)-AE12),0) -> 129804 | AL13: 2016-17 | AM13: =DATA!K49 -> 0 | AN13: =DATA!F49 -> 0 | AU13: 1 | AV13: 2018-19 & Subsequent Years unless withdrawn | AW13: 2,500/-
AB14: Health Cess @ 1% | AC14: =ROUND(AC13*1%,0.1) -> 1298 | AD14: Health Cess @ 1% | AE14: =ROUND(AE13*1%,0.1) -> 1298 | AL14: =B77 -> 2017-18 | AM14: =DATA!K48 -> 0 | AN14: =DATA!F48 -> 0 | AU14: 2 | AV14: 2017-18 | AW14: 2,500/-
C15: b. | D15: Pament in the nature of gratuity in respect of past services, extending over a period of not less than 5 years in accordance with the provisions of sub-rule (3) of rule 21A | S15: Rs. | T15: Not Applicable | AB15: Education Cess @ 3% | AC15: =ROUND(AC13*3%,0.1) -> 3894 | AD15: Education Cess @ 3% | AE15: =ROUND(AE13*3%,0.1) -> 3894 | AL15: 2018-19 | AM15: =DATA!K47 -> 0 | AN15: =DATA!F47 -> 0 | AU15: 3 | AV15: 2016-17 | AW15: 5,000/-
AB16: Total Tax | AC16: =SUM(AC13:AC15) -> 134996 | AD16: Total Tax | AE16: =SUM(AE13:AE15) -> 134996 | AF16: =AC16-AE16 -> 0 | AL16: 2015-16 | AM16: =DATA!K50 -> 0 | AN16: =DATA!F50 -> 0 | AU16: 4 | AV16: 2015-16 | AW16: 2,000/-
AB17: Detail | AC17: 2017-18 | AD17: Detail | AE17: 2017-18 | AU17: 5 | AV17: 2014-15 | AW17: 2,000/-
C18: c. | D18: Payment in the nature of compensation from the employer or former employer at or in connection with termination of employment after continuous service of not less than 3 years or where the unexpired portion of term of employment is also not less than 3 years in accordancewith the provisions of sub rule (4) of the 21A | S18: Rs. | T18: Not Applicable | AF18: | | AU18: 6 | AV18: 2013-14 | AW18: 2,000/-
AB19: Net Taxable Income | AC19: =IF(AM14="","",AM14) -> 0 | AD19: Net Taxable Income | AE19: =AC19 -> 0 | AL19: Total Arrears | AN19: =SUM(AN11:AN16) -> 0 | AO19: =IF(DATA!CL274=2,Bill!P25,Bill!#REF!) -> #REF!
AB20: Arrears Received | AC20: =IF(AN14="","",AN14) -> 0 | AD20: Arrears Received | AE20: 0 | AO20: =AN17-AN16 -> 0
AB21: Total Taxable Income | AC21: =SUM(AC19:AC20) -> 0 | AD21: Total Taxable Income | AE21: =SUM(AE19:AE20) -> 0 | AL21: Tax Relief | AM21: =IF(U61=0,"No Tax Relief",U61) -> No Tax Relief
AB22: Up to Rs. 5,00,000 | AC22: 0 | AD22: Up to Rs. 2,50,000 | AE22: 0
AB23: Rs.2,50,001 To 5,00,000. (@ 5%) | AC23: =IF(AH23>0,AH23,0)*5% -> 0 | AD23: Rs.2,50,001 To 5,00,000. (@ 5%) | AE23: =IF(AJ23>0,AJ23,0)*5% -> 0 | AG23: =AC21-250000 -> -250000 | AH23: =IF(AG23>250000,250000,AG23) -> -250000 | AI23: =AE21-250000 -> -250000 | AJ23: =IF(AI23>250000,250000,AI23) -> -250000 | AM23: For result See in Anex-II, Serial No-20
C24: d. | D24: Payment in commutation of pension in accordance with the provisions of sub-rule (5) of rule 21A | S24: Rs. | T24: Not Applicable | AB24: Rs.5,00,001 To 10,00,000. (@ 20%) | AC24: =IF(AH24>0,AH24,0)*20% -> 0 | AD24: Rs.5,00,001 To 10,00,000. (@ 20%) | AE24: =IF(AJ24>0,AJ24,0)*20% -> 0 | AG24: =AC21-500000 -> -500000 | AH24: =IF(AG24>500000,500000,AG24) -> -500000 | AI24: =AE21-500000 -> -500000 | AJ24: =IF(AI24>500000,500000,AI24) -> -500000 | AM24: See in Form-16 Back,Serial No-19
AB25: above Rs.10,00,001. (@ 30%) | AC25: =IF(AH25>0,AH25,0)*30% -> 0 | AD25: above Rs.10,00,001. (@ 30%) | AE25: =IF(AJ25>0,AJ25,0)*30% -> 0 | AG25: =AC21-1000000 -> -1000000 | AH25: =IF(AG25>500000,500000,AG25) -> -1000000 | AI25: =AE21-1000000 -> -1000000 | AJ25: =IF(AI25>500000,500000,AI25) -> -1000000 | AM25: Print this page and add with Form-16
AB26: Tax rebate U/s 87A | AC26: =IF(AC21>350000,0,2500) -> 2500 | AD26: Tax rebate U/s 87A | AE26: =IF(AC19>350000,0,2500) -> 2500
B27: 2 | D27: Detailed particulars of payments refered to above may be given in Annexure-I, II, IIA, III, or IV, as the case may be | T27: Annexure-I | AB27: Total | AC27: =IF((SUM(AC22:AC25)-AC26)>0,(SUM(AC22:AC25)-AC26),0) -> 0 | AD27: Total | AE27: =IF((SUM(AE22:AE25)-AE26)>0,(SUM(AE22:AE25)-AE26),0) -> 0
AB28: Education Cess @ 1% | AC28: =ROUND(AC27*1%,0.1) -> 0 | AD28: Education Cess @ 1% | AE28: =ROUND(AE27*1%,0.1) -> 0
AB29: Secondary & Higher Education Cess @ 2% | AC29: =ROUND(AC27*2%,0.1) -> 0 | AD29: Secondary & Higher Education Cess @ 2% | AE29: =ROUND(AE27*2%,0.1) -> 0
P31: Signature of the employee | AB31: Total Tax | AC31: =SUM(AC27:AC30) -> 0 | AD31: Total Tax | AE31: =SUM(AE27:AE30) -> 0 | AF31: =AC31-AE31 -> 0
B32: Verification
AB33: Detail | AC33: 2020-21 | AD33: Detail | AE33: 2020-21
C34: =CONCATENATE(" I ",DATA!BN172," ",DATA!E10," do here by declare that what is stated above is true to the best of my knowledge and belief.") -> I Sri. A.Nagesh do here by declare that what is stated above is true to the best of my knowledge and belief. | AF34: |
AB35: Net Taxable Income | AC35: =IF(AM17="","",AM17) | AD35: Net Taxable Income | AE35: =AC35
AB36: Arrears Received | AC36: =IF(AN17="","",AN17) | AD36: Arrears Received | AE36: 0
AB37: Total Taxable Income | AC37: =SUM(AC35:AC36) -> 0 | AD37: Total Taxable Income | AE37: =SUM(AE35:AE36) -> 0
B38: Verified today : | F38: =TODAY() -> 44553 | AB38: Up to Rs. 2,50,000 | AC38: 0 | AD38: Up to Rs. 2,50,000 | AE38: 0
AB39: Rs.2,50,001 To 5,00,000. (@ 5%) | AC39: =IF(AH39>0,AH39,0)*5% -> 0 | AD39: Rs.2,50,001 To 5,00,000. (@ 10%) | AE39: =IF(AJ39>0,AJ39,0)*5% -> 0 | AG39: =AC37-250000 -> -250000 | AH39: =IF(AG39>250000,250000,AG39) -> -250000 | AI39: =AE37-250000 -> -250000 | AJ39: =IF(AI39>250000,250000,AI39) -> -250000
AB40: Rs.5,00,001 To 10,00,000. (@ 20%) | AC40: =IF(AH40>0,AH40,0)*20% -> 0 | AD40: Rs.5,00,001 To 10,00,000. (@ 20%) | AE40: =IF(AJ40>0,AJ40,0)*20% -> 0 | AG40: =AC37-500000 -> -500000 | AH40: =IF(AG40>500000,500000,AG40) -> -500000 | AI40: =AE37-500000 -> -500000 | AJ40: =IF(AI40>500000,500000,AI40) -> -500000
B41: Place : | D41: =DATA!E21 -> Velgode | AB41: above Rs.10,00,001. (@ 30%) | AC41: =IF(AH41>0,AH41,0)*30% -> 0 | AD41: above Rs.10,00,001. (@ 30%) | AE41: =IF(AJ41>0,AJ41,0)*30% -> 0 | AG41: =AC37-1000000 -> -1000000 | AH41: =IF(AG41>500000,500000,AG41) -> -1000000 | AI41: =AE37-1000000 -> -1000000 | AJ41: =IF(AI41>500000,500000,AI41) -> -1000000
B42: Date : | D42: =TODAY() -> 44553 | P42: Signature of the employee | AB42: Tax rebate U/s 87A | AC42: =IF(AC37>500000,0,12500) -> 12500 | AD42: Tax rebate U/s 87A | AE42: =IF(AE37>500000,0,12500) -> 12500
AB43: Total | AC43: =IF((SUM(AC38:AC41)-AC42)>0,(SUM(AC38:AC41)-AC42),0) -> 0 | AD43: Total | AE43: =IF((SUM(AE38:AE41)-AE42)>0,(SUM(AE38:AE41)-AE42),0) -> 0
AB44: Education Cess @ 1% | AC44: =ROUND(AC43*1%,0.1) -> 0 | AD44: Education Cess @ 1% | AE44: =ROUND(AE43*1%,0.1) -> 0
AB45: Secondary & Higher Education Cess @ 3% | AC45: =ROUND(AC43*3%,0.1) -> 0 | AD45: Secondary & Higher Education Cess @ 3% | AE45: =ROUND(AE43*3%,0.1) -> 0
AB46: Total Tax | AC46: =SUM(AC43:AC45) -> 0 | AD46: Total Tax | AE46: =SUM(AE43:AE45) -> 0 | AF46: =AC46-AE46 -> 0
B49: Annexure-I
B50: (See item 2 of Form No. 10E) | AB50: Detail | AC50: 2016-17 | AD50: Detail | AE50: 2016-17
B51: ARREARS OR ADVANCE SALARY | AF51: |
B52: 1 | C52: Total income (excluding salary received in arrars or advance) | T52: Rs. | U52: =AC4 -> 1057680 | AB52: Net Taxable Income | AC52: =IF(AM13="","",AM13) -> 0 | AD52: Net Taxable Income | AE52: =AC52 -> 0
B53: 2 | C53: Salary received in arrears or advance | T53: Rs. | U53: =I81 -> 0 | AB53: Arrears Received | AC53: =IF(AN13="","",AN13) -> 0 | AD53: Arrears Received | AE53: 0
B54: 3 | C54: Total income (as increased by salary received in arrears or advance) | T54: Rs. | U54: =SUM(U52,U53) -> 1057680 | AB54: Total Taxable Income | AC54: =SUM(AC52:AC53) -> 0 | AD54: Total Taxable Income | AE54: =SUM(AE52:AE53) -> 0
B55: 4 | C55: Tax on total income (as per item 3) | T55: Rs. | U55: =AC16 -> 134996 | AB55: Up to Rs. 2,50,000 | AC55: 0 | AD55: Up to Rs. 2,50,000 | AE55: 0
B56: 5 | C56: Tax on total income (as per item 1) | T56: Rs. | U56: =AE16 -> 134996 | AB56: Rs.2,50,001 To 5,00,000. (@ 10%) | AC56: =IF(AH56>0,AH56,0)*10% -> 0 | AD56: Rs.2,50,001 To 5,00,000. (@ 10%) | AE56: =IF(AJ56>0,AJ56,0)*10% -> 0 | AG56: =AC54-250000 -> -250000 | AH56: =IF(AG56>250000,250000,AG56) -> -250000 | AI56: =AE54-250000 -> -250000 | AJ56: =IF(AI56>250000,250000,AI56) -> -250000
B57: 6 | C57: Tax on salary received in arrears or advance | T57: Rs. | U57: =IF(W80=0,0,(U55-U56)) -> 0 | AB57: Rs.5,00,001 To 10,00,000. (@ 20%) | AC57: =IF(AH57>0,AH57,0)*20% -> 0 | AD57: Rs.5,00,001 To 10,00,000. (@ 20%) | AE57: =IF(AJ57>0,AJ57,0)*20% -> 0 | AG57: =AC54-500000 -> -500000 | AH57: =IF(AG57>500000,500000,AG57) -> -500000 | AI57: =AE54-500000 -> -500000 | AJ57: =IF(AI57>500000,500000,AI57) -> -500000
C58: (Difference of item 4 and item 5) | AB58: above Rs.10,00,001. (@ 30%) | AC58: =IF(AH58>0,AH58,0)*30% -> 0 | AD58: above Rs.10,00,001. (@ 30%) | AE58: =IF(AJ58>0,AJ58,0)*30% -> 0 | AG58: =AC54-1000000 -> -1000000 | AH58: =IF(AG58>500000,500000,AG58) -> -1000000 | AI58: =AE54-1000000 -> -1000000 | AJ58: =IF(AI58>500000,500000,AI58) -> -1000000
B59: 7 | C59: Tax computed in accordance with table "A" | T59: Rs. | U59: =W80 -> 0 | AB59: Tax rebate U/s 87A | AC59: =IF(AC54>500000,0,5000) -> 5000 | AD59: Tax rebate U/s 87A | AE59: =IF(AE54>500000,0,5000) -> 5000
C60: (Brought from column 7 of Table "A") | AB60: Total | AC60: =IF((SUM(AC55:AC58)-AC59)>0,(SUM(AC55:AC58)-AC59),0) -> 0 | AD60: Total | AE60: =IF((SUM(AE55:AE58)-AE59)>0,(SUM(AE55:AE58)-AE59),0) -> 0 | AJ60: =IF(U61>0,U61,0) -> 0
B61: 8 | C61: Relief under section 89(1) [Indicate the difference between the amounts mentioned against items 6 and 7] | T61: Rs. | U61: =IF((U57-U59)>0,(U57-U59),0) -> 0 | AB61: Education Cess @ 1% | AC61: =ROUND(AC60*1%,0.1) -> 0 | AD61: Education Cess @ 1% | AE61: =ROUND(AE60*1%,0.1) -> 0
AB62: Secondary & Higher Education Cess @ 2% | AC62: =ROUND(AC60*2%,0.1) -> 0 | AD62: Secondary & Higher Education Cess @ 2% | AE62: =ROUND(AE60*2%,0.1) -> 0
AB63: Total Tax | AC63: =SUM(AC60:AC62) -> 0 | AD63: Total Tax | AE63: =SUM(AE60:AE62) -> 0 | AF63: =AC63-AE63 -> 0
B65: TABLE "A"
B66: {See item 7 of Annexure I}
B67: Previous Year(s) | E67: Total income of the relevent previous year (Rs.) | I67: Salary received in arrears or advance relating to the previous year as mentioned in column(1) (Rs) | M67: Total income (as increased by salary received in arrears or advance) of the relevent previous year mentioned in column 1 (Rs.) | Q67: Tax on total income {as per column (2)} (Rs.) | T67: Tax on total income {as per column (4)} (Rs.) | W67: Difference in tax {amount under column (6) minus amount under column (5)} (Rs.) | AB67: Relief under section 89(1) [Indicate the difference between the amounts] | AF67: =IF((AF16-AF31-AF46-AF63-AF88-AF107-AF127)>0,(AF16-AF31-AF46-AF63-AF88-AF107-AF127),0) -> 0
AB68: =IF(AF67<=0,"You are not eligible to get relief Under section 89(1)","You are eligible to claim relief above mentioned amount Under Section 89(1)") -> You are not eligible to get relief Under section 89(1)
B73: 1 | E73: 2 | I73: 3 | M73: 4 | Q73: 5 | T73: 6 | W73: 7
B74: 2020-21 | E74: =IF(AM17="",0,AM17) -> 0 | I74: =IF(E80=0,0,IF(AN17="",0,AN17)) -> 0 | M74: =E80+I80 -> 0 | Q74: =IF(AE46>0,AE46,0) -> 0 | T74: =IF(AC46>0,AC46,0) -> 0 | W74: =T74-Q74 -> 0
B75: 2019-20 | E75: =IF(AM12="",0,AM12) -> 0 | I75: =IF(E75=0,0,IF(AN12="",0,AN12)) -> 0 | M75: =E75+I75 -> 0 | Q75: =IF(AE127>0,AE127,0) -> 0 | T75: =IF(AC127>0,AC127,0) -> 0 | W75: =T75-Q75 -> 0
B76: 2018-19 | E76: =IF(AM15="",0,AM15) -> 0 | I76: =IF(E76=0,0,IF(AN15="",0,AN15)) -> 0 | M76: =E76+I76 -> 0 | Q76: =IF(AE107>0,AE107,0) -> 0 | T76: =IF(AC107>0,AC107,0) -> 0 | W76: =T76-Q76 -> 0 | AB76: Details | AC76: 2015-16 | AD76: Details | AE76: 2015-16 | AF76: |
B77: 2017-18 | E77: =IF(AM14="",0,AM14) -> 0 | I77: =IF(E77=0,0,IF(AN14="",0,AN14)) -> 0 | M77: =E77+I77 -> 0 | Q77: =IF(AE31>0,AE31,0) -> 0 | T77: =IF(AC31>0,AC31,0) -> 0 | W77: =T77-Q77 -> 0 | AB77: Net Taxable Income | AC77: =IF(AM16="","",AM16) -> 0 | AD77: Net Taxable Income | AE77: =AC77 -> 0
B78: 2016-17 | E78: =IF(AM13="",0,AM13) -> 0 | I78: =IF(E78=0,0,IF(AN13="",0,AN13)) -> 0 | M78: =E78+I78 -> 0 | Q78: =IF(AE63>0,AE63,0) -> 0 | T78: =IF(AC63>0,AC63,0) -> 0 | W78: =T78-Q78 -> 0 | AB78: Arrears Received | AC78: =IF(AN16="","",AN16) -> 0 | AD78: Arrears Received | AE78: 0
B79: 2015-16 | E79: =IF(AM16="",0,AM16) -> 0 | I79: =IF(E79=0,0,IF(AN16="",0,AN16)) -> 0 | M79: =E79+I79 -> 0 | Q79: =IF(AE88>0,AE88,0) -> 0 | T79: =IF(AC88>0,AC88,0) -> 0 | W79: =T79-Q79 -> 0 | AB79: Total Taxable Income | AC79: =SUM(AC77:AC78) -> 0 | AD79: Total Taxable Income | AE79: =SUM(AE77:AE78) -> 0
B80: Total | E80: =SUM(E74:H79) -> 0 | I80: =SUM(I74:L79) -> 0 | M80: =SUM(M74:P79) -> 0 | Q80: =SUM(Q74:S79) -> 0 | T80: =SUM(T74:V79) -> 0 | W80: =SUM(W74:Z79) -> 0 | AB80: Up to Rs. 2,50,000 | AC80: 0 | AD80: Up to Rs. 2,50,000 | AE80: 0 | AG80: =AC79-250000 -> -250000 | AH80: =IF(AG80>250000,250000,AG80) -> -250000 | AI80: =AE79-250000 -> -250000 | AJ80: =IF(AI80>250000,250000,AI80) -> -250000
AB81: Rs.2,50,001 To 5,00,000. (@ 10%) | AC81: =IF(AH80>0,AH80,0)*10% -> 0 | AD81: Rs.2,50,001 To 5,00,000. (@ 10%) | AE81: =IF(AJ80>0,AJ80,0)*10% -> 0 | AG81: =AC79-500000 -> -500000 | AH81: =IF(AG81>500000,500000,AG81) -> -500000 | AI81: =AE79-500000 -> -500000 | AJ81: =IF(AI81>500000,500000,AI81) -> -500000
AB82: Rs.5,00,001 To 10,00,000. (@ 20%) | AC82: =IF(AH81>0,AH81,0)*20% -> 0 | AD82: Rs.5,00,001 To 10,00,000. (@ 20%) | AE82: =IF(AJ81>0,AJ81,0)*20% -> 0 | AG82: =AC79-1000000 -> -1000000 | AH82: =IF(AG82>500000,500000,AG82) -> -1000000 | AI82: =AE79-1000000 -> -1000000 | AJ82: =IF(AI82>500000,500000,AI82) -> -1000000
AB83: above Rs.10,00,001. (@ 30%) | AC83: =IF(AH82>0,AH82,0)*30% -> 0 | AD83: above Rs.10,00,001. (@ 30%) | AE83: =IF(AJ82>0,AJ82,0)*30% -> 0
P84: Signature : | AB84: Tax rebate U/s 87A | AC84: =IF(AC79>500000,0,2000) -> 2000 | AD84: Tax rebate U/s 87A | AE84: =IF(AE79>500000,0,2000) -> 2000
C85: Place : | P85: Name : | AB85: Total | AC85: =IF((SUM(AC80:AC83)-AC84)>0,(SUM(AC80:AC83)-AC84),0) -> 0 | AD85: Total | AE85: =IF((SUM(AE80:AE83)-AE84)>0,(SUM(AE80:AE83)-AE84),0) -> 0
P86: Designation: | AB86: Education Cess @ 1% | AC86: =ROUND(AC85*1%,0.1) -> 0 | AD86: Education Cess @ 1% | AE86: =ROUND(AE85*1%,0.1) -> 0
C87: Date: | D87: =TODAY() -> 44553 | P87: Department: | AB87: Secondary & Higher Education Cess @ 2% | AC87: =ROUND(AC85*2%,0.1) -> 0 | AD87: Secondary & Higher Education Cess @ 2% | AE87: =ROUND(AE85*2%,0.1) -> 0
AB88: Total Tax | AC88: =SUM(AC85:AC87) -> 0 | AD88: Total Tax | AE88: =SUM(AE85:AE87) -> 0 | AF88: =AC88-AE88 -> 0
AB94: Detail | AC94: 2018-19 | AD94: Detail | AE94: 2018-19
AF95: |
AB96: Net Taxable Income | AC96: =AM15 -> 0 | AD96: Net Taxable Income | AE96: =AC96 -> 0
AB97: Arrears Received | AC97: =AN15 -> 0 | AD97: Arrears Received | AE97: 0
AB98: Total Taxable Income | AC98: =SUM(AC96:AC97) -> 0 | AD98: Total Taxable Income | AE98: =SUM(AE96:AE97) -> 0
AB99: Up to Rs. 2,50,000 | AC99: 0 | AD99: Up to Rs. 2,50,000 | AE99: 0 | AG99: =AC98-250000 -> -250000 | AH99: =IF(AG99>250000,250000,AG99) -> -250000 | AI99: =AE98-250000 -> -250000 | AJ99: =IF(AI99>250000,250000,AI99) -> -250000
AB100: Rs.2,50,001 To 5,00,000. (@ 5%) | AC100: =IF(AH99>0,AH99,0)*10% -> 0 | AD100: Rs.2,50,001 To 5,00,000. (@ 5%) | AE100: =IF(AJ99>0,AJ99,0)*10% -> 0 | AG100: =AC98-500000 -> -500000 | AH100: =IF(AG100>500000,500000,AG100) -> -500000 | AI100: =AE98-500000 -> -500000 | AJ100: =IF(AI100>500000,500000,AI100) -> -500000
AB101: Rs.5,00,001 To 10,00,000. (@ 20%) | AC101: =IF(AH100>0,AH100,0)*20% -> 0 | AD101: Rs.5,00,001 To 10,00,000. (@ 20%) | AE101: =IF(AJ100>0,AJ100,0)*20% -> 0 | AG101: =AC98-1000000 -> -1000000 | AH101: =IF(AG101>500000,500000,AG101) -> -1000000 | AI101: =AE98-1000000 -> -1000000 | AJ101: =IF(AI101>500000,500000,AI101) -> -1000000
AB102: above Rs.10,00,001. (@ 30%) | AC102: =IF(AH101>0,AH101,0)*30% -> 0 | AD102: above Rs.10,00,001. (@ 30%) | AE102: =IF(AJ101>0,AJ101,0)*30% -> 0
AB103: Tax rebate U/s 87A | AC103: =IF(AC98>500000,0,2000) -> 2000 | AD103: Tax rebate U/s 87A | AE103: =IF(AE98>500000,0,2000) -> 2000
AB104: Total | AC104: =IF((SUM(AC99:AC102)-AC103)>0,(SUM(AC99:AC102)-AC103),0) -> 0 | AD104: Total | AE104: =IF((SUM(AE99:AE102)-AE103)>0,(SUM(AE99:AE102)-AE103),0) -> 0
AB105: Health Cess @ 1% | AC105: =ROUND(AC104*1%,0.1) -> 0 | AD105: Health Cess @ 1% | AE105: =ROUND(AE104*1%,0.1) -> 0
AB106: Education Cess @ 3% | AC106: =ROUND(AC104*3%,0.1) -> 0 | AD106: Education Cess @ 3% | AE106: =ROUND(AE104*3%,0.1) -> 0
AB107: Total Tax | AC107: =SUM(AC104:AC106) -> 0 | AD107: Total Tax | AE107: =SUM(AE104:AE106) -> 0 | AF107: =AC107-AE107 -> 0
AB113: Detail | AC113: 2019-20 | AD113: Detail | AE113: 2019-20
AB115: Total income (excluding salary received in arrars or advance) | AC115: =IF(AM12="","",AM12) -> 0 | AD115: Net Taxable Income | AE115: =AC115 -> 0
AB117: Arrears Received | AC117: =IF(AN12="","",AN12) -> 0 | AD117: Arrears Received | AE117: 0
AB118: Total Taxable Income | AC118: =SUM(AC115:AC117) -> 0 | AD118: Total Taxable Income | AE118: =SUM(AE115:AE117) -> 0
AB119: Up to Rs. 5,00,000 | AC119: 0 | AD119: Up to Rs. 2,50,000 | AE119: 0
AB120: Rs.2,50,001 To 5,00,000. (@ 5%) | AC120: =IF(DATA!K50>AG124,AG125,0) -> 0 | AD120: Rs.2,50,001 To 5,00,000. (@ 5%) | AE120: =IF(DATA!K50>AG124,AG126,0) -> 0 | AG120: =AC118-250000 -> -250000 | AH120: =IF(AG120>250000,250000,AG120) -> -250000 | AI120: =AE118-250000 -> -250000 | AJ120: =IF(AI120>250000,250000,AI120) -> -250000
AB121: Rs.5,00,001 To 10,00,000. (@ 20%) | AC121: =IF(AH121>0,AH121,0)*20% -> 0 | AD121: Rs.5,00,001 To 10,00,000. (@ 20%) | AE121: =IF(AJ121>0,AJ121,0)*20% -> 0 | AG121: =AC118-500000 -> -500000 | AH121: =IF(AG121>500000,500000,AG121) -> -500000 | AI121: =AE118-500000 -> -500000 | AJ121: =IF(AI121>500000,500000,AI121) -> -500000
AB122: above Rs.10,00,001. (@ 30%) | AC122: =IF(AH122>0,AH122,0)*30% -> 0 | AD122: above Rs.10,00,001. (@ 30%) | AE122: =IF(AJ122>0,AJ122,0)*30% -> 0 | AG122: =AC118-1000000 -> -1000000 | AH122: =IF(AG122>500000,500000,AG122) -> -1000000 | AI122: =AE118-1000000 -> -1000000 | AJ122: =IF(AI122>500000,500000,AI122) -> -1000000
...

Sheet DA Table
B2: =IF(DATA!CL$274=1,"AP New DA Arrears Calculator","TS New DA Arrears Calculator") -> AP New DA Arrears Calculator
B5: Basic Pay on Jan 2022
B6: Increament Month ( After Jan 2022 )
B7: Are You Taken AAS (6/12/18/24 Years) Before Dec 2020
B8: Are You Taken Promotion (07/18 to 12/20) Before Dec 20
B9: If You Taken Surrender Leave (07/2018 to 12/2020)
B10: Select CPS / PF
B11: Select HRA %
B13: =IF(DATA!CL$274=1,"AP Teachers & Employees July 2018 - 30.392% ","TS Teachers & Employees July 2019 - 38.776% ") -> AP Teachers & Employees July 2018 - 30.392%
B15: Month & Year | C15: Basic Pay | D15: Eligible DA | E15: Already Drawn DA | F15: DA Defference | G15: =IF(V190=T154,"CPS Adjustment 10%","PF Adjustment") -> PF Adjustment | H15: =IF(V190=T154,"CPS Cash 90%","PF Cash") -> PF Cash
B16: =IF(DATA!CL$274=1,"July 2018 DA","Jan 2019 DA") -> July 2018 DA | D16: =IF(DATA!CL$274=1,"30.392%","38.776%") -> 30.392% | E16: =IF(DATA!CL$274=1,"27.248%","33.536%") -> 27.248% | F16: =D16-E16 -> 0.03144 | G16: www.teacherNews.in
B17: =IF(DATA!CL$274=1,M154,"") -> 43282 | C17: =IF(B17="","",Z198) -> 19500 | D17: =IF(B17="","",ROUND(C17*D$16,0)) -> 5926 | E17: =IF(B17="","",ROUND(C17*E$16,0)) -> 5313 | F17: =IF(B17="","",(D17-E17)) -> 613 | G17: =IF(V$190=T$154,ROUND(F17*10%,0),F17) -> 613 | H17: =IF(B17="","",(IF(V$190=T$154,ROUND(F17*90%,0),0))) -> 0
B18: =IF(DATA!CL$274=1,M155,"") -> 43313 | C18: =IF(B18="","",Z199) -> 20050 | D18: =IF(B18="","",ROUND(C18*D$16,0)) -> 6094 | E18: =IF(B18="","",ROUND(C18*E$16,0)) -> 5463 | F18: =IF(B18="","",(D18-E18)) -> 631 | G18: =IF(V$190=T$154,ROUND(F18*10%,0),F18) -> 631 | H18: =IF(B18="","",(IF(V$190=T$154,ROUND(F18*90%,0),0))) -> 0
B19: =IF(DATA!CL$274=1,M156,"") -> 43344 | C19: =IF(B19="","",Z200) -> 20050 | D19: =IF(B19="","",ROUND(C19*D$16,0)) -> 6094 | E19: =IF(B19="","",ROUND(C19*E$16,0)) -> 5463 | F19: =IF(B19="","",(D19-E19)) -> 631 | G19: =IF(V$190=T$154,ROUND(F19*10%,0),F19) -> 631 | H19: =IF(B19="","",(IF(V$190=T$154,ROUND(F19*90%,0),0))) -> 0
B20: =IF(DATA!CL$274=1,M157,"") -> 43374 | C20: =IF(B20="","",Z201) -> 20050 | D20: =IF(B20="","",ROUND(C20*D$16,0)) -> 6094 | E20: =IF(B20="","",ROUND(C20*E$16,0)) -> 5463 | F20: =IF(B20="","",(D20-E20)) -> 631 | G20: =IF(V$190=T$154,ROUND(F20*10%,0),F20) -> 631 | H20: =IF(B20="","",(IF(V$190=T$154,ROUND(F20*90%,0),0))) -> 0
B21: =IF(DATA!CL$274=1,M158,"") -> 43405 | C21: =IF(B21="","",Z202) -> 20050 | D21: =IF(B21="","",ROUND(C21*D$16,0)) -> 6094 | E21: =IF(B21="","",ROUND(C21*E$16,0)) -> 5463 | F21: =IF(B21="","",(D21-E21)) -> 631 | G21: =IF(V$190=T$154,ROUND(F21*10%,0),F21) -> 631 | H21: =IF(B21="","",(IF(V$190=T$154,ROUND(F21*90%,0),0))) -> 0
B22: =IF(DATA!CL$274=1,M159,"") -> 43435 | C22: =IF(B22="","",Z203) -> 20050 | D22: =IF(B22="","",ROUND(C22*D$16,0)) -> 6094 | E22: =IF(B22="","",ROUND(C22*E$16,0)) -> 5463 | F22: =IF(B22="","",(D22-E22)) -> 631 | G22: =IF(V$190=T$154,ROUND(F22*10%,0),F22) -> 631 | H22: =IF(B22="","",(IF(V$190=T$154,ROUND(F22*90%,0),0))) -> 0
B23: =IF(DATA!CL$274=1,M160,"") -> 43466 | C23: =IF(B23="","",Z204) -> 20050 | D23: =IF(B23="","",ROUND(C23*D$16,0)) -> 6094 | E23: =IF(B23="","",ROUND(C23*E$16,0)) -> 5463 | F23: =IF(B23="","",(D23-E23)) -> 631 | G23: =IF(V$190=T$154,ROUND(F23*10%,0),F23) -> 631 | H23: =IF(B23="","",(IF(V$190=T$154,ROUND(F23*90%,0),0))) -> 0
B24: =IF(DATA!CL$274=1,M161,"") -> 43497 | C24: =IF(B24="","",Z205) -> 20050 | D24: =IF(B24="","",ROUND(C24*D$16,0)) -> 6094 | E24: =IF(B24="","",ROUND(C24*E$16,0)) -> 5463 | F24: =IF(B24="","",(D24-E24)) -> 631 | G24: =IF(V$190=T$154,ROUND(F24*10%,0),F24) -> 631 | H24: =IF(B24="","",(IF(V$190=T$154,ROUND(F24*90%,0),0))) -> 0
B25: =IF(DATA!CL$274=1,M162,"") -> 43525 | C25: =IF(B25="","",Z206) -> 20050 | D25: =IF(B25="","",ROUND(C25*D$16,0)) -> 6094 | E25: =IF(B25="","",ROUND(C25*E$16,0)) -> 5463 | F25: =IF(B25="","",(D25-E25)) -> 631 | G25: =IF(V$190=T$154,ROUND(F25*10%,0),F25) -> 631 | H25: =IF(B25="","",(IF(V$190=T$154,ROUND(F25*90%,0),0))) -> 0
B26: =IF(DATA!CL$274=1,M163,"") -> 43556 | C26: =IF(B26="","",Z207) -> 20050 | D26: =IF(B26="","",ROUND(C26*D$16,0)) -> 6094 | E26: =IF(B26="","",ROUND(C26*E$16,0)) -> 5463 | F26: =IF(B26="","",(D26-E26)) -> 631 | G26: =IF(V$190=T$154,ROUND(F26*10%,0),F26) -> 631 | H26: =IF(B26="","",(IF(V$190=T$154,ROUND(F26*90%,0),0))) -> 0
B27: =IF(DATA!CL$274=1,M164,"") -> 43586 | C27: =IF(B27="","",Z208) -> 20050 | D27: =IF(B27="","",ROUND(C27*D$16,0)) -> 6094 | E27: =IF(B27="","",ROUND(C27*E$16,0)) -> 5463 | F27: =IF(B27="","",(D27-E27)) -> 631 | G27: =IF(V$190=T$154,ROUND(F27*10%,0),F27) -> 631 | H27: =IF(B27="","",(IF(V$190=T$154,ROUND(F27*90%,0),0))) -> 0
B28: =IF(DATA!CL$274=1,M165,"") -> 43617 | C28: =IF(B28="","",Z209) -> 20050 | D28: =IF(B28="","",ROUND(C28*D$16,0)) -> 6094 | E28: =IF(B28="","",ROUND(C28*E$16,0)) -> 5463 | F28: =IF(B28="","",(D28-E28)) -> 631 | G28: =IF(V$190=T$154,ROUND(F28*10%,0),F28) -> 631 | H28: =IF(B28="","",(IF(V$190=T$154,ROUND(F28*90%,0),0))) -> 0
B29: 43647 | C29: =Z210 -> 20050 | D29: =ROUND(C29*D$16,0) -> 6094 | E29: =ROUND(C29*E$16,0) -> 5463 | F29: =D29-E29 -> 631 | G29: =IF(V$190=T$154,ROUND(F29*10%,0),F29) -> 631 | H29: =IF(V$190=T$154,ROUND(F29*90%,0),0) -> 0
B30: 43678 | C30: =Z211 -> 20640 | D30: =ROUND(C30*D$16,0) -> 6273 | E30: =ROUND(C30*E$16,0) -> 5624 | F30: =D30-E30 -> 649 | G30: =IF(V$190=T$154,ROUND(F30*10%,0),F30) -> 649 | H30: =IF(V$190=T$154,ROUND(F30*90%,0),0) -> 0
B31: 43709 | C31: =Z212 -> 20640 | D31: =ROUND(C31*D$16,0) -> 6273 | E31: =ROUND(C31*E$16,0) -> 5624 | F31: =D31-E31 -> 649 | G31: =IF(V$190=T$154,ROUND(F31*10%,0),F31) -> 649 | H31: =IF(V$190=T$154,ROUND(F31*90%,0),0) -> 0
B32: 43739 | C32: =Z213 -> 20640 | D32: =ROUND(C32*D$16,0) -> 6273 | E32: =ROUND(C32*E$16,0) -> 5624 | F32: =D32-E32 -> 649 | G32: =IF(V$190=T$154,ROUND(F32*10%,0),F32) -> 649 | H32: =IF(V$190=T$154,ROUND(F32*90%,0),0) -> 0
B33: 43770 | C33: =Z214 -> 20640 | D33: =ROUND(C33*D$16,0) -> 6273 | E33: =ROUND(C33*E$16,0) -> 5624 | F33: =D33-E33 -> 649 | G33: =IF(V$190=T$154,ROUND(F33*10%,0),F33) -> 649 | H33: =IF(V$190=T$154,ROUND(F33*90%,0),0) -> 0
B34: 43800 | C34: =Z215 -> 20640 | D34: =ROUND(C34*D$16,0) -> 6273 | E34: =ROUND(C34*E$16,0) -> 5624 | F34: =D34-E34 -> 649 | G34: =IF(V$190=T$154,ROUND(F34*10%,0),F34) -> 649 | H34: =IF(V$190=T$154,ROUND(F34*90%,0),0) -> 0
B35: 43831 | C35: =Z216 -> 20640 | D35: =ROUND(C35*D$16,0) -> 6273 | E35: =ROUND(C35*E$16,0) -> 5624 | F35: =D35-E35 -> 649 | G35: =IF(V$190=T$154,ROUND(F35*10%,0),F35) -> 649 | H35: =IF(V$190=T$154,ROUND(F35*90%,0),0) -> 0
B36: 43862 | C36: =Z217 -> 20640 | D36: =ROUND(C36*D$16,0) -> 6273 | E36: =ROUND(C36*E$16,0) -> 5624 | F36: =D36-E36 -> 649 | G36: =IF(V$190=T$154,ROUND(F36*10%,0),F36) -> 649 | H36: =IF(V$190=T$154,ROUND(F36*90%,0),0) -> 0
B37: 43891 | C37: =Z218 -> 20640 | D37: =ROUND(C37*D$16,0) -> 6273 | E37: =ROUND(C37*E$16,0) -> 5624 | F37: =D37-E37 -> 649 | G37: =IF(V$190=T$154,ROUND(F37*10%,0),F37) -> 649 | H37: =IF(V$190=T$154,ROUND(F37*90%,0),0) -> 0
B38: 43922 | C38: =Z219 -> 20640 | D38: =ROUND(C38*D$16,0) -> 6273 | E38: =ROUND(C38*E$16,0) -> 5624 | F38: =D38-E38 -> 649 | G38: =IF(V$190=T$154,ROUND(F38*10%,0),F38) -> 649 | H38: =IF(V$190=T$154,ROUND(F38*90%,0),0) -> 0
B39: 43952 | C39: =Z220 -> 20640 | D39: =ROUND(C39*D$16,0) -> 6273 | E39: =ROUND(C39*E$16,0) -> 5624 | F39: =D39-E39 -> 649 | G39: =IF(V$190=T$154,ROUND(F39*10%,0),F39) -> 649 | H39: =IF(V$190=T$154,ROUND(F39*90%,0),0) -> 0
B40: 43983 | C40: =Z221 -> 20640 | D40: =ROUND(C40*D$16,0) -> 6273 | E40: =ROUND(C40*E$16,0) -> 5624 | F40: =D40-E40 -> 649 | G40: =IF(V$190=T$154,ROUND(F40*10%,0),F40) -> 649 | H40: =IF(V$190=T$154,ROUND(F40*90%,0),0) -> 0
... B44: 44105 | C44: =Z225 -> 21230 | D44: =ROUND(C44*D$16,0) -> 6452 | E44: =ROUND(C44*E$16,0) -> 5785 | F44: =D44-E44 -> 667 | G44: =IF(V$190=T$154,ROUND(F44*10%,0),F44) -> 667 | H44: =IF(V$190=T$154,ROUND(F44*90%,0),0) -> 0
B45: =IF(DATA!CL$274=1,"Nov-20","") -> Nov-20 | C45: =IF(B45="","",Z226) -> 21230 | D45: =IF(B45="","",ROUND(C45*D$16,0)) -> 6452 | E45: =IF(B45="","",ROUND(C45*E$16,0)) -> 5785 | F45: =IF(B45="","",D45-E45) -> 667 | G45: =IF(V$190=T$154,ROUND(F45*10%,0),F45) -> 667 | H45: =IF(B45="","",(IF(V$190=T$154,ROUND(F45*90%,0),0))) -> 0
B46: =IF(DATA!CL$274=1,"Dec-20","") -> Dec-20 | C46: =IF(B46="","",Z227) -> 21230 | D46: =IF(B46="","",ROUND(C46*D$16,0)) -> 6452 | E46: =IF(B46="","",ROUND(C46*E$16,0)) -> 5785 | F46: =IF(B46="","",D46-E46) -> 667 | G46: =IF(V$190=T$154,ROUND(F46*10%,0),F46) -> 667 | H46: =IF(B46="","",(IF(V$190=T$154,ROUND(F46*90%,0),0))) -> 0
B47: =IF(DATA!CL$274=1,"Jan-21","") -> Jan-21 | C47: =IF(B47="","",Z228) -> 21230 | D47: =IF(B47="","",ROUND(C47*D$16,0)) -> 6452 | E47: =IF(B47="","",ROUND(C47*E$16,0)) -> 5785 | F47: =IF(B47="","",D47-E47) -> 667 | G47: =IF(V$190=T$154,ROUND(F47*10%,0),F47) -> 667 | H47: =IF(B47="","",(IF(V$190=T$154,ROUND(F47*90%,0),0))) -> 0 | I47: =IF(DATA!CL$274=1,"Cash","") -> Cash
B48: Total | C48: =SUM(C17:C46) -> 613930 | D48: =SUM(D17:D46) -> 186590 | E48: =SUM(E17:E46) -> 167282 | F48: =SUM(F17:F46) -> 19308 | G48: =SUM(G17:G46) -> 19308 | H48: =SUM(H17:H46) -> 0
B50: DA Table Developed by C.Ramanjaneyulu -www.teacherNews.in
B52: AAS Arrears from | D52: =IF(X255="","",X256) -> #VALUE! | E52: =IF(X255="","","to") -> to | F52: =IF(X255="","",X257) -> 43769 | G52: =IF(X255="","",CONCATENATE("(",Z257," Days",")")) -> #VALUE! | H52: =IF(X255="","",I52) -> #N/A | I52: =CONCATENATE("Rs. ",Y258) -> #N/A
B53: Surrender Leave Arrears Month of | F53: =W189 | G53: =IF(F53="","",V189) | H53: =IF(F53="","",CONCATENATE("Rs. ",Z251))
B54: Ist Instalment | D54: =SUM(G17:G26) -> 6292 | F54: 2nd Instalment | H54: =SUM(G27:G36) -> 6436
B55: =IF(DATA!CL$274=1,"Jan 2021 Month Salary with New DA","Nov 2020 Month Salary with New DA") -> Jan 2021 Month Salary with New DA | D55: Bassic Pay | E55: DA | F55: IR | G55: HRA | H55: Total
D56: =IF(DATA!CL$274=1,Z228,Z226) -> 21230 | E56: =ROUND(D56*D16,0) -> 6452 | F56: =ROUND(D56*27%,0) -> 5732 | G56: =ROUND(D56*V192,0) -> 2548 | H56: =SUM(D56:G56) -> 35962
B57: Visit More Employees Softwares at www.teacherNews.in (C Ramanjaneyulu)
K153: 1 | L153: Select
K154: 2 | L154: 43313 | M154: 43282 | N154: 1 | O154: 13000 | P154: 13390 | Q154: 13000 | R154: 13780 | S154: 43313 | T154: CPS | U154: No | V154: Yes | W154: 12 | X154: Jan | Y154: One DA | Z154: 1 | AA154: One Inc.
K155: 3 | L155: 43344 | M155: 43313 | N155: 2 | O155: 13390 | P155: 13780 | Q155: 13390 | R155: 14170 | S155: 43344 | T155: PF | U155: 15 Days | V155: No | W155: 14.5 | X155: Feb | Y155: Two DA | Z155: 2 | AA155: Two Inc.
K156: 4 | L156: 43374 | M156: 43344 | N156: 3 | O156: 13780 | P156: 14170 | Q156: 13780 | R156: 14600 | S156: 43374 | U156: 30 Days | W156: 20 | X156: Mar | Z156: 3
K157: 5 | L157: 43405 | M157: 43374 | N157: 4 | O157: 14170 | P157: 14600 | Q157: 14170 | R157: 15030 | S157: 43405 | V157: 1 | W157: 30 | X157: Apr | Z157: 4
K158: 6 | L158: 43435 | M158: 43405 | N158: 5 | O158: 14600 | P158: 15030 | Q158: 14600 | R158: 15460 | S158: 43435 | T158: 2 | V158: =VLOOKUP(V157,N154:V155,9,FALSE) -> Yes | X158: May | Z158: 5 | AA158: 1
K159: 7 | L159: 43466 | M159: 43435 | N159: 6 | O159: 15030 | P159: 15460 | Q159: 15030 | R159: 15930 | S159: 43466 | W159: 1 | X159: Jun | Z159: 6
K160: 8 | L160: 43497 | M160: 43466 | N160: 7 | O160: 15460 | P160: 15930 | Q160: 15460 | R160: 16400 | S160: 43497 | T160: =VLOOKUP(T158,N154:T155,7,FALSE) -> PF | U160: 1 | V160: 2 | W160: =VLOOKUP(W159,N154:W157,10,FALSE) -> 12 | X160: Jul | Z160: 7 | AA160: =IF(AA158=1,VLOOKUP(AD188,O154:P230,2,FALSE),AD188) -> 61450
K161: 9 | L161: 43525 | M161: 43497 | N161: 8 | O161: 15930 | P161: 16400 | Q161: 15930 | R161: 16870 | S161: 43525 | U161: =VLOOKUP(U160,N154:U156,8,FALSE) -> No | V161: =VLOOKUP(V160,N154:V155,9,FALSE) -> No | W161: 1 | X161: Aug | Y161: 43313 | Z161: 8 | AA161: =IF(AA158=2,AD188,VLOOKUP(AD188,Q154:R230,2,FALSE)) -> 63010
K162: 10 | L162: 43556 | M162: 43525 | N162: 9 | O162: 16400 | P162: 16870 | Q162: 16400 | R162: 17380 | S162: 43556 | W162: 2 | X162: Sep | Y162: 43344 | Z162: 9
K163: 11 | L163: 43586 | M163: 43556 | N163: 10 | O163: 16870 | P163: 17380 | Q163: 16870 | R163: 17890 | S163: 43586 | W163: 3 | X163: Oct | Y163: 43374 | Z163: 10
K164: 12 | L164: 43617 | M164: 43586 | N164: 11 | O164: 17380 | P164: 17890 | Q164: 17380 | R164: 18400 | S164: 43617 | W164: 4 | X164: Nov | Y164: 43405 | Z164: 11
K165: 13 | L165: 43647 | M165: 43617 | N165: 12 | O165: 17890 | P165: 18400 | Q165: 17890 | R165: 18950 | S165: 43647 | W165: 5 | X165: Dec | Y165: 43435 | Z165: 12
K166: 14 | L166: 43678 | M166: 43647 | N166: 13 | O166: 18400 | P166: 18950 | Q166: 18400 | R166: 19500 | S166: 43678 | V166: 2 | W166: 6 | X166: Jan | Y166: 43466 | Z166: 13
K167: 15 | L167: 43709 | M167: 43678 | N167: 14 | O167: 18950 | P167: 19500 | Q167: 18950 | R167: 20050 | S167: 43709 | V167: =VLOOKUP(V166,N154:V155,9,FALSE) -> No | W167: 7 | X167: Feb | Y167: 43497 | Z167: 14
K168: 16 | L168: 43739 | M168: 43709 | N168: 15 | O168: 19500 | P168: 20050 | Q168: 19500 | R168: 20640 | S168: 43739 | W168: 8 | X168: Mar | Y168: 43525 | Z168: 15
K169: 17 | L169: 43770 | M169: 43739 | N169: 16 | O169: 20050 | P169: 20640 | Q169: 20050 | R169: 21230 | S169: 43770 | W169: 9 | X169: Apr | Y169: 43556 | Z169: 16
K170: 18 | L170: 43800 | M170: 43770 | N170: 17 | O170: 20640 | P170: 21230 | Q170: 20640 | R170: 21820 | S170: 43800 | W170: 10 | X170: May | Y170: 43586 | Z170: 17
K171: 19 | L171: 43831 | M171: 43800 | N171: 18 | O171: 21230 | P171: 21820 | Q171: 21230 | R171: 22840 | S171: 43831 | W171: 11 | X171: Jun | Y171: 43617 | Z171: 18
K172: 20 | L172: 43862 | M172: 43831 | N172: 19 | O172: 21820 | P172: 22840 | Q172: 21820 | R172: 23100 | S172: 43862 | W172: 12 | X172: Jul | Y172: 43647 | Z172: 19
K173: 21 | L173: 43891 | M173: 43862 | N173: 20 | O173: 22840 | P173: 23100 | Q173: 22840 | R173: 23740 | S173: 43891 | Z173: 20
K174: 22 | L174: 43922 | M174: 43891 | N174: 21 | O174: 23100 | P174: 23740 | Q174: 23100 | R174: 24440 | S174: 43922 | X174: 1 | Z174: 21
K175: 23 | L175: 43952 | M175: 43922 | N175: 22 | O175: 23740 | P175: 24440 | Q175: 23740 | R175: 25140 | S175: 43952 | X175: =VLOOKUP(X174,W161:X172,2,FALSE) -> Aug | Z175: 22
K176: 24 | L176: 43983 | M176: 43952 | N176: 23 | O176: 24440 | P176: 25140 | Q176: 24440 | R176: 25840 | S176: 43983 | X176: =VLOOKUP(X175,X161:Y172,2,FALSE) -> 43313 | Z176: 23
K177: 25 | L177: 44013 | M177: 43983 | N177: 24 | O177: 25140 | P177: 25840 | Q177: 25140 | R177: 26600 | S177: 44013 | Z177: 24
K178: 26 | L178: 44044 | M178: 44013 | N178: 25 | O178: 25840 | P178: 26600 | Q178: 25840 | R178: 27360 | S178: 44044 | Z178: 25
K179: 27 | L179: 44075 | M179: 44044 | N179: 26 | O179: 26600 | P179: 27360 | Q179: 26600 | R179: 28120 | S179: 44075 | Z179: 26
K180: 28 | L180: 44105 | M180: 44075 | N180: 27 | O180: 27360 | P180: 28120 | Q180: 27360 | R180: 28940 | S180: 44105 | Z180: 27
K181: 29 | L181: 44136 | M181: 44105 | N181: 28 | O181: 28120 | P181: 28940 | Q181: 28120 | R181: 29760 | S181: 44136 | Z181: 28
K182: 30 | L182: 44166 | M182: 44136 | N182: 29 | O182: 28940 | P182: 29760 | Q182: 28940 | R182: 30580 | S182: 44166 | Z182: 29
L183: 44197 | M183: 44166 | N183: 30 | O183: 29760 | P183: 30580 | Q183: 29760 | R183: 31460 | S183: 44197 | Z183: 30
L184: 44228 | M184: 44562 | N184: 31 | O184: 30580 | P184: 31460 | Q184: 30580 | R184: 32340 | S184: 44593 | Z184: 50
K185: 14 | N185: 32 | O185: 31460 | P185: 32340 | Q185: 31460 | R185: 33220
K186: AAS | L186: 16 | N186: 33 | O186: 32340 | P186: 33220 | Q186: 32340 | R186: 34170 | U186: 2022 | V186: =VLOOKUP(O233,N154:O230,2,FALSE) -> 56870 | W186: =CONCATENATE(V187,"-",U186) -> Aug-2022 | AB186: 44562 | AC186: 22 | AI186: =O234 -> 56870
L187: =VLOOKUP(L186,K153:L182,2,FALSE) -> 43739 | N187: 34 | O187: 33220 | P187: 34170 | Q187: 33220 | R187: 35120 | U187: Inc. | V187: =X175 -> Aug | W187: =MONTH(W186) -> 8 | X187: =W187-1 -> 7 | Y187: =DATA!BA141 -> 7 | Z187: 44592 | AB187: Inc. | AC187: =X176 -> 43313 | AD187: =VLOOKUP(AI186,O154:P230,2,FALSE) -> 58330 | AE187: =SMALL(AC187:AC189,1) -> 43313 | AI187: =VLOOKUP(AI186,O154:P230,2,FALSE) -> 58330
L188: =IF(L187=L153,"",L187) -> 43739 | N188: 35 | O188: 34170 | P188: 35120 | Q188: 34170 | R188: 36070 | U188: AAS | V188: =V158 -> Yes | W188: =Z188 -> 43739 | Y188: =K186 -> AAS | Z188: =IF(AA188="","",IF(V188=V154,AA188,Z187)) -> 43739 | AA188: =L188 -> 43739 | AB188: AAS | AC188: =L189 -> 43739 | AD188: =IF(L186=1,AD187,VLOOKUP(AD187,O154:P230,2,FALSE)) -> 59890 | AE188: =SMALL(AC187:AC189,2) -> 43647
L189: =IF(L187=L153,AB186,L187) -> 43739 | N189: 36 | O189: 35120 | P189: 36070 | Q189: 35120 | R189: 37100 | U189: SL | V189: =U161 -> No | W189: =IF(U160=1,"",L191) | X189: =DATA!AU189 -> 42736 | Y189: =VLOOKUP(X189,M154:S184,6,TRUE) -> #N/A | AB189: Pro | AC189: =L197 -> 43647 | AD189: =IF(AND(L194=1,AA158=1),VLOOKUP(AD188,O154:P230,2,FALSE),IF(AND(L194=1,AA158=2),VLOOKUP(AD188,Q154:R230,2,FALSE),AD188)) -> 59890 | AE189: =SMALL(AC187:AC189,3) -> 43739
K190: SL | L190: 1 | N190: 37 | O190: 36070 | P190: 37100 | Q190: 36070 | R190: 38130 | U190: PF/CPS | V190: =T160 -> PF | X190: =VLOOKUP(W188,S154:Z184,8,TRUE) -> 15 | Y190: =X190-1 -> 14
L191: =VLOOKUP(L190,K153:L183,2,FALSE) -> Select | N191: 38 | O191: 37100 | P191: 38130 | Q191: 37100 | R191: 39160 | U191: HRA | V191: =W160 -> 12
L192: =IF(L191=L153,"",L191) | N192: 39 | O192: 38130 | P192: 39160 | Q192: 38130 | R192: 40270 | V192: =CONCATENATE(V191,"%") -> 12%
L193: =IF(L191=L153,AB186,L191) -> 44562 | N193: 40 | O193: 39160 | P193: 40270 | Q193: 39160 | R193: 41380 | V193: =DATA!CL$274 -> 1 | Z193: 43282 | AA193: 0.27248 | AB193: 0.30392 | AC193: =AB193-AA193 -> 0.03144
K194: Pro | L194: 13 | N194: 41 | O194: 40270 | P194: 41380 | Q194: 40270 | R194: 42490 | U194: Promotion | V194: =AA158 -> 1 | Z194: 43466 | AA194: 0.30392 | AB194: 0.33536 | AC194: =AB194-AA194 -> 0.03144
L195: =VLOOKUP(L194,K153:L183,2,FALSE) -> 43647 | N195: 42 | O195: 41380 | P195: 42490 | Q195: 41380 | R195: 43680
L196: =IF(L195=L153,"",L195) -> 43647 | N196: 43 | O196: 42490 | P196: 43680 | Q196: 42490 | R196: 44870
L197: =IF(L195=L153,AB186,L195) -> 43647 | N197: 44 | O197: 43680 | P197: 44870 | Q197: 43680 | R197: 46060 | Y197: =IF(X198<=X$189,VLOOKUP(V198,P$154:Q$231,2,TRUE),V198) -> 19500 | AA197: 43282 | AB197: 43466
N198: 45 | O198: 44870 | P198: 46060 | Q198: 44870 | R198: 47330 | U198: 7 | V198: =IF(U198=Y187,VLOOKUP(V199,P154:Q231,2,TRUE),V199) -> 19500 | W198: 0 | X198: 43282 | Y198: =IF(X198<=X$189,VLOOKUP(V198,P$154:Q$231,2,TRUE),V198) -> 19500 | Z198: =IF(V$188=V$154,Y198,V198) -> 19500 | AA198: =ROUND(Z198*AC$193,0) -> 613
N199: 46 | O199: 46060 | P199: 47330 | Q199: 46060 | R199: 48600 | U199: 8 | V199: =IF(U199=Y187,VLOOKUP(V200,P154:Q231,2,TRUE),V200) -> 20050 | W199: 1 | X199: 43313 | Y199: =IF(X199<=X$189,VLOOKUP(V199,P$154:Q$231,2,TRUE),V199) -> 20050 | Z199: =IF(V$188=V$154,Y199,V199) -> 20050 | AA199: =ROUND(Z199*AC$193,0) -> 630
N200: 47 | O200: 47330 | P200: 48600 | Q200: 47330 | R200: 49870 | U200: 9 | V200: =IF(U200=Y187,VLOOKUP(V201,P154:Q231,2,TRUE),V201) -> 20050 | W200: 2 | X200: 43344 | Y200: =IF(X200<=X$189,VLOOKUP(V200,P$154:Q$231,2,TRUE),V200) -> 20050 | Z200: =IF(V$188=V$154,Y200,V200) -> 20050 | AA200: =ROUND(Z200*AC$193,0) -> 630
N201: 48 | O201: 48600 | P201: 49870 | Q201: 48600 | R201: 51230 | U201: 10 | V201: =IF(U201=Y187,VLOOKUP(V202,P154:Q231,2,TRUE),V202) -> 20050 | W201: 3 | X201: 43374 | Y201: =IF(X201<=X$189,VLOOKUP(V201,P$154:Q$231,2,TRUE),V201) -> 20050 | Z201: =IF(V$188=V$154,Y201,V201) -> 20050 | AA201: =ROUND(Z201*AC$193,0) -> 630
N202: 49 | O202: 49870 | P202: 51230 | Q202: 49870 | R202: 52590 | U202: 11 | V202: =IF(U202=Y187,VLOOKUP(V203,P154:Q231,2,TRUE),V203) -> 20050 | W202: 4 | X202: 43405 | Y202: =IF(X202<=X$189,VLOOKUP(V202,P$154:Q$231,2,TRUE),V202) -> 20050 | Z202: =IF(V$188=V$154,Y202,V202) -> 20050 | AA202: =ROUND(Z202*AC$193,0) -> 630
N203: 50 | O203: 51230 | P203: 52590 | Q203: 51230 | R203: 53950 | U203: 12 | V203: =IF(U203=Y187,VLOOKUP(V204,P154:Q231,2,TRUE),V204) -> 20050 | W203: 5 | X203: 43435 | Y203: =IF(X203<=X$189,VLOOKUP(V203,P$154:Q$231,2,TRUE),V203) -> 20050 | Z203: =IF(V$188=V$154,Y203,V203) -> 20050 | AA203: =ROUND(Z203*AC$193,0) -> 630
N204: 51 | O204: 52590 | P204: 53950 | Q204: 52590 | R204: 55410 | U204: 1 | V204: =IF(U204=Y187,VLOOKUP(V205,P154:Q231,2,TRUE),V205) -> 20050 | W204: 6 | X204: 43466 | Y204: =IF(X204<=X$189,VLOOKUP(V204,P$154:Q$231,2,TRUE),V204) -> 20050 | Z204: =IF(V$188=V$154,Y204,V204) -> 20050 | AA204: =ROUND(Z204*AC$193,0) -> 630 | AB204: =ROUND(Z204*AC$194,0) -> 630
N205: 52 | O205: 53950 | P205: 55410 | Q205: 53950 | R205: 56870 | U205: 2 | V205: =IF(U205=Y187,VLOOKUP(V206,P154:Q231,2,TRUE),V206) -> 20050 | W205: 7 | X205: 43497 | Y205: =IF(X205<=X$189,VLOOKUP(V205,P$154:Q$231,2,TRUE),V205) -> 20050 | Z205: =IF(V$188=V$154,Y205,V205) -> 20050 | AA205: =ROUND(Z205*AC$193,0) -> 630 | AB205: =ROUND(Z205*AC$194,0) -> 630
...

Sheet Rent Receipt
C4: RECEIPT OF HOUSE RENT
C5: (Under Section 1 (13-A) of Income Tax Act )
F8: =IF(DATA!AH49=1,"","Received a sum of House Rent 12 months amount ") -> Received a sum of House Rent 12 months amount | T8: =DATA!S11 -> 12000
C9: =IF(DATA!AH49=1,"","from") -> from | E9: =IF(DATA!AH49=1,"",CONCATENATE('Annexure -I I'!D6)) -> Sri. A.Nagesh | J9: =IF(DATA!AH49=1,"","(Tenant) Rs.") -> (Tenant) Rs. | L9: =IF(DATA!AH49=1,"",F11*12) -> 144000 | T9: =T8*12 -> 144000
C10: =IF(DATA!AH49=1,"","Amount in words") -> Amount in words | F10: =IF(DATA!AH49=1,"",DATA!CC229) -> One Lakh Fourty Four Thousands and only
C11: =IF(DATA!AH49=1,"","towards the rent @") -> towards the rent @ | F11: =IF(DATA!AH49=1,"",DATA!S11) -> 12000 | H11: =IF(DATA!AH49=1,"","Per Month during the financial year") -> Per Month during the financial year
C12: =IF(DATA!AH49=1,"",S45) -> in respect of House No: 13-254/ A, Near Bus Stand, Peapully, Peapully (Mandal), Kurnool (Dt.).
C16: Owner's and Address :
C18: Name: | E18: =DATA!O50 -> K Suresh
C20: Address: | E20: =CONCATENATE(DATA!Q45,", ",DATA!Q46) -> 13-254/ A, Near Bus Stand
E21: =CONCATENATE(DATA!Q47,", ",DATA!Q48,"( Mandal)") -> Peapully, Peapully( Mandal)
E22: =CONCATENATE(DATA!Q49," ","( District)") -> Kurnool ( District)
C23: PAN No: | E23: =DATA!S50 -> xxxxxxxxx
K28: (Affix Revenue Stamp of Rs.1/-)
D33: Signature of the Tenant | I33: Signature of the House Owner
S45: =CONCATENATE("in respect of House No: ",DATA!Q45,", ",DATA!Q46,", ",DATA!Q47,", ",DATA!Q48," (","Mandal",")",", ",DATA!Q49," (","Dt.",")",".") -> in respect of House No: 13-254/ A, Near Bus Stand, Peapully, Peapully (Mandal), Kurnool (Dt.).
